Workbook
Name Slicer_Account_Name: #N/A
Name Slicer_Created_Date: #N/A

Sheet Guidelines
A1: Report Name | B1: Billing Profile Change History
A2: Procedure | B2: - Extract the data from "Billing Profile Change History" report for the previous week
B3: - Run the cleanup macro which will highlight the potential errors and will verify the data
B4: - Check the fields Stylistic and Formatting (abbreviated words, punctuation, entity type formatting, etc.) as per "Account Creation Best Practices" Guidelines
B5: - Update the necessary changes in the records based on the audit
B6: - Visually check the records to see if any additional potential errors in the report
A8: Validation in fields levels
A9: Account Name | B9: Run a macro which identify potential error in Account name based on the standards (abbreviated words, punctuation, entity type formatting, etc.) also will check proper casing
A10: Account Street | B10: Run a macro which identify potential error in address field based on the standards (abbreviated words, punctuation, entity type formatting, etc.) also will check proper casing
A11: Account City | B11: Check proper casing in City field
A12: Account State/Province | B12: Check proper casing in State/Province field
A13: Account Country | B13: Check for US Territories AS, FM, GU, MH, MP, PW, PR, VI, UM and relocate to Billing state field
A14: Tax ID / VAT # | B14: Check the standard format (includes county code in VAT and blank for US country etc.) for Tax ID/VAT numbers alone If Deal Desk is inserting Tax IDs that aren't VAT/CNPJ/ABN/EFN #s it's fine to leave them in. I don't think it should cause any harm.
A15: Account Contact Name | B15: Check proper casing in Bill To Contact field

Sheet Audit_Description
A1: S.No. | B1: Audit Fields | C1: Description | D1: Formula Applied in the Account Profile Audit Sheet
A2: 1 | B2: Unique_Record_Flag | C2: Filter out unique records to avoid duplicate rows | D2: =IF(G2=G1,"","Unique Record")
A3: =A2+1 -> 2 | B3: Account_Upper Case_Flag | C3: Check the Account Name to see if the value is entered in the UPPER case. | D3: =IF(F2="","",IF(EXACT(F2,(UPPER(F2))),"Account Upper Case",""))
A4: =A3+1 -> 3 | B4: Account_Lower Case__Flag | C4: Check the Account Name to see if the value is entered in the LOWER case. | D4: =IF(F2="","",IF(EXACT(F2,(LOWER(F2))),"Account Lower Case",""))
A5: =A4+1 -> 4 | B5: Billing Street_ProperCase_Flag | C5: Billing Street: check if the value doesn’t enter in the PROPER case. | D5: =IF(EXACT(H2,PROPER(H2)),"","Billing Street - casing")
A6: =A5+1 -> 5 | B6: Billing City_ProperCase_Flag | C6: Billing City: check if the value doesn’t enter in the PROPER case. | D6: =IF(EXACT(I2,PROPER(I2)),"","City - casing")
A7: =A6+1 -> 6 | B7: Billing_City_Saint_Flag | C7: Saint abbreviation (St or St.) check in city | D7: =IF(OR(ISNUMBER(SEARCH("St.",I2)),ISNUMBER(SEARCH("St ",I2))),"Check St in city field",IF(RIGHT(I2,1)=".","Dot found in city field",""))
A8: =A7+1 -> 7 | B8: Billing_City_Special_Char_Flag | C8: Symbols check in City | D8: =IF((SUMPRODUCT(--ISNUMBER(SEARCH({"!","@","#","$","%","^","&","~*","(",")","_","+","=","{","}","[","]","|","\",":",";","'","""","<",">",",",".","~?","/","~~","`"}, I2)))>0)=TRUE,"Special Characters Found in City","")
A9: =A8+1 -> 8 | B9: Account_Special_Char_Flag | C9: Symbols check in Account | D9: =IF((SUMPRODUCT(--ISNUMBER(SEARCH({"!","@","#","$","%","^","~*","(",")","_","+","=","{","}","[","]","|","\",":",";","'","""","<",">","~?","/","~~","`"},F2)))>0)=TRUE,"Special Characters Found in Account field","")
A10: =A9+1 -> 9 | B10: Address1_Directionals_Flag | C10: Check the Directional Name to see if the value is entered in the abbreviated format. | D10: =IF(SUM(--ISNUMBER(SEARCH({1,2,3,4,5,6,7,8,9,0},MID(H2,(SEARCH(" E ",H2)-1),1))))+SUM(--ISNUMBER(SEARCH({1,2,3,4,5,6,7,8,9,0},MID(H2,(SEARCH(" E ",H2)+3),1))))=2,"",IF(SUM(--ISNUMBER(SEARCH({"Parte E","Apoquindo N"},H2)))>0,"",IF(OR(RIGHT(H2,3)=" NE",RIGHT(H2,3)=" NW",RIGHT(H2,3)=" SW",RIGHT(H2,3)=" SE",RIGHT(H2,2)=" N",RIGHT(H2,2)=" E",RIGHT(H2,2)=" W",RIGHT(H2,2)=" S",LEFT(H2,3)="NE ",LEFT(H2,3)="NW ",LEFT(H2,3)="SW ",LEFT(H2,3)="SE ",LEFT(H2,2)="N ",LEFT(H2,2)="E ",LEFT(H2,2)="W ",LEFT(H2,2)="S "),"Directional Check",IF(SUM(--ISNUMBER(SEARCH({" N "," E "," W "," S "," NE "," NW "," SW "," SE ","N.E","N.W","S.W","S.E","E.","N.","S.","W."},H2)))>0,"Directional Check",IF(SUM(--ISNUMBER(SEARCH({1,2,3,4,5,6,7,8,9,0},MID(H2,(SEARCH("nd ",H2)-1),1))))+SUM(--ISNUMBER(SEARCH({1,2,3,4,5,6,7,8,9,0},MID(H2,(SEARCH("rd ",H2)-1),1)))+SUM(--ISNUMBER(SEARCH({1,2,3,4,5,6,7,8,9,0},MID(H2,(SEARCH("st ",H2)-1),1))))+SUM(--ISNUMBER(SEARCH({1,2,3,4,5,6,7,8,9,0},MID(H2,(SEARCH("th ",H2)-1),1)))))>0,"","")))))
A11: =A10+1 -> 10 | B11: State_Code_Flag | C11: Check the State codes to see if the value is entered properly based on countries. (US, CA, BR and AU should have proper abbreviated codes.) | D11: =IF(IF(L2="US",IFERROR(VLOOKUP(J2,'Country Codes'!$B:$B,1,0)=J2,"US State Code Error"),IF(L2="CA",IFERROR(VLOOKUP(J2,'Country Codes'!$E:$E,1,0)=J2,"Canada State Code Error"),IF(L2="BR",IFERROR(VLOOKUP(J2,'Country Codes'!$H:$H,1,0)=J2,"Brazil State Code Error"),IF(L2="AU",IFERROR(VLOOKUP(J2,'Country Codes'!$K:$K,1,0)=J2,"Australia State Code Error"),""))))=TRUE,"",IF(L2="US",IFERROR(VLOOKUP(J2,'Country Codes'!$B:$B,1,0)=J2,"US State Code Error"),IF(L2="CA",IFERROR(VLOOKUP(J2,'Country Codes'!$E:$E,1,0)=J2,"Canada State Code Error"),IF(L2="BR",IFERROR(VLOOKUP(J2,'Country Codes'!$H:$H,1,0)=J2,"Brazil State Code Error"),IF(L2="AU",IFERROR(VLOOKUP(J2,'Country Codes'!$K:$K,1,0)=J2,"Australia State Code Error"),"")))))
A12: =A11+1 -> 11 | B12: State_Upper_Case_Flag | C12: Check the State codes to see if the value is entered UPPER case for the countries US, CA, BR & AU and all other countries should have proper case.) | D12: =IF(OR(L2="US",L2="CA",L2="BR",L2="AU"),IF((EXACT(UPPER(J2),J2)),"","Country Code Casing"),IF(EXACT(J2,PROPER(J2)),"","Billing State casing"))
A13: =A12+1 -> 12 | B13: Address_Flag | C13: Check the City/State/PO/Countries to see if the value are entered Address 1 field | D13: =IFERROR(IFS(IF(AND(LEN(I2)=0,ISBLANK(I2)=FALSE),"",ISNUMBER(SEARCH(I2,H2))),"City/Postal Code/Country Found in Address",IF(AND(LEN(K2)=0,ISBLANK(K2)=FALSE),"",ISNUMBER(SEARCH(K2,H2))),"City/Postal Code/Country Found in Address",IF(AND(LEN(L2)=0,ISBLANK(L2)=FALSE),"",ISNUMBER(SEARCH(", "&L2,H2))),"City/Postal Code/Country Found in Address",IF(AND(LEN(J2)=0,ISBLANK(J2)=FALSE),"",ISNUMBER(SEARCH(", "&J2,H2))),"City/Postal Code/Country Found in Address",IF(AND(LEN(L2)=0,ISBLANK(L2)=FALSE),"",ISNUMBER(SEARCH(","&L2,H2))),"City/Postal Code/Country Found in Address",IF(AND(LEN(J2)=0,ISBLANK(J2)=FALSE),"",ISNUMBER(SEARCH(","&J2,H2))),"City/Postal Code/Country Found in Address"),"")
A14: =A13+1 -> 13 | B14: Incorrect_TaxID_Field_Flag | C14: Check the PO Number to see if the value is entered in Tax ID field. | D14: =IF(ISNUMBER(SEARCH("PO",N2)),"PO# Entered in Tax ID Field","")
... A20: =A19+1 -> 19 | B20: Consolidate_Error_Remarks | C20: This field combines all the above errors as a single value to perform audit | D20: =IF(S2="","",S2&"; ")&IF(T2="","",T2&"; ")&IF(U2="","",U2&"; ")&IF(V2="","",V2&"; ")&IF(AF2="","",AF2&"; ")&IF(AG2="","",AG2&"; ")&IF(AH2="","",AH2&"; ")&IF(AL2="","",AL2&"; ")&IF(Z2="","",Z2&"; ")&IF(AA2="","",AA2&"; ")&IF(AB2="","",AB2&"; ")&IF(AC2="","",AC2&"; ")&IF(AD2="","",AD2&"; ")&IF(AE2="","",AE2&"; ")&IF(AJ2="","",AJ2&"; ")&IF(AK2="","",AK2&"; ")&IF(AI2="","",AI2&"; ")&IF(W2="","",W2&"; ")&IF(X2="","",X2&"; ")&IF(Y2="","",Y2&"; ")
A21: =A20+1 -> 20 | B21: Audited_Status | C21: Enter remarks once the audit is complete for the row

Sheet Dashboard
D3: =IFERROR("Source Quality "&TEXT(G7/D7,"##.00%"),"") -> Source Quality 98.82% | R3: Pivot Table
R5: Unique_Record_Flag | S5: Unique Record
D6: Total Records | G6: Clean Records | J6: Issue Records | M6: Avg. Issue/Rec
D7: =SUM(T9:T1048576)/2 -> 931 | G7: =(SUM(T9:T1048576)/2)-(SUM(U9:U1048576)/2) -> 920 | J7: =(SUM(U9:U1048576)/2) -> 11 | M7: =(AVERAGE(U9:U1048576)/2) -> 0.012557078 | T7: Values | AA7: Values
D8: Unique Records | G8: ="Percentage: " & TEXT((COUNTIFS(Account_Profile_Audit!$R:$R,"Unique Record",Account_Profile_Audit!AJ:AJ,"")/COUNTIFS(Account_Profile_Audit!$R:$R,"Unique Record")),"#.00%") -> Percentage: 98.93% | J8: ="Percentage: " & TEXT(J7/D7,"#.00%") -> Percentage: 1.18% | M8: ="Error ratio is "&IF(M7>=0.1,"High (✖)",IF(M7>=0.05,"Medium (⚠)","Low (!)")) -> Error ratio is Low (!) | R8: Created Date | S8: Account Name | T8: Count of Account ID | U8: Sum of Total | V8: Sum of Casing | W8: Sum of Abbreviation | X8: Sum of Incorrect | Y8: Sum of Format | AA8: -Casing | AB8: 5
R9: 45315 | S9: Sample flow, inc. | T9: 4 | U9: 1 | V9: 1 | W9: 0 | X9: 0 | Y9: 0 | AA9: -Incorrect | AB9: 4
R10: 45423 | S10: SampleCo Partners | T10: 1 | U10: 0 | V10: 0 | W10: 0 | X10: 0 | Y10: 0 | AA10: -Format | AB10: 2
R11: 45424 | S11: Sample Ltd | T11: 1 | U11: 0 | V11: 0 | W11: 0 | X11: 0 | Y11: 0 | AA11: -Abbreviation | AB11: 1
R12: 45424 | S12: SampleCo, Inc. | T12: 1 | U12: 0 | V12: 0 | W12: 0 | X12: 0 | Y12: 0
R13: 45424 | S13: SampleCorp Ltd | T13: 1 | U13: 0 | V13: 0 | W13: 0 | X13: 0 | Y13: 0
R14: 45425 | S14: Sample Technologies, Inc. | T14: 1 | U14: 0 | V14: 0 | W14: 0 | X14: 0 | Y14: 0
R15: 45425 | S15: SampleCorp Technologies, Inc. | T15: 1 | U15: 0 | V15: 0 | W15: 0 | X15: 0 | Y15: 0
R16: 45426 | S16: Sample Ltd | T16: 1 | U16: 0 | V16: 0 | W16: 0 | X16: 0 | Y16: 0
R17: 45426 | S17: SampleCo Technologies, Inc. | T17: 2 | U17: 0 | V17: 0 | W17: 0 | X17: 0 | Y17: 0
R18: 45426 | S18: SampleCorp Technologies, Inc. | T18: 1 | U18: 0 | V18: 0 | W18: 0 | X18: 0 | Y18: 0
R19: 45427 | S19: SampleCorp Products, Inc. | T19: 1 | U19: 0 | V19: 0 | W19: 0 | X19: 0 | Y19: 0
R20: 45428 | S20: SampleCo Partners | T20: 1 | U20: 0 | V20: 0 | W20: 0 | X20: 0 | Y20: 0
R21: 45428 | S21: SampleCorp Partners | T21: 1 | U21: 0 | V21: 0 | W21: 0 | X21: 0 | Y21: 0
R22: 45428 | S22: SampleCorp Technologies, Inc. | T22: 1 | U22: 0 | V22: 0 | W22: 0 | X22: 0 | Y22: 0
R23: 45429 | S23: Sample Products, Inc. | T23: 2 | U23: 0 | V23: 0 | W23: 0 | X23: 0 | Y23: 0
... R883: 46149 | S883: SampleCorp Technologies, Inc. | T883: 1 | U883: 0 | V883: 0 | W883: 0 | X883: 0 | Y883: 0
R884: Grand Total | T884: 931 | U884: 11 | V884: 5 | W884: 1 | X884: 4 | Y884: 1

Sheet Account_Profile_Audit
A1: CRM Change History Report | Q1: - | R1: - | S1: Casing | T1: Casing | U1: Casing | V1: Casing | W1: Abbreviation | X1: Format | Y1: Format | Z1: Abbreviation | AA1: Incorrect | AB1: Casing | AC1: Incorrect | AD1: Incorrect | AE1: Incorrect | AF1: Format | AG1: Casing | AH1: Incorrect | AI1: Incorrect | AJ1: - | AK1: - | AL1: Error Category | AV1: Created Date | AW1: Account Name
A2: Created Date | B2: Created By | C2: Field | D2: Original Value | E2: New Value | F2: Account Name | G2: Account ID | H2: Billing Street | I2: Billing City | J2: Billing State/Province | K2: Billing Zip/Postal Code | L2: Billing Country | M2: PO Number | N2: Tax ID / VAT # | O2: Bill To Contact | P2: Billing Contact Name | Q2: - | R2: Unique_Record_Flag | S2: Account_Upper Case_Flag | T2: Account_Lower Case__Flag | U2: Billing Street_ProperCase_Flag | V2: Billing City_ProperCase_Flag | W2: Billing_City_Saint_Flag | X2: Billing_City_Special_Char_Flag | Y2: Account_Special_Char_Flag | Z2: Address1_Directionals_Flag | AA2: State_Code_Flag | AB2: State_Upper_Case_Flag | AC2: Address_Flag | AD2: Incorrect_TaxID_Field_Flag | AE2: Incorrect_PO#_Flag | AF2: Tax ID_VAT_Validation | AG2: Contact_ProperCase_Flag | AH2: US_Territories_Flag | AI2: Country_Code_Flag | AJ2: Consolidate_Error_Remarks | AK2: Audited_Status | AL2: - | AM2: Casing | AN2: Abbreviation | AO2: Incorrect | AP2: Format | AQ2: Total | AS2: Error Category | AT2: Cout | AV2: All | AW2: All
A3: 45590 | B3: User 1 | C3: PO Number | D3: PO-007496 | E3: PO-017004 | F3: Sample, Inc. | G3: ID_Num_1 | H3: Suite 30000A, Street | I3: bozeman | J3: MT | K3: 59715 | L3: US | M3: PO-017 | P3: Accounts Payable | R3: =IF(G3=G2,"","Unique Record") -> Unique Record | S3: =IF(F3="","",IF(EXACT(F3,(UPPER(F3))),"Account Upper Case","")) | T3: =IF(F3="","",IF(EXACT(F3,(LOWER(F3))),"Account Lower Case","")) | U3: =IF(EXACT(H3,PROPER(H3)),"","Billing Street - casing") | V3: =IF(EXACT(I3,PROPER(I3)),"","City - casing") -> City - casing | W3: =IF(OR(ISNUMBER(SEARCH("East",I3)),ISNUMBER(SEARCH("West",I3)),ISNUMBER(SEARCH("North",I3)),ISNUMBER(SEARCH("South",I3))),"",IF(OR(ISNUMBER(SEARCH("St.",I3)),ISNUMBER(SEARCH("St ",I3))),"Check St in city field",IF(RIGHT(I3,1)=".","Dot found in city field",""))) | X3: {=IF((SUMPRODUCT(--ISNUMBER(SEARCH({"!","@","#","$","%","^","&","~*","(",")","_","+","=","{","}","[","]","|","\",":",";","'","""","<",">",",",".","~?","/","~~","`"}, I3)))>0)=TRUE,"Special Characters Found in City","")} | Y3: {=IF((SUMPRODUCT(--ISNUMBER(SEARCH({"!","@","#","$","%","^","~*","(",")","_","+","=","{","}","[","]","|","\",":",";","'","""","<",">","~?","/","~~","`"},F3)))>0)=TRUE,"Special Characters Found in Account field","")} | Z3: {=IF(SUM(--ISNUMBER(SEARCH({1,2,3,4,5,6,7,8,9,0},MID(H3,(SEARCH(" E ",H3)-1),1))))+SUM(--ISNUMBER(SEARCH({1,2,3,4,5,6,7,8,9,0},MID(H3,(SEARCH(" E ",H3)+3),1))))=2,"",IF(SUM(--ISNUMBER(SEARCH({"Parte E","Apoquindo N"},H3)))>0,"",IF(OR(RIGHT(H3,3)=" NE",RIGHT(H3,3)=" NW",RIGHT(H3,3)=" SW",RIGHT(H3,3)=" SE",RIGHT(H3,2)=" N",RIGHT(H3,2)=" E",RIGHT(H3,2)=" W",RIGHT(H3,2)=" S",LEFT(H3,3)="NE ",LEFT(H3,3)="NW ",LEFT(H3,3)="SW ",LEFT(H3,3)="SE ",LEFT(H3,2)="N ",LEFT(H3,2)="E ",LEFT(H3,2)="W ",LEFT(H3,2)="S "),"Directional Check",IF(SUM(--ISNUMBER(SEARCH({" N "," E "," W "," S "," NE "," NW "," SW "," SE ","N.E","N.W","S.W","S.E","E.","N.","S.","W."},H3)))>0,"Directional Check",IF(SUM(--ISNUMBER(SEARCH({1,2,3,4,5,6,7,8,9,0},MID(H3,(SEARCH("nd ",H3)-1),1))))+SUM(--ISNUMBER(SEARCH({1,2,3,4,5,6,7,8,9,0},MID(H3,(SEARCH("rd ",H3)-1),1)))+SUM(--ISNUMBER(SEARCH({1,2,3,4,5,6,7,8,9,0},MID(H3,(SEARCH("st ",H3)-1),1))))+SUM(--ISNUMBER(SEARCH({1,2,3,4,5,6,7,8,9,0},MID(H3,(SEARCH("th ",H3)-1),1)))))>0,"","")))))} | AA3: =IF(IF(L3="US",IFERROR(VLOOKUP(J3,Country_Codes!$B:$B,1,0)=J3,"US State Code Error"),IF(L3="CA",IFERROR(VLOOKUP(J3,Country_Codes!$E:$E,1,0)=J3,"Canada State Code Error"),IF(L3="BR",IFERROR(VLOOKUP(J3,Country_Codes!$H:$H,1,0)=J3,"Brazil State Code Error"),IF(L3="AU",IFERROR(VLOOKUP(J3,Country_Codes!$K:$K,1,0)=J3,"Australia State Code Error"),""))))=TRUE,"",IF(L3="US",IFERROR(VLOOKUP(J3,Country_Codes!$B:$B,1,0)=J3,"US State Code Error"),IF(L3="CA",IFERROR(VLOOKUP(J3,Country_Codes!$E:$E,1,0)=J3,"Canada State Code Error"),IF(L3="BR",IFERROR(VLOOKUP(J3,Country_Codes!$H:$H,1,0)=J3,"Brazil State Code Error"),IF(L3="AU",IFERROR(VLOOKUP(J3,Country_Codes!$K:$K,1,0)=J3,"Australia State Code Error"),""))))) | AB3: =IF(OR(L3="US",L3="CA",L3="BR",L3="AU"),IF((EXACT(UPPER(J3),J3)),"","Country Code Casing"),IF(EXACT(J3,PROPER(J3)),"","Billing State casing")) | AC3: {=IFERROR(_xlfn.IFS(IF(AND(LEN(I3)=0,ISBLANK(I3)=FALSE),"",ISNUMBER(SEARCH(I3,H3))),"City/Postal Code/Country Found in Address",IF(AND(LEN(K3)=0,ISBLANK(K3)=FALSE),"",ISNUMBER(SEARCH(K3,H3))),"City/Postal Code/Country Found in Address",IF(AND(LEN(L3)=0,ISBLANK(L3)=FALSE),"",ISNUMBER(SEARCH(", "&L3,H3))),"City/Postal Code/Country Found in Address",IF(AND(LEN(J3)=0,ISBLANK(J3)=FALSE),"",ISNUMBER(SEARCH(", "&J3,H3))),"City/Postal Code/Country Found in Address",IF(AND(LEN(L3)=0,ISBLANK(L3)=FALSE),"",ISNUMBER(SEARCH(","&L3,H3))),"City/Postal Code/Country Found in Address",IF(AND(LEN(J3)=0,ISBLANK(J3)=FALSE),"",ISNUMBER(SEARCH(","&J3,H3))),"City/Postal Code/Country Found in Address"),"")} | AD3: =IF(ISNUMBER(SEARCH("PO",N3)),"PO# Entered in Tax ID Field","") | AE3: {=IFERROR(IF(VLOOKUP(LEFT(M3,MIN(SEARCH({1,2,3,4,5,6,7,8,9,0},M3&{1,2,3,4,5,6,7,8,9,0}))-1),Country_Codes!$N:$N,1,0)>0,"PO Number may be incorrect",""),"")} | AF3: =IF(N3="","",IF(EXACT(L3,LEFT(N3,2)),IF(EXACT(MID(N3,3,1)," "),"Check the Space inbetween County code & VAT",""),"Check the VAT Country Code Format")) | AG3: =IF((ISNUMBER(SEARCH("@",P3)))>0,"",IF(IF(--(ISNUMBER(SEARCH("'",P3)))>0,OR(EXACT(PROPER(P3),P3),EXACT((PROPER(LEFT(P3,FIND("'",P3)-2))&LOWER(MID(P3,FIND("'",P3)-1,1))&PROPER(MID(P3,FIND("'",P3)+0,LEN(P3)-FIND("'",P3)+1))),P3)),"Please check Billing Contact Casing")=TRUE,"","Please check Billing Contact casing")) | AH3: =IF(OR(L3="AS",L3="FM",L3="GU",L3="MH",L3="MP",L3="PW",L3="PR",L3="VI",L3="UM"),"US Territories Check","") | AI3: {=IF(G3="","",_xlfn.IFNA(_xlfn.IFS(L3=VLOOKUP(L3,Country_Codes!$M:$M,1,0)=TRUE,""),"Please check the country code"))} | AJ3: =IF(S3="","",S3&"; ")&IF(T3="","",T3&"; ")&IF(U3="","",U3&"; ")&IF(V3="","",V3&"; ")&IF(AF3="","",AF3&"; ")&IF(AG3="","",AG3&"; ")&IF(AH3="","",AH3&"; ")&IF(Z3="","",Z3&"; ")&IF(AA3="","",AA3&"; ")&IF(AB3="","",AB3&"; ")&IF(AC3="","",AC3&"; ")&IF(AD3="","",AD3&"; ")&IF(AE3="","",AE3&"; ")&IF(AI3="","",AI3&"; ")&IF(W3="","",W3&"; ")&IF(X3="","",X3&"; ")&IF(Y3="","",Y3&"; ") -> City - casing; | AM3: =(COUNTA(S3:V3)-COUNTIFS((S3:V3),""))+(COUNTA(AB3)-COUNTIFS((AB3),""))+(COUNTA(AG3)-COUNTIFS((AG3),"")) -> 1 | AN3: =(COUNTA(W3)-COUNTIFS((W3),""))+(COUNTA(Z3)-COUNTIFS((Z3),"")) -> 0 | AO3: =(COUNTA(AA3)-COUNTIFS((AA3),""))+(COUNTA(AC3:AE3)-COUNTIFS((AC3:AE3),""))+(COUNTA(AH3:AI3)-COUNTIFS((AH3:AI3),"")) -> 0 | AP3: =(COUNTA(X3:Y3)-COUNTIFS((X3:Y3),""))+(COUNTA(AF3)-COUNTIFS((AF3),"")) -> 0 | AQ3: =SUM(AM3:AP3) -> 1 | AS3: Casing | AT3: =SUM($AM:$AM) -> 5 | AV3: {=_xlfn._xlws.SORT(_xlfn.UNIQUE(A4:A1047),,1)} -> 45315 | AW3: {=_xlfn._xlws.SORT(_xlfn.UNIQUE(F4:F1047),,1)} -> Sample flow, inc.
A4: 45594 | B4: User 1 | C4: Account Name | D4: Sample Inc. | E4: Sample, Inc. | F4: Sample, Inc. | G4: ID_Num_1 | H4: Suite 30000A, Street | I4: Bozeman | J4: MT | K4: 59715 | L4: US | M4: PO-017 | P4: Accounts Payable | R4: =IF(G4=G3,"","Unique Record") | S4: =IF(F4="","",IF(EXACT(F4,(UPPER(F4))),"Account Upper Case","")) | T4: =IF(F4="","",IF(EXACT(F4,(LOWER(F4))),"Account Lower Case","")) | U4: =IF(EXACT(H4,PROPER(H4)),"","Billing Street - casing") | V4: =IF(EXACT(I4,PROPER(I4)),"","City - casing") | W4: =IF(OR(ISNUMBER(SEARCH("East",I4)),ISNUMBER(SEARCH("West",I4)),ISNUMBER(SEARCH("North",I4)),ISNUMBER(SEARCH("South",I4))),"",IF(OR(ISNUMBER(SEARCH("St.",I4)),ISNUMBER(SEARCH("St ",I4))),"Check St in city field",IF(RIGHT(I4,1)=".","Dot found in city field",""))) | X4: {=IF((SUMPRODUCT(--ISNUMBER(SEARCH({"!","@","#","$","%","^","&","~*","(",")","_","+","=","{","}","[","]","|","\",":",";","'","""","<",">",",",".","~?","/","~~","`"}, I4)))>0)=TRUE,"Special Characters Found in City","")} | Y4: {=IF((SUMPRODUCT(--ISNUMBER(SEARCH({"!","@","#","$","%","^","~*","(",")","_","+","=","{","}","[","]","|","\",":",";","'","""","<",">","~?","/","~~","`"},F4)))>0)=TRUE,"Special Characters Found in Account field","")} | Z4: {=IF(SUM(--ISNUMBER(SEARCH({1,2,3,4,5,6,7,8,9,0},MID(H4,(SEARCH(" E ",H4)-1),1))))+SUM(--ISNUMBER(SEARCH({1,2,3,4,5,6,7,8,9,0},MID(H4,(SEARCH(" E ",H4)+3),1))))=2,"",IF(SUM(--ISNUMBER(SEARCH({"Parte E","Apoquindo N"},H4)))>0,"",IF(OR(RIGHT(H4,3)=" NE",RIGHT(H4,3)=" NW",RIGHT(H4,3)=" SW",RIGHT(H4,3)=" SE",RIGHT(H4,2)=" N",RIGHT(H4,2)=" E",RIGHT(H4,2)=" W",RIGHT(H4,2)=" S",LEFT(H4,3)="NE ",LEFT(H4,3)="NW ",LEFT(H4,3)="SW ",LEFT(H4,3)="SE ",LEFT(H4,2)="N ",LEFT(H4,2)="E ",LEFT(H4,2)="W ",LEFT(H4,2)="S "),"Directional Check",IF(SUM(--ISNUMBER(SEARCH({" N "," E "," W "," S "," NE "," NW "," SW "," SE ","N.E","N.W","S.W","S.E","E.","N.","S.","W."},H4)))>0,"Directional Check",IF(SUM(--ISNUMBER(SEARCH({1,2,3,4,5,6,7,8,9,0},MID(H4,(SEARCH("nd ",H4)-1),1))))+SUM(--ISNUMBER(SEARCH({1,2,3,4,5,6,7,8,9,0},MID(H4,(SEARCH("rd ",H4)-1),1)))+SUM(--ISNUMBER(SEARCH({1,2,3,4,5,6,7,8,9,0},MID(H4,(SEARCH("st ",H4)-1),1))))+SUM(--ISNUMBER(SEARCH({1,2,3,4,5,6,7,8,9,0},MID(H4,(SEARCH("th ",H4)-1),1)))))>0,"","")))))} | AA4: =IF(IF(L4="US",IFERROR(VLOOKUP(J4,Country_Codes!$B:$B,1,0)=J4,"US State Code Error"),IF(L4="CA",IFERROR(VLOOKUP(J4,Country_Codes!$E:$E,1,0)=J4,"Canada State Code Error"),IF(L4="BR",IFERROR(VLOOKUP(J4,Country_Codes!$H:$H,1,0)=J4,"Brazil State Code Error"),IF(L4="AU",IFERROR(VLOOKUP(J4,Country_Codes!$K:$K,1,0)=J4,"Australia State Code Error"),""))))=TRUE,"",IF(L4="US",IFERROR(VLOOKUP(J4,Country_Codes!$B:$B,1,0)=J4,"US State Code Error"),IF(L4="CA",IFERROR(VLOOKUP(J4,Country_Codes!$E:$E,1,0)=J4,"Canada State Code Error"),IF(L4="BR",IFERROR(VLOOKUP(J4,Country_Codes!$H:$H,1,0)=J4,"Brazil State Code Error"),IF(L4="AU",IFERROR(VLOOKUP(J4,Country_Codes!$K:$K,1,0)=J4,"Australia State Code Error"),""))))) | AB4: =IF(OR(L4="US",L4="CA",L4="BR",L4="AU"),IF((EXACT(UPPER(J4),J4)),"","Country Code Casing"),IF(EXACT(J4,PROPER(J4)),"","Billing State casing")) | AC4: {=IFERROR(_xlfn.IFS(IF(AND(LEN(I4)=0,ISBLANK(I4)=FALSE),"",ISNUMBER(SEARCH(I4,H4))),"City/Postal Code/Country Found in Address",IF(AND(LEN(K4)=0,ISBLANK(K4)=FALSE),"",ISNUMBER(SEARCH(K4,H4))),"City/Postal Code/Country Found in Address",IF(AND(LEN(L4)=0,ISBLANK(L4)=FALSE),"",ISNUMBER(SEARCH(", "&L4,H4))),"City/Postal Code/Country Found in Address",IF(AND(LEN(J4)=0,ISBLANK(J4)=FALSE),"",ISNUMBER(SEARCH(", "&J4,H4))),"City/Postal Code/Country Found in Address",IF(AND(LEN(L4)=0,ISBLANK(L4)=FALSE),"",ISNUMBER(SEARCH(","&L4,H4))),"City/Postal Code/Country Found in Address",IF(AND(LEN(J4)=0,ISBLANK(J4)=FALSE),"",ISNUMBER(SEARCH(","&J4,H4))),"City/Postal Code/Country Found in Address"),"")} | AD4: =IF(ISNUMBER(SEARCH("PO",N4)),"PO# Entered in Tax ID Field","") | AE4: {=IFERROR(IF(VLOOKUP(LEFT(M4,MIN(SEARCH({1,2,3,4,5,6,7,8,9,0},M4&{1,2,3,4,5,6,7,8,9,0}))-1),Country_Codes!$N:$N,1,0)>0,"PO Number may be incorrect",""),"")} | AF4: =IF(N4="","",IF(EXACT(L4,LEFT(N4,2)),IF(EXACT(MID(N4,3,1)," "),"Check the Space inbetween County code & VAT",""),"Check the VAT Country Code Format")) | AG4: =IF((ISNUMBER(SEARCH("@",P4)))>0,"",IF(IF(--(ISNUMBER(SEARCH("'",P4)))>0,OR(EXACT(PROPER(P4),P4),EXACT((PROPER(LEFT(P4,FIND("'",P4)-2))&LOWER(MID(P4,FIND("'",P4)-1,1))&PROPER(MID(P4,FIND("'",P4)+0,LEN(P4)-FIND("'",P4)+1))),P4)),"Please check Billing Contact Casing")=TRUE,"","Please check Billing Contact casing")) | AH4: =IF(OR(L4="AS",L4="FM",L4="GU",L4="MH",L4="MP",L4="PW",L4="PR",L4="VI",L4="UM"),"US Territories Check","") | AI4: {=IF(G4="","",_xlfn.IFNA(_xlfn.IFS(L4=VLOOKUP(L4,Country_Codes!$M:$M,1,0)=TRUE,""),"Please check the country code"))} | AJ4: =IF(S4="","",S4&"; ")&IF(T4="","",T4&"; ")&IF(U4="","",U4&"; ")&IF(V4="","",V4&"; ")&IF(AF4="","",AF4&"; ")&IF(AG4="","",AG4&"; ")&IF(AH4="","",AH4&"; ")&IF(Z4="","",Z4&"; ")&IF(AA4="","",AA4&"; ")&IF(AB4="","",AB4&"; ")&IF(AC4="","",AC4&"; ")&IF(AD4="","",AD4&"; ")&IF(AE4="","",AE4&"; ")&IF(AI4="","",AI4&"; ")&IF(W4="","",W4&"; ")&IF(X4="","",X4&"; ")&IF(Y4="","",Y4&"; ") | AM4: =(COUNTA(S4:V4)-COUNTIFS((S4:V4),""))+(COUNTA(AB4)-COUNTIFS((AB4),""))+(COUNTA(AG4)-COUNTIFS((AG4),"")) -> 0 | AN4: =(COUNTA(W4)-COUNTIFS((W4),""))+(COUNTA(Z4)-COUNTIFS((Z4),"")) -> 0 | AO4: =(COUNTA(AA4)-COUNTIFS((AA4),""))+(COUNTA(AC4:AE4)-COUNTIFS((AC4:AE4),""))+(COUNTA(AH4:AI4)-COUNTIFS((AH4:AI4),"")) -> 0 | AP4: =(COUNTA(X4:Y4)-COUNTIFS((X4:Y4),""))+(COUNTA(AF4)-COUNTIFS((AF4),"")) -> 0 | AQ4: =SUM(AM4:AP4) -> 0 | AS4: Incorrect | AT4: =SUM($AO:$AO) -> 4 | AV4: 45393 | AW4: Sample Ltd
A5: 45596 | B5: User 2 | C5: Bill To Contact | D5: ID-0001a000 | E5: ID-0002a000 | F5: SAMPLE PARTNERS | G5: ID_Num_2 | H5: 50000 N Street | I5: Dallas | J5: TX | K5: 75201 | L5: US | O5: Justin Frank | R5: =IF(G5=G4,"","Unique Record") -> Unique Record | S5: =IF(F5="","",IF(EXACT(F5,(UPPER(F5))),"Account Upper Case","")) -> Account Upper Case | T5: =IF(F5="","",IF(EXACT(F5,(LOWER(F5))),"Account Lower Case","")) | U5: =IF(EXACT(H5,PROPER(H5)),"","Billing Street - casing") | V5: =IF(EXACT(I5,PROPER(I5)),"","City - casing") | W5: =IF(OR(ISNUMBER(SEARCH("East",I5)),ISNUMBER(SEARCH("West",I5)),ISNUMBER(SEARCH("North",I5)),ISNUMBER(SEARCH("South",I5))),"",IF(OR(ISNUMBER(SEARCH("St.",I5)),ISNUMBER(SEARCH("St ",I5))),"Check St in city field",IF(RIGHT(I5,1)=".","Dot found in city field",""))) | X5: {=IF((SUMPRODUCT(--ISNUMBER(SEARCH({"!","@","#","$","%","^","&","~*","(",")","_","+","=","{","}","[","]","|","\",":",";","'","""","<",">",",",".","~?","/","~~","`"}, I5)))>0)=TRUE,"Special Characters Found in City","")} | Y5: {=IF((SUMPRODUCT(--ISNUMBER(SEARCH({"!","@","#","$","%","^","~*","(",")","_","+","=","{","}","[","]","|","\",":",";","'","""","<",">","~?","/","~~","`"},F5)))>0)=TRUE,"Special Characters Found in Account field","")} | Z5: {=IF(SUM(--ISNUMBER(SEARCH({1,2,3,4,5,6,7,8,9,0},MID(H5,(SEARCH(" E ",H5)-1),1))))+SUM(--ISNUMBER(SEARCH({1,2,3,4,5,6,7,8,9,0},MID(H5,(SEARCH(" E ",H5)+3),1))))=2,"",IF(SUM(--ISNUMBER(SEARCH({"Parte E","Apoquindo N"},H5)))>0,"",IF(OR(RIGHT(H5,3)=" NE",RIGHT(H5,3)=" NW",RIGHT(H5,3)=" SW",RIGHT(H5,3)=" SE",RIGHT(H5,2)=" N",RIGHT(H5,2)=" E",RIGHT(H5,2)=" W",RIGHT(H5,2)=" S",LEFT(H5,3)="NE ",LEFT(H5,3)="NW ",LEFT(H5,3)="SW ",LEFT(H5,3)="SE ",LEFT(H5,2)="N ",LEFT(H5,2)="E ",LEFT(H5,2)="W ",LEFT(H5,2)="S "),"Directional Check",IF(SUM(--ISNUMBER(SEARCH({" N "," E "," W "," S "," NE "," NW "," SW "," SE ","N.E","N.W","S.W","S.E","E.","N.","S.","W."},H5)))>0,"Directional Check",IF(SUM(--ISNUMBER(SEARCH({1,2,3,4,5,6,7,8,9,0},MID(H5,(SEARCH("nd ",H5)-1),1))))+SUM(--ISNUMBER(SEARCH({1,2,3,4,5,6,7,8,9,0},MID(H5,(SEARCH("rd ",H5)-1),1)))+SUM(--ISNUMBER(SEARCH({1,2,3,4,5,6,7,8,9,0},MID(H5,(SEARCH("st ",H5)-1),1))))+SUM(--ISNUMBER(SEARCH({1,2,3,4,5,6,7,8,9,0},MID(H5,(SEARCH("th ",H5)-1),1)))))>0,"","")))))} -> Directional Check | AA5: =IF(IF(L5="US",IFERROR(VLOOKUP(J5,Country_Codes!$B:$B,1,0)=J5,"US State Code Error"),IF(L5="CA",IFERROR(VLOOKUP(J5,Country_Codes!$E:$E,1,0)=J5,"Canada State Code Error"),IF(L5="BR",IFERROR(VLOOKUP(J5,Country_Codes!$H:$H,1,0)=J5,"Brazil State Code Error"),IF(L5="AU",IFERROR(VLOOKUP(J5,Country_Codes!$K:$K,1,0)=J5,"Australia State Code Error"),""))))=TRUE,"",IF(L5="US",IFERROR(VLOOKUP(J5,Country_Codes!$B:$B,1,0)=J5,"US State Code Error"),IF(L5="CA",IFERROR(VLOOKUP(J5,Country_Codes!$E:$E,1,0)=J5,"Canada State Code Error"),IF(L5="BR",IFERROR(VLOOKUP(J5,Country_Codes!$H:$H,1,0)=J5,"Brazil State Code Error"),IF(L5="AU",IFERROR(VLOOKUP(J5,Country_Codes!$K:$K,1,0)=J5,"Australia State Code Error"),""))))) | AB5: =IF(OR(L5="US",L5="CA",L5="BR",L5="AU"),IF((EXACT(UPPER(J5),J5)),"","Country Code Casing"),IF(EXACT(J5,PROPER(J5)),"","Billing State casing")) | AC5: {=IFERROR(_xlfn.IFS(IF(AND(LEN(I5)=0,ISBLANK(I5)=FALSE),"",ISNUMBER(SEARCH(I5,H5))),"City/Postal Code/Country Found in Address",IF(AND(LEN(K5)=0,ISBLANK(K5)=FALSE),"",ISNUMBER(SEARCH(K5,H5))),"City/Postal Code/Country Found in Address",IF(AND(LEN(L5)=0,ISBLANK(L5)=FALSE),"",ISNUMBER(SEARCH(", "&L5,H5))),"City/Postal Code/Country Found in Address",IF(AND(LEN(J5)=0,ISBLANK(J5)=FALSE),"",ISNUMBER(SEARCH(", "&J5,H5))),"City/Postal Code/Country Found in Address",IF(AND(LEN(L5)=0,ISBLANK(L5)=FALSE),"",ISNUMBER(SEARCH(","&L5,H5))),"City/Postal Code/Country Found in Address",IF(AND(LEN(J5)=0,ISBLANK(J5)=FALSE),"",ISNUMBER(SEARCH(","&J5,H5))),"City/Postal Code/Country Found in Address"),"")} | AD5: =IF(ISNUMBER(SEARCH("PO",N5)),"PO# Entered in Tax ID Field","") | AE5: {=IFERROR(IF(VLOOKUP(LEFT(M5,MIN(SEARCH({1,2,3,4,5,6,7,8,9,0},M5&{1,2,3,4,5,6,7,8,9,0}))-1),Country_Codes!$N:$N,1,0)>0,"PO Number may be incorrect",""),"")} | AF5: =IF(N5="","",IF(EXACT(L5,LEFT(N5,2)),IF(EXACT(MID(N5,3,1)," "),"Check the Space inbetween County code & VAT",""),"Check the VAT Country Code Format")) | AG5: =IF((ISNUMBER(SEARCH("@",P5)))>0,"",IF(IF(--(ISNUMBER(SEARCH("'",P5)))>0,OR(EXACT(PROPER(P5),P5),EXACT((PROPER(LEFT(P5,FIND("'",P5)-2))&LOWER(MID(P5,FIND("'",P5)-1,1))&PROPER(MID(P5,FIND("'",P5)+0,LEN(P5)-FIND("'",P5)+1))),P5)),"Please check Billing Contact Casing")=TRUE,"","Please check Billing Contact casing")) | AH5: =IF(OR(L5="AS",L5="FM",L5="GU",L5="MH",L5="MP",L5="PW",L5="PR",L5="VI",L5="UM"),"US Territories Check","") | AI5: {=IF(G5="","",_xlfn.IFNA(_xlfn.IFS(L5=VLOOKUP(L5,Country_Codes!$M:$M,1,0)=TRUE,""),"Please check the country code"))} | AJ5: =IF(S5="","",S5&"; ")&IF(T5="","",T5&"; ")&IF(U5="","",U5&"; ")&IF(V5="","",V5&"; ")&IF(AF5="","",AF5&"; ")&IF(AG5="","",AG5&"; ")&IF(AH5="","",AH5&"; ")&IF(Z5="","",Z5&"; ")&IF(AA5="","",AA5&"; ")&IF(AB5="","",AB5&"; ")&IF(AC5="","",AC5&"; ")&IF(AD5="","",AD5&"; ")&IF(AE5="","",AE5&"; ")&IF(AI5="","",AI5&"; ")&IF(W5="","",W5&"; ")&IF(X5="","",X5&"; ")&IF(Y5="","",Y5&"; ") -> Account Upper Case; Directional Check; | AM5: =(COUNTA(S5:V5)-COUNTIFS((S5:V5),""))+(COUNTA(AB5)-COUNTIFS((AB5),""))+(COUNTA(AG5)-COUNTIFS((AG5),"")) -> 1 | AN5: =(COUNTA(W5)-COUNTIFS((W5),""))+(COUNTA(Z5)-COUNTIFS((Z5),"")) -> 1 | AO5: =(COUNTA(AA5)-COUNTIFS((AA5),""))+(COUNTA(AC5:AE5)-COUNTIFS((AC5:AE5),""))+(COUNTA(AH5:AI5)-COUNTIFS((AH5:AI5),"")) -> 0 | AP5: =(COUNTA(X5:Y5)-COUNTIFS((X5:Y5),""))+(COUNTA(AF5)-COUNTIFS((AF5),"")) -> 0 | AQ5: =SUM(AM5:AP5) -> 2 | AS5: Format | AT5: =SUM($AP:$AP) -> 2 | AV5: 45419 | AW5: SAMPLE PARTNERS
A6: 45574 | B6: User 1 | C6: Bill To Contact | D6: ID-0003a000 | E6: ID-0004a000 | F6: Sample Products, Inc. | G6: ID_Num_3 | H6: 10000 Sample Court, Suite 200 | I6: Mississauga | J6: ON | K6: L5N 5R5 | L6: CA | M6: 5600004 | O6: Smith Frank | R6: =IF(G6=G5,"","Unique Record") -> Unique Record | S6: =IF(F6="","",IF(EXACT(F6,(UPPER(F6))),"Account Upper Case","")) | T6: =IF(F6="","",IF(EXACT(F6,(LOWER(F6))),"Account Lower Case","")) | U6: =IF(EXACT(H6,PROPER(H6)),"","Billing Street - casing") | V6: =IF(EXACT(I6,PROPER(I6)),"","City - casing") | W6: =IF(OR(ISNUMBER(SEARCH("East",I6)),ISNUMBER(SEARCH("West",I6)),ISNUMBER(SEARCH("North",I6)),ISNUMBER(SEARCH("South",I6))),"",IF(OR(ISNUMBER(SEARCH("St.",I6)),ISNUMBER(SEARCH("St ",I6))),"Check St in city field",IF(RIGHT(I6,1)=".","Dot found in city field",""))) | X6: {=IF((SUMPRODUCT(--ISNUMBER(SEARCH({"!","@","#","$","%","^","&","~*","(",")","_","+","=","{","}","[","]","|","\",":",";","'","""","<",">",",",".","~?","/","~~","`"}, I6)))>0)=TRUE,"Special Characters Found in City","")} | Y6: {=IF((SUMPRODUCT(--ISNUMBER(SEARCH({"!","@","#","$","%","^","~*","(",")","_","+","=","{","}","[","]","|","\",":",";","'","""","<",">","~?","/","~~","`"},F6)))>0)=TRUE,"Special Characters Found in Account field","")} | Z6: {=IF(SUM(--ISNUMBER(SEARCH({1,2,3,4,5,6,7,8,9,0},MID(H6,(SEARCH(" E ",H6)-1),1))))+SUM(--ISNUMBER(SEARCH({1,2,3,4,5,6,7,8,9,0},MID(H6,(SEARCH(" E ",H6)+3),1))))=2,"",IF(SUM(--ISNUMBER(SEARCH({"Parte E","Apoquindo N"},H6)))>0,"",IF(OR(RIGHT(H6,3)=" NE",RIGHT(H6,3)=" NW",RIGHT(H6,3)=" SW",RIGHT(H6,3)=" SE",RIGHT(H6,2)=" N",RIGHT(H6,2)=" E",RIGHT(H6,2)=" W",RIGHT(H6,2)=" S",LEFT(H6,3)="NE ",LEFT(H6,3)="NW ",LEFT(H6,3)="SW ",LEFT(H6,3)="SE ",LEFT(H6,2)="N ",LEFT(H6,2)="E ",LEFT(H6,2)="W ",LEFT(H6,2)="S "),"Directional Check",IF(SUM(--ISNUMBER(SEARCH({" N "," E "," W "," S "," NE "," NW "," SW "," SE ","N.E","N.W","S.W","S.E","E.","N.","S.","W."},H6)))>0,"Directional Check",IF(SUM(--ISNUMBER(SEARCH({1,2,3,4,5,6,7,8,9,0},MID(H6,(SEARCH("nd ",H6)-1),1))))+SUM(--ISNUMBER(SEARCH({1,2,3,4,5,6,7,8,9,0},MID(H6,(SEARCH("rd ",H6)-1),1)))+SUM(--ISNUMBER(SEARCH({1,2,3,4,5,6,7,8,9,0},MID(H6,(SEARCH("st ",H6)-1),1))))+SUM(--ISNUMBER(SEARCH({1,2,3,4,5,6,7,8,9,0},MID(H6,(SEARCH("th ",H6)-1),1)))))>0,"","")))))} | AA6: =IF(IF(L6="US",IFERROR(VLOOKUP(J6,Country_Codes!$B:$B,1,0)=J6,"US State Code Error"),IF(L6="CA",IFERROR(VLOOKUP(J6,Country_Codes!$E:$E,1,0)=J6,"Canada State Code Error"),IF(L6="BR",IFERROR(VLOOKUP(J6,Country_Codes!$H:$H,1,0)=J6,"Brazil State Code Error"),IF(L6="AU",IFERROR(VLOOKUP(J6,Country_Codes!$K:$K,1,0)=J6,"Australia State Code Error"),""))))=TRUE,"",IF(L6="US",IFERROR(VLOOKUP(J6,Country_Codes!$B:$B,1,0)=J6,"US State Code Error"),IF(L6="CA",IFERROR(VLOOKUP(J6,Country_Codes!$E:$E,1,0)=J6,"Canada State Code Error"),IF(L6="BR",IFERROR(VLOOKUP(J6,Country_Codes!$H:$H,1,0)=J6,"Brazil State Code Error"),IF(L6="AU",IFERROR(VLOOKUP(J6,Country_Codes!$K:$K,1,0)=J6,"Australia State Code Error"),""))))) | AB6: =IF(OR(L6="US",L6="CA",L6="BR",L6="AU"),IF((EXACT(UPPER(J6),J6)),"","Country Code Casing"),IF(EXACT(J6,PROPER(J6)),"","Billing State casing")) | AC6: {=IFERROR(_xlfn.IFS(IF(AND(LEN(I6)=0,ISBLANK(I6)=FALSE),"",ISNUMBER(SEARCH(I6,H6))),"City/Postal Code/Country Found in Address",IF(AND(LEN(K6)=0,ISBLANK(K6)=FALSE),"",ISNUMBER(SEARCH(K6,H6))),"City/Postal Code/Country Found in Address",IF(AND(LEN(L6)=0,ISBLANK(L6)=FALSE),"",ISNUMBER(SEARCH(", "&L6,H6))),"City/Postal Code/Country Found in Address",IF(AND(LEN(J6)=0,ISBLANK(J6)=FALSE),"",ISNUMBER(SEARCH(", "&J6,H6))),"City/Postal Code/Country Found in Address",IF(AND(LEN(L6)=0,ISBLANK(L6)=FALSE),"",ISNUMBER(SEARCH(","&L6,H6))),"City/Postal Code/Country Found in Address",IF(AND(LEN(J6)=0,ISBLANK(J6)=FALSE),"",ISNUMBER(SEARCH(","&J6,H6))),"City/Postal Code/Country Found in Address"),"")} | AD6: =IF(ISNUMBER(SEARCH("PO",N6)),"PO# Entered in Tax ID Field","") | AE6: {=IFERROR(IF(VLOOKUP(LEFT(M6,MIN(SEARCH({1,2,3,4,5,6,7,8,9,0},M6&{1,2,3,4,5,6,7,8,9,0}))-1),Country_Codes!$N:$N,1,0)>0,"PO Number may be incorrect",""),"")} | AF6: =IF(N6="","",IF(EXACT(L6,LEFT(N6,2)),IF(EXACT(MID(N6,3,1)," "),"Check the Space inbetween County code & VAT",""),"Check the VAT Country Code Format")) | AG6: =IF((ISNUMBER(SEARCH("@",P6)))>0,"",IF(IF(--(ISNUMBER(SEARCH("'",P6)))>0,OR(EXACT(PROPER(P6),P6),EXACT((PROPER(LEFT(P6,FIND("'",P6)-2))&LOWER(MID(P6,FIND("'",P6)-1,1))&PROPER(MID(P6,FIND("'",P6)+0,LEN(P6)-FIND("'",P6)+1))),P6)),"Please check Billing Contact Casing")=TRUE,"","Please check Billing Contact casing")) | AH6: =IF(OR(L6="AS",L6="FM",L6="GU",L6="MH",L6="MP",L6="PW",L6="PR",L6="VI",L6="UM"),"US Territories Check","") | AI6: {=IF(G6="","",_xlfn.IFNA(_xlfn.IFS(L6=VLOOKUP(L6,Country_Codes!$M:$M,1,0)=TRUE,""),"Please check the country code"))} | AJ6: =IF(S6="","",S6&"; ")&IF(T6="","",T6&"; ")&IF(U6="","",U6&"; ")&IF(V6="","",V6&"; ")&IF(AF6="","",AF6&"; ")&IF(AG6="","",AG6&"; ")&IF(AH6="","",AH6&"; ")&IF(Z6="","",Z6&"; ")&IF(AA6="","",AA6&"; ")&IF(AB6="","",AB6&"; ")&IF(AC6="","",AC6&"; ")&IF(AD6="","",AD6&"; ")&IF(AE6="","",AE6&"; ")&IF(AI6="","",AI6&"; ")&IF(W6="","",W6&"; ")&IF(X6="","",X6&"; ")&IF(Y6="","",Y6&"; ") | AM6: =(COUNTA(S6:V6)-COUNTIFS((S6:V6),""))+(COUNTA(AB6)-COUNTIFS((AB6),""))+(COUNTA(AG6)-COUNTIFS((AG6),"")) -> 0 | AN6: =(COUNTA(W6)-COUNTIFS((W6),""))+(COUNTA(Z6)-COUNTIFS((Z6),"")) -> 0 | AO6: =(COUNTA(AA6)-COUNTIFS((AA6),""))+(COUNTA(AC6:AE6)-COUNTIFS((AC6:AE6),""))+(COUNTA(AH6:AI6)-COUNTIFS((AH6:AI6),"")) -> 0 | AP6: =(COUNTA(X6:Y6)-COUNTIFS((X6:Y6),""))+(COUNTA(AF6)-COUNTIFS((AF6),"")) -> 0 | AQ6: =SUM(AM6:AP6) -> 0 | AS6: Abbreviation | AT6: =SUM($AN:$AN) -> 1 | AV6: 45423 | AW6: Sample Products, Inc.
A7: 45393 | B7: User 3 | C7: PO Number | D7: 3587 | E7: 4490 | F7: Sample Products, Inc. | G7: ID_Num_3 | H7: 10000 Sample Court, Suite 200 | I7: Mississauga | J7: ON | K7: L5N 5R5 | L7: CA | M7: 5600004 | O7: Smith Frank | R7: =IF(G7=G6,"","Unique Record") | S7: =IF(F7="","",IF(EXACT(F7,(UPPER(F7))),"Account Upper Case","")) | T7: =IF(F7="","",IF(EXACT(F7,(LOWER(F7))),"Account Lower Case","")) | U7: =IF(EXACT(H7,PROPER(H7)),"","Billing Street - casing") | V7: =IF(EXACT(I7,PROPER(I7)),"","City - casing") | W7: =IF(OR(ISNUMBER(SEARCH("East",I7)),ISNUMBER(SEARCH("West",I7)),ISNUMBER(SEARCH("North",I7)),ISNUMBER(SEARCH("South",I7))),"",IF(OR(ISNUMBER(SEARCH("St.",I7)),ISNUMBER(SEARCH("St ",I7))),"Check St in city field",IF(RIGHT(I7,1)=".","Dot found in city field",""))) | X7: {=IF((SUMPRODUCT(--ISNUMBER(SEARCH({"!","@","#","$","%","^","&","~*","(",")","_","+","=","{","}","[","]","|","\",":",";","'","""","<",">",",",".","~?","/","~~","`"}, I7)))>0)=TRUE,"Special Characters Found in City","")} | Y7: {=IF((SUMPRODUCT(--ISNUMBER(SEARCH({"!","@","#","$","%","^","~*","(",")","_","+","=","{","}","[","]","|","\",":",";","'","""","<",">","~?","/","~~","`"},F7)))>0)=TRUE,"Special Characters Found in Account field","")} | Z7: {=IF(SUM(--ISNUMBER(SEARCH({1,2,3,4,5,6,7,8,9,0},MID(H7,(SEARCH(" E ",H7)-1),1))))+SUM(--ISNUMBER(SEARCH({1,2,3,4,5,6,7,8,9,0},MID(H7,(SEARCH(" E ",H7)+3),1))))=2,"",IF(SUM(--ISNUMBER(SEARCH({"Parte E","Apoquindo N"},H7)))>0,"",IF(OR(RIGHT(H7,3)=" NE",RIGHT(H7,3)=" NW",RIGHT(H7,3)=" SW",RIGHT(H7,3)=" SE",RIGHT(H7,2)=" N",RIGHT(H7,2)=" E",RIGHT(H7,2)=" W",RIGHT(H7,2)=" S",LEFT(H7,3)="NE ",LEFT(H7,3)="NW ",LEFT(H7,3)="SW ",LEFT(H7,3)="SE ",LEFT(H7,2)="N ",LEFT(H7,2)="E ",LEFT(H7,2)="W ",LEFT(H7,2)="S "),"Directional Check",IF(SUM(--ISNUMBER(SEARCH({" N "," E "," W "," S "," NE "," NW "," SW "," SE ","N.E","N.W","S.W","S.E","E.","N.","S.","W."},H7)))>0,"Directional Check",IF(SUM(--ISNUMBER(SEARCH({1,2,3,4,5,6,7,8,9,0},MID(H7,(SEARCH("nd ",H7)-1),1))))+SUM(--ISNUMBER(SEARCH({1,2,3,4,5,6,7,8,9,0},MID(H7,(SEARCH("rd ",H7)-1),1)))+SUM(--ISNUMBER(SEARCH({1,2,3,4,5,6,7,8,9,0},MID(H7,(SEARCH("st ",H7)-1),1))))+SUM(--ISNUMBER(SEARCH({1,2,3,4,5,6,7,8,9,0},MID(H7,(SEARCH("th ",H7)-1),1)))))>0,"","")))))} | AA7: =IF(IF(L7="US",IFERROR(VLOOKUP(J7,Country_Codes!$B:$B,1,0)=J7,"US State Code Error"),IF(L7="CA",IFERROR(VLOOKUP(J7,Country_Codes!$E:$E,1,0)=J7,"Canada State Code Error"),IF(L7="BR",IFERROR(VLOOKUP(J7,Country_Codes!$H:$H,1,0)=J7,"Brazil State Code Error"),IF(L7="AU",IFERROR(VLOOKUP(J7,Country_Codes!$K:$K,1,0)=J7,"Australia State Code Error"),""))))=TRUE,"",IF(L7="US",IFERROR(VLOOKUP(J7,Country_Codes!$B:$B,1,0)=J7,"US State Code Error"),IF(L7="CA",IFERROR(VLOOKUP(J7,Country_Codes!$E:$E,1,0)=J7,"Canada State Code Error"),IF(L7="BR",IFERROR(VLOOKUP(J7,Country_Codes!$H:$H,1,0)=J7,"Brazil State Code Error"),IF(L7="AU",IFERROR(VLOOKUP(J7,Country_Codes!$K:$K,1,0)=J7,"Australia State Code Error"),""))))) | AB7: =IF(OR(L7="US",L7="CA",L7="BR",L7="AU"),IF((EXACT(UPPER(J7),J7)),"","Country Code Casing"),IF(EXACT(J7,PROPER(J7)),"","Billing State casing")) | AC7: {=IFERROR(_xlfn.IFS(IF(AND(LEN(I7)=0,ISBLANK(I7)=FALSE),"",ISNUMBER(SEARCH(I7,H7))),"City/Postal Code/Country Found in Address",IF(AND(LEN(K7)=0,ISBLANK(K7)=FALSE),"",ISNUMBER(SEARCH(K7,H7))),"City/Postal Code/Country Found in Address",IF(AND(LEN(L7)=0,ISBLANK(L7)=FALSE),"",ISNUMBER(SEARCH(", "&L7,H7))),"City/Postal Code/Country Found in Address",IF(AND(LEN(J7)=0,ISBLANK(J7)=FALSE),"",ISNUMBER(SEARCH(", "&J7,H7))),"City/Postal Code/Country Found in Address",IF(AND(LEN(L7)=0,ISBLANK(L7)=FALSE),"",ISNUMBER(SEARCH(","&L7,H7))),"City/Postal Code/Country Found in Address",IF(AND(LEN(J7)=0,ISBLANK(J7)=FALSE),"",ISNUMBER(SEARCH(","&J7,H7))),"City/Postal Code/Country Found in Address"),"")} | AD7: =IF(ISNUMBER(SEARCH("PO",N7)),"PO# Entered in Tax ID Field","") | AE7: {=IFERROR(IF(VLOOKUP(LEFT(M7,MIN(SEARCH({1,2,3,4,5,6,7,8,9,0},M7&{1,2,3,4,5,6,7,8,9,0}))-1),Country_Codes!$N:$N,1,0)>0,"PO Number may be incorrect",""),"")} | AF7: =IF(N7="","",IF(EXACT(L7,LEFT(N7,2)),IF(EXACT(MID(N7,3,1)," "),"Check the Space inbetween County code & VAT",""),"Check the VAT Country Code Format")) | AG7: =IF((ISNUMBER(SEARCH("@",P7)))>0,"",IF(IF(--(ISNUMBER(SEARCH("'",P7)))>0,OR(EXACT(PROPER(P7),P7),EXACT((PROPER(LEFT(P7,FIND("'",P7)-2))&LOWER(MID(P7,FIND("'",P7)-1,1))&PROPER(MID(P7,FIND("'",P7)+0,LEN(P7)-FIND("'",P7)+1))),P7)),"Please check Billing Contact Casing")=TRUE,"","Please check Billing Contact casing")) | AH7: =IF(OR(L7="AS",L7="FM",L7="GU",L7="MH",L7="MP",L7="PW",L7="PR",L7="VI",L7="UM"),"US Territories Check","") | AI7: {=IF(G7="","",_xlfn.IFNA(_xlfn.IFS(L7=VLOOKUP(L7,Country_Codes!$M:$M,1,0)=TRUE,""),"Please check the country code"))} | AJ7: =IF(S7="","",S7&"; ")&IF(T7="","",T7&"; ")&IF(U7="","",U7&"; ")&IF(V7="","",V7&"; ")&IF(AF7="","",AF7&"; ")&IF(AG7="","",AG7&"; ")&IF(AH7="","",AH7&"; ")&IF(Z7="","",Z7&"; ")&IF(AA7="","",AA7&"; ")&IF(AB7="","",AB7&"; ")&IF(AC7="","",AC7&"; ")&IF(AD7="","",AD7&"; ")&IF(AE7="","",AE7&"; ")&IF(AI7="","",AI7&"; ")&IF(W7="","",W7&"; ")&IF(X7="","",X7&"; ")&IF(Y7="","",Y7&"; ") | AM7: =(COUNTA(S7:V7)-COUNTIFS((S7:V7),""))+(COUNTA(AB7)-COUNTIFS((AB7),""))+(COUNTA(AG7)-COUNTIFS((AG7),"")) -> 0 | AN7: =(COUNTA(W7)-COUNTIFS((W7),""))+(COUNTA(Z7)-COUNTIFS((Z7),"")) -> 0 | AO7: =(COUNTA(AA7)-COUNTIFS((AA7),""))+(COUNTA(AC7:AE7)-COUNTIFS((AC7:AE7),""))+(COUNTA(AH7:AI7)-COUNTIFS((AH7:AI7),"")) -> 0 | AP7: =(COUNTA(X7:Y7)-COUNTIFS((X7:Y7),""))+(COUNTA(AF7)-COUNTIFS((AF7),"")) -> 0 | AQ7: =SUM(AM7:AP7) -> 0 | AS7: Total | AT7: =SUM(AT3:AT6) -> 12 | AV7: 45424 | AW7: Sample Technologies, Inc.
A8: 45315 | B8: User 1 | C8: Bill To Contact | D8: ID-0005a000 | E8: ID-0006a000 | F8: Sample flow, inc. | G8: ID_Num_4 | H8: 11111 Sample Place | I8: Charlotte | J8: NC | K8: 28277 | L8: US | O8: Tony Frank | R8: =IF(G8=G7,"","Unique Record") -> Unique Record | S8: =IF(F8="","",IF(EXACT(F8,(UPPER(F8))),"Account Upper Case","")) | T8: =IF(F8="","",IF(EXACT(F8,(LOWER(F8))),"Account Lower Case","")) | U8: =IF(EXACT(H8,PROPER(H8)),"","Billing Street - casing") | V8: =IF(EXACT(I8,PROPER(I8)),"","City - casing") | W8: =IF(OR(ISNUMBER(SEARCH("East",I8)),ISNUMBER(SEARCH("West",I8)),ISNUMBER(SEARCH("North",I8)),ISNUMBER(SEARCH("South",I8))),"",IF(OR(ISNUMBER(SEARCH("St.",I8)),ISNUMBER(SEARCH("St ",I8))),"Check St in city field",IF(RIGHT(I8,1)=".","Dot found in city field",""))) | X8: {=IF((SUMPRODUCT(--ISNUMBER(SEARCH({"!","@","#","$","%","^","&","~*","(",")","_","+","=","{","}","[","]","|","\",":",";","'","""","<",">",",",".","~?","/","~~","`"}, I8)))>0)=TRUE,"Special Characters Found in City","")} | Y8: {=IF((SUMPRODUCT(--ISNUMBER(SEARCH({"!","@","#","$","%","^","~*","(",")","_","+","=","{","}","[","]","|","\",":",";","'","""","<",">","~?","/","~~","`"},F8)))>0)=TRUE,"Special Characters Found in Account field","")} | Z8: {=IF(SUM(--ISNUMBER(SEARCH({1,2,3,4,5,6,7,8,9,0},MID(H8,(SEARCH(" E ",H8)-1),1))))+SUM(--ISNUMBER(SEARCH({1,2,3,4,5,6,7,8,9,0},MID(H8,(SEARCH(" E ",H8)+3),1))))=2,"",IF(SUM(--ISNUMBER(SEARCH({"Parte E","Apoquindo N"},H8)))>0,"",IF(OR(RIGHT(H8,3)=" NE",RIGHT(H8,3)=" NW",RIGHT(H8,3)=" SW",RIGHT(H8,3)=" SE",RIGHT(H8,2)=" N",RIGHT(H8,2)=" E",RIGHT(H8,2)=" W",RIGHT(H8,2)=" S",LEFT(H8,3)="NE ",LEFT(H8,3)="NW ",LEFT(H8,3)="SW ",LEFT(H8,3)="SE ",LEFT(H8,2)="N ",LEFT(H8,2)="E ",LEFT(H8,2)="W ",LEFT(H8,2)="S "),"Directional Check",IF(SUM(--ISNUMBER(SEARCH({" N "," E "," W "," S "," NE "," NW "," SW "," SE ","N.E","N.W","S.W","S.E","E.","N.","S.","W."},H8)))>0,"Directional Check",IF(SUM(--ISNUMBER(SEARCH({1,2,3,4,5,6,7,8,9,0},MID(H8,(SEARCH("nd ",H8)-1),1))))+SUM(--ISNUMBER(SEARCH({1,2,3,4,5,6,7,8,9,0},MID(H8,(SEARCH("rd ",H8)-1),1)))+SUM(--ISNUMBER(SEARCH({1,2,3,4,5,6,7,8,9,0},MID(H8,(SEARCH("st ",H8)-1),1))))+SUM(--ISNUMBER(SEARCH({1,2,3,4,5,6,7,8,9,0},MID(H8,(SEARCH("th ",H8)-1),1)))))>0,"","")))))} | AA8: =IF(IF(L8="US",IFERROR(VLOOKUP(J8,Country_Codes!$B:$B,1,0)=J8,"US State Code Error"),IF(L8="CA",IFERROR(VLOOKUP(J8,Country_Codes!$E:$E,1,0)=J8,"Canada State Code Error"),IF(L8="BR",IFERROR(VLOOKUP(J8,Country_Codes!$H:$H,1,0)=J8,"Brazil State Code Error"),IF(L8="AU",IFERROR(VLOOKUP(J8,Country_Codes!$K:$K,1,0)=J8,"Australia State Code Error"),""))))=TRUE,"",IF(L8="US",IFERROR(VLOOKUP(J8,Country_Codes!$B:$B,1,0)=J8,"US State Code Error"),IF(L8="CA",IFERROR(VLOOKUP(J8,Country_Codes!$E:$E,1,0)=J8,"Canada State Code Error"),IF(L8="BR",IFERROR(VLOOKUP(J8,Country_Codes!$H:$H,1,0)=J8,"Brazil State Code Error"),IF(L8="AU",IFERROR(VLOOKUP(J8,Country_Codes!$K:$K,1,0)=J8,"Australia State Code Error"),""))))) | AB8: =IF(OR(L8="US",L8="CA",L8="BR",L8="AU"),IF((EXACT(UPPER(J8),J8)),"","Country Code Casing"),IF(EXACT(J8,PROPER(J8)),"","Billing State casing")) | AC8: {=IFERROR(_xlfn.IFS(IF(AND(LEN(I8)=0,ISBLANK(I8)=FALSE),"",ISNUMBER(SEARCH(I8,H8))),"City/Postal Code/Country Found in Address",IF(AND(LEN(K8)=0,ISBLANK(K8)=FALSE),"",ISNUMBER(SEARCH(K8,H8))),"City/Postal Code/Country Found in Address",IF(AND(LEN(L8)=0,ISBLANK(L8)=FALSE),"",ISNUMBER(SEARCH(", "&L8,H8))),"City/Postal Code/Country Found in Address",IF(AND(LEN(J8)=0,ISBLANK(J8)=FALSE),"",ISNUMBER(SEARCH(", "&J8,H8))),"City/Postal Code/Country Found in Address",IF(AND(LEN(L8)=0,ISBLANK(L8)=FALSE),"",ISNUMBER(SEARCH(","&L8,H8))),"City/Postal Code/Country Found in Address",IF(AND(LEN(J8)=0,ISBLANK(J8)=FALSE),"",ISNUMBER(SEARCH(","&J8,H8))),"City/Postal Code/Country Found in Address"),"")} | AD8: =IF(ISNUMBER(SEARCH("PO",N8)),"PO# Entered in Tax ID Field","") | AE8: {=IFERROR(IF(VLOOKUP(LEFT(M8,MIN(SEARCH({1,2,3,4,5,6,7,8,9,0},M8&{1,2,3,4,5,6,7,8,9,0}))-1),Country_Codes!$N:$N,1,0)>0,"PO Number may be incorrect",""),"")} | AF8: =IF(N8="","",IF(EXACT(L8,LEFT(N8,2)),IF(EXACT(MID(N8,3,1)," "),"Check the Space inbetween County code & VAT",""),"Check the VAT Country Code Format")) | AG8: =IF((ISNUMBER(SEARCH("@",P8)))>0,"",IF(IF(--(ISNUMBER(SEARCH("'",P8)))>0,OR(EXACT(PROPER(P8),P8),EXACT((PROPER(LEFT(P8,FIND("'",P8)-2))&LOWER(MID(P8,FIND("'",P8)-1,1))&PROPER(MID(P8,FIND("'",P8)+0,LEN(P8)-FIND("'",P8)+1))),P8)),"Please check Billing Contact Casing")=TRUE,"","Please check Billing Contact casing")) | AH8: =IF(OR(L8="AS",L8="FM",L8="GU",L8="MH",L8="MP",L8="PW",L8="PR",L8="VI",L8="UM"),"US Territories Check","") | AI8: {=IF(G8="","",_xlfn.IFNA(_xlfn.IFS(L8=VLOOKUP(L8,Country_Codes!$M:$M,1,0)=TRUE,""),"Please check the country code"))} | AJ8: =IF(S8="","",S8&"; ")&IF(T8="","",T8&"; ")&IF(U8="","",U8&"; ")&IF(V8="","",V8&"; ")&IF(AF8="","",AF8&"; ")&IF(AG8="","",AG8&"; ")&IF(AH8="","",AH8&"; ")&IF(Z8="","",Z8&"; ")&IF(AA8="","",AA8&"; ")&IF(AB8="","",AB8&"; ")&IF(AC8="","",AC8&"; ")&IF(AD8="","",AD8&"; ")&IF(AE8="","",AE8&"; ")&IF(AI8="","",AI8&"; ")&IF(W8="","",W8&"; ")&IF(X8="","",X8&"; ")&IF(Y8="","",Y8&"; ") | AM8: =(COUNTA(S8:V8)-COUNTIFS((S8:V8),""))+(COUNTA(AB8)-COUNTIFS((AB8),""))+(COUNTA(AG8)-COUNTIFS((AG8),"")) -> 0 | AN8: =(COUNTA(W8)-COUNTIFS((W8),""))+(COUNTA(Z8)-COUNTIFS((Z8),"")) -> 0 | AO8: =(COUNTA(AA8)-COUNTIFS((AA8),""))+(COUNTA(AC8:AE8)-COUNTIFS((AC8:AE8),""))+(COUNTA(AH8:AI8)-COUNTIFS((AH8:AI8),"")) -> 0 | AP8: =(COUNTA(X8:Y8)-COUNTIFS((X8:Y8),""))+(COUNTA(AF8)-COUNTIFS((AF8),"")) -> 0 | AQ8: =SUM(AM8:AP8) -> 0 | AV8: 45425 | AW8: Sample, Inc.
A9: 45622 | B9: User 1 | C9: Bill To Contact | D9: ID-0006a000 | F9: Sample Ltd | G9: ID_Num_5 | H9: main street, 5th Floor | I9: London | K9: EC2V 7EE | L9: GB | M9: PO 030 | P9: Smith Frank | R9: =IF(G9=G8,"","Unique Record") -> Unique Record | S9: =IF(F9="","",IF(EXACT(F9,(UPPER(F9))),"Account Upper Case","")) | T9: =IF(F9="","",IF(EXACT(F9,(LOWER(F9))),"Account Lower Case","")) | U9: =IF(EXACT(H9,PROPER(H9)),"","Billing Street - casing") -> Billing Street - casing | V9: =IF(EXACT(I9,PROPER(I9)),"","City - casing") | W9: =IF(OR(ISNUMBER(SEARCH("East",I9)),ISNUMBER(SEARCH("West",I9)),ISNUMBER(SEARCH("North",I9)),ISNUMBER(SEARCH("South",I9))),"",IF(OR(ISNUMBER(SEARCH("St.",I9)),ISNUMBER(SEARCH("St ",I9))),"Check St in city field",IF(RIGHT(I9,1)=".","Dot found in city field",""))) | X9: {=IF((SUMPRODUCT(--ISNUMBER(SEARCH({"!","@","#","$","%","^","&","~*","(",")","_","+","=","{","}","[","]","|","\",":",";","'","""","<",">",",",".","~?","/","~~","`"}, I9)))>0)=TRUE,"Special Characters Found in City","")} | Y9: {=IF((SUMPRODUCT(--ISNUMBER(SEARCH({"!","@","#","$","%","^","~*","(",")","_","+","=","{","}","[","]","|","\",":",";","'","""","<",">","~?","/","~~","`"},F9)))>0)=TRUE,"Special Characters Found in Account field","")} | Z9: {=IF(SUM(--ISNUMBER(SEARCH({1,2,3,4,5,6,7,8,9,0},MID(H9,(SEARCH(" E ",H9)-1),1))))+SUM(--ISNUMBER(SEARCH({1,2,3,4,5,6,7,8,9,0},MID(H9,(SEARCH(" E ",H9)+3),1))))=2,"",IF(SUM(--ISNUMBER(SEARCH({"Parte E","Apoquindo N"},H9)))>0,"",IF(OR(RIGHT(H9,3)=" NE",RIGHT(H9,3)=" NW",RIGHT(H9,3)=" SW",RIGHT(H9,3)=" SE",RIGHT(H9,2)=" N",RIGHT(H9,2)=" E",RIGHT(H9,2)=" W",RIGHT(H9,2)=" S",LEFT(H9,3)="NE ",LEFT(H9,3)="NW ",LEFT(H9,3)="SW ",LEFT(H9,3)="SE ",LEFT(H9,2)="N ",LEFT(H9,2)="E ",LEFT(H9,2)="W ",LEFT(H9,2)="S "),"Directional Check",IF(SUM(--ISNUMBER(SEARCH({" N "," E "," W "," S "," NE "," NW "," SW "," SE ","N.E","N.W","S.W","S.E","E.","N.","S.","W."},H9)))>0,"Directional Check",IF(SUM(--ISNUMBER(SEARCH({1,2,3,4,5,6,7,8,9,0},MID(H9,(SEARCH("nd ",H9)-1),1))))+SUM(--ISNUMBER(SEARCH({1,2,3,4,5,6,7,8,9,0},MID(H9,(SEARCH("rd ",H9)-1),1)))+SUM(--ISNUMBER(SEARCH({1,2,3,4,5,6,7,8,9,0},MID(H9,(SEARCH("st ",H9)-1),1))))+SUM(--ISNUMBER(SEARCH({1,2,3,4,5,6,7,8,9,0},MID(H9,(SEARCH("th ",H9)-1),1)))))>0,"","")))))} | AA9: =IF(IF(L9="US",IFERROR(VLOOKUP(J9,Country_Codes!$B:$B,1,0)=J9,"US State Code Error"),IF(L9="CA",IFERROR(VLOOKUP(J9,Country_Codes!$E:$E,1,0)=J9,"Canada State Code Error"),IF(L9="BR",IFERROR(VLOOKUP(J9,Country_Codes!$H:$H,1,0)=J9,"Brazil State Code Error"),IF(L9="AU",IFERROR(VLOOKUP(J9,Country_Codes!$K:$K,1,0)=J9,"Australia State Code Error"),""))))=TRUE,"",IF(L9="US",IFERROR(VLOOKUP(J9,Country_Codes!$B:$B,1,0)=J9,"US State Code Error"),IF(L9="CA",IFERROR(VLOOKUP(J9,Country_Codes!$E:$E,1,0)=J9,"Canada State Code Error"),IF(L9="BR",IFERROR(VLOOKUP(J9,Country_Codes!$H:$H,1,0)=J9,"Brazil State Code Error"),IF(L9="AU",IFERROR(VLOOKUP(J9,Country_Codes!$K:$K,1,0)=J9,"Australia State Code Error"),""))))) | AB9: =IF(OR(L9="US",L9="CA",L9="BR",L9="AU"),IF((EXACT(UPPER(J9),J9)),"","Country Code Casing"),IF(EXACT(J9,PROPER(J9)),"","Billing State casing")) | AC9: {=IFERROR(_xlfn.IFS(IF(AND(LEN(I9)=0,ISBLANK(I9)=FALSE),"",ISNUMBER(SEARCH(I9,H9))),"City/Postal Code/Country Found in Address",IF(AND(LEN(K9)=0,ISBLANK(K9)=FALSE),"",ISNUMBER(SEARCH(K9,H9))),"City/Postal Code/Country Found in Address",IF(AND(LEN(L9)=0,ISBLANK(L9)=FALSE),"",ISNUMBER(SEARCH(", "&L9,H9))),"City/Postal Code/Country Found in Address",IF(AND(LEN(J9)=0,ISBLANK(J9)=FALSE),"",ISNUMBER(SEARCH(", "&J9,H9))),"City/Postal Code/Country Found in Address",IF(AND(LEN(L9)=0,ISBLANK(L9)=FALSE),"",ISNUMBER(SEARCH(","&L9,H9))),"City/Postal Code/Country Found in Address",IF(AND(LEN(J9)=0,ISBLANK(J9)=FALSE),"",ISNUMBER(SEARCH(","&J9,H9))),"City/Postal Code/Country Found in Address"),"")} | AD9: =IF(ISNUMBER(SEARCH("PO",N9)),"PO# Entered in Tax ID Field","") | AE9: {=IFERROR(IF(VLOOKUP(LEFT(M9,MIN(SEARCH({1,2,3,4,5,6,7,8,9,0},M9&{1,2,3,4,5,6,7,8,9,0}))-1),Country_Codes!$N:$N,1,0)>0,"PO Number may be incorrect",""),"")} | AF9: =IF(N9="","",IF(EXACT(L9,LEFT(N9,2)),IF(EXACT(MID(N9,3,1)," "),"Check the Space inbetween County code & VAT",""),"Check the VAT Country Code Format")) | AG9: =IF((ISNUMBER(SEARCH("@",P9)))>0,"",IF(IF(--(ISNUMBER(SEARCH("'",P9)))>0,OR(EXACT(PROPER(P9),P9),EXACT((PROPER(LEFT(P9,FIND("'",P9)-2))&LOWER(MID(P9,FIND("'",P9)-1,1))&PROPER(MID(P9,FIND("'",P9)+0,LEN(P9)-FIND("'",P9)+1))),P9)),"Please check Billing Contact Casing")=TRUE,"","Please check Billing Contact casing")) | AH9: =IF(OR(L9="AS",L9="FM",L9="GU",L9="MH",L9="MP",L9="PW",L9="PR",L9="VI",L9="UM"),"US Territories Check","") | AI9: {=IF(G9="","",_xlfn.IFNA(_xlfn.IFS(L9=VLOOKUP(L9,Country_Codes!$M:$M,1,0)=TRUE,""),"Please check the country code"))} | AJ9: =IF(S9="","",S9&"; ")&IF(T9="","",T9&"; ")&IF(U9="","",U9&"; ")&IF(V9="","",V9&"; ")&IF(AF9="","",AF9&"; ")&IF(AG9="","",AG9&"; ")&IF(AH9="","",AH9&"; ")&IF(Z9="","",Z9&"; ")&IF(AA9="","",AA9&"; ")&IF(AB9="","",AB9&"; ")&IF(AC9="","",AC9&"; ")&IF(AD9="","",AD9&"; ")&IF(AE9="","",AE9&"; ")&IF(AI9="","",AI9&"; ")&IF(W9="","",W9&"; ")&IF(X9="","",X9&"; ")&IF(Y9="","",Y9&"; ") -> Billing Street - casing; | AM9: =(COUNTA(S9:V9)-COUNTIFS((S9:V9),""))+(COUNTA(AB9)-COUNTIFS((AB9),""))+(COUNTA(AG9)-COUNTIFS((AG9),"")) -> 1 | AN9: =(COUNTA(W9)-COUNTIFS((W9),""))+(COUNTA(Z9)-COUNTIFS((Z9),"")) -> 0 | AO9: =(COUNTA(AA9)-COUNTIFS((AA9),""))+(COUNTA(AC9:AE9)-COUNTIFS((AC9:AE9),""))+(COUNTA(AH9:AI9)-COUNTIFS((AH9:AI9),"")) -> 0 | AP9: =(COUNTA(X9:Y9)-COUNTIFS((X9:Y9),""))+(COUNTA(AF9)-COUNTIFS((AF9),"")) -> 0 | AQ9: =SUM(AM9:AP9) -> 1 | AV9: 45426 | AW9: SampleCo Ltd
A10: 45622 | B10: User 1 | C10: Billing Contact Name | E10: Smith Francis | F10: Sample Ltd | G10: ID_Num_5 | H10: Main Street | I10: London | K10: EC2V 7EE | L10: GB | M10: PO 030 | P10: Smith Frank | R10: =IF(G10=G9,"","Unique Record") | S10: =IF(F10="","",IF(EXACT(F10,(UPPER(F10))),"Account Upper Case","")) | T10: =IF(F10="","",IF(EXACT(F10,(LOWER(F10))),"Account Lower Case","")) | U10: =IF(EXACT(H10,PROPER(H10)),"","Billing Street - casing") | V10: =IF(EXACT(I10,PROPER(I10)),"","City - casing") | W10: =IF(OR(ISNUMBER(SEARCH("East",I10)),ISNUMBER(SEARCH("West",I10)),ISNUMBER(SEARCH("North",I10)),ISNUMBER(SEARCH("South",I10))),"",IF(OR(ISNUMBER(SEARCH("St.",I10)),ISNUMBER(SEARCH("St ",I10))),"Check St in city field",IF(RIGHT(I10,1)=".","Dot found in city field",""))) | X10: {=IF((SUMPRODUCT(--ISNUMBER(SEARCH({"!","@","#","$","%","^","&","~*","(",")","_","+","=","{","}","[","]","|","\",":",";","'","""","<",">",",",".","~?","/","~~","`"}, I10)))>0)=TRUE,"Special Characters Found in City","")} | Y10: {=IF((SUMPRODUCT(--ISNUMBER(SEARCH({"!","@","#","$","%","^","~*","(",")","_","+","=","{","}","[","]","|","\",":",";","'","""","<",">","~?","/","~~","`"},F10)))>0)=TRUE,"Special Characters Found in Account field","")} | Z10: {=IF(SUM(--ISNUMBER(SEARCH({1,2,3,4,5,6,7,8,9,0},MID(H10,(SEARCH(" E ",H10)-1),1))))+SUM(--ISNUMBER(SEARCH({1,2,3,4,5,6,7,8,9,0},MID(H10,(SEARCH(" E ",H10)+3),1))))=2,"",IF(SUM(--ISNUMBER(SEARCH({"Parte E","Apoquindo N"},H10)))>0,"",IF(OR(RIGHT(H10,3)=" NE",RIGHT(H10,3)=" NW",RIGHT(H10,3)=" SW",RIGHT(H10,3)=" SE",RIGHT(H10,2)=" N",RIGHT(H10,2)=" E",RIGHT(H10,2)=" W",RIGHT(H10,2)=" S",LEFT(H10,3)="NE ",LEFT(H10,3)="NW ",LEFT(H10,3)="SW ",LEFT(H10,3)="SE ",LEFT(H10,2)="N ",LEFT(H10,2)="E ",LEFT(H10,2)="W ",LEFT(H10,2)="S "),"Directional Check",IF(SUM(--ISNUMBER(SEARCH({" N "," E "," W "," S "," NE "," NW "," SW "," SE ","N.E","N.W","S.W","S.E","E.","N.","S.","W."},H10)))>0,"Directional Check",IF(SUM(--ISNUMBER(SEARCH({1,2,3,4,5,6,7,8,9,0},MID(H10,(SEARCH("nd ",H10)-1),1))))+SUM(--ISNUMBER(SEARCH({1,2,3,4,5,6,7,8,9,0},MID(H10,(SEARCH("rd ",H10)-1),1)))+SUM(--ISNUMBER(SEARCH({1,2,3,4,5,6,7,8,9,0},MID(H10,(SEARCH("st ",H10)-1),1))))+SUM(--ISNUMBER(SEARCH({1,2,3,4,5,6,7,8,9,0},MID(H10,(SEARCH("th ",H10)-1),1)))))>0,"","")))))} | AA10: =IF(IF(L10="US",IFERROR(VLOOKUP(J10,Country_Codes!$B:$B,1,0)=J10,"US State Code Error"),IF(L10="CA",IFERROR(VLOOKUP(J10,Country_Codes!$E:$E,1,0)=J10,"Canada State Code Error"),IF(L10="BR",IFERROR(VLOOKUP(J10,Country_Codes!$H:$H,1,0)=J10,"Brazil State Code Error"),IF(L10="AU",IFERROR(VLOOKUP(J10,Country_Codes!$K:$K,1,0)=J10,"Australia State Code Error"),""))))=TRUE,"",IF(L10="US",IFERROR(VLOOKUP(J10,Country_Codes!$B:$B,1,0)=J10,"US State Code Error"),IF(L10="CA",IFERROR(VLOOKUP(J10,Country_Codes!$E:$E,1,0)=J10,"Canada State Code Error"),IF(L10="BR",IFERROR(VLOOKUP(J10,Country_Codes!$H:$H,1,0)=J10,"Brazil State Code Error"),IF(L10="AU",IFERROR(VLOOKUP(J10,Country_Codes!$K:$K,1,0)=J10,"Australia State Code Error"),""))))) | AB10: =IF(OR(L10="US",L10="CA",L10="BR",L10="AU"),IF((EXACT(UPPER(J10),J10)),"","Country Code Casing"),IF(EXACT(J10,PROPER(J10)),"","Billing State casing")) | AC10: {=IFERROR(_xlfn.IFS(IF(AND(LEN(I10)=0,ISBLANK(I10)=FALSE),"",ISNUMBER(SEARCH(I10,H10))),"City/Postal Code/Country Found in Address",IF(AND(LEN(K10)=0,ISBLANK(K10)=FALSE),"",ISNUMBER(SEARCH(K10,H10))),"City/Postal Code/Country Found in Address",IF(AND(LEN(L10)=0,ISBLANK(L10)=FALSE),"",ISNUMBER(SEARCH(", "&L10,H10))),"City/Postal Code/Country Found in Address",IF(AND(LEN(J10)=0,ISBLANK(J10)=FALSE),"",ISNUMBER(SEARCH(", "&J10,H10))),"City/Postal Code/Country Found in Address",IF(AND(LEN(L10)=0,ISBLANK(L10)=FALSE),"",ISNUMBER(SEARCH(","&L10,H10))),"City/Postal Code/Country Found in Address",IF(AND(LEN(J10)=0,ISBLANK(J10)=FALSE),"",ISNUMBER(SEARCH(","&J10,H10))),"City/Postal Code/Country Found in Address"),"")} | AD10: =IF(ISNUMBER(SEARCH("PO",N10)),"PO# Entered in Tax ID Field","") | AE10: {=IFERROR(IF(VLOOKUP(LEFT(M10,MIN(SEARCH({1,2,3,4,5,6,7,8,9,0},M10&{1,2,3,4,5,6,7,8,9,0}))-1),Country_Codes!$N:$N,1,0)>0,"PO Number may be incorrect",""),"")} | AF10: =IF(N10="","",IF(EXACT(L10,LEFT(N10,2)),IF(EXACT(MID(N10,3,1)," "),"Check the Space inbetween County code & VAT",""),"Check the VAT Country Code Format")) | AG10: =IF((ISNUMBER(SEARCH("@",P10)))>0,"",IF(IF(--(ISNUMBER(SEARCH("'",P10)))>0,OR(EXACT(PROPER(P10),P10),EXACT((PROPER(LEFT(P10,FIND("'",P10)-2))&LOWER(MID(P10,FIND("'",P10)-1,1))&PROPER(MID(P10,FIND("'",P10)+0,LEN(P10)-FIND("'",P10)+1))),P10)),"Please check Billing Contact Casing")=TRUE,"","Please check Billing Contact casing")) | AH10: =IF(OR(L10="AS",L10="FM",L10="GU",L10="MH",L10="MP",L10="PW",L10="PR",L10="VI",L10="UM"),"US Territories Check","") | AI10: {=IF(G10="","",_xlfn.IFNA(_xlfn.IFS(L10=VLOOKUP(L10,Country_Codes!$M:$M,1,0)=TRUE,""),"Please check the country code"))} | AJ10: =IF(S10="","",S10&"; ")&IF(T10="","",T10&"; ")&IF(U10="","",U10&"; ")&IF(V10="","",V10&"; ")&IF(AF10="","",AF10&"; ")&IF(AG10="","",AG10&"; ")&IF(AH10="","",AH10&"; ")&IF(Z10="","",Z10&"; ")&IF(AA10="","",AA10&"; ")&IF(AB10="","",AB10&"; ")&IF(AC10="","",AC10&"; ")&IF(AD10="","",AD10&"; ")&IF(AE10="","",AE10&"; ")&IF(AI10="","",AI10&"; ")&IF(W10="","",W10&"; ")&IF(X10="","",X10&"; ")&IF(Y10="","",Y10&"; ") | AM10: =(COUNTA(S10:V10)-COUNTIFS((S10:V10),""))+(COUNTA(AB10)-COUNTIFS((AB10),""))+(COUNTA(AG10)-COUNTIFS((AG10),"")) -> 0 | AN10: =(COUNTA(W10)-COUNTIFS((W10),""))+(COUNTA(Z10)-COUNTIFS((Z10),"")) -> 0 | AO10: =(COUNTA(AA10)-COUNTIFS((AA10),""))+(COUNTA(AC10:AE10)-COUNTIFS((AC10:AE10),""))+(COUNTA(AH10:AI10)-COUNTIFS((AH10:AI10),"")) -> 0 | AP10: =(COUNTA(X10:Y10)-COUNTIFS((X10:Y10),""))+(COUNTA(AF10)-COUNTIFS((AF10),"")) -> 0 | AQ10: =SUM(AM10:AP10) -> 0 | AV10: 45427 | AW10: SampleCo Partners
A11: 45546 | B11: User 2 | C11: Bill To Contact | D11: ID-0006a000 | F11: Sample Technologies, Inc. | G11: ID_Num_6 | H11: 10000 Sample Way | I11: Redwood City | J11: CA | K11: 94063 | L11: US | P11: Accounts Payable | R11: =IF(G11=G10,"","Unique Record") -> Unique Record | S11: =IF(F11="","",IF(EXACT(F11,(UPPER(F11))),"Account Upper Case","")) | T11: =IF(F11="","",IF(EXACT(F11,(LOWER(F11))),"Account Lower Case","")) | U11: =IF(EXACT(H11,PROPER(H11)),"","Billing Street - casing") | V11: =IF(EXACT(I11,PROPER(I11)),"","City - casing") | W11: =IF(OR(ISNUMBER(SEARCH("East",I11)),ISNUMBER(SEARCH("West",I11)),ISNUMBER(SEARCH("North",I11)),ISNUMBER(SEARCH("South",I11))),"",IF(OR(ISNUMBER(SEARCH("St.",I11)),ISNUMBER(SEARCH("St ",I11))),"Check St in city field",IF(RIGHT(I11,1)=".","Dot found in city field",""))) | X11: {=IF((SUMPRODUCT(--ISNUMBER(SEARCH({"!","@","#","$","%","^","&","~*","(",")","_","+","=","{","}","[","]","|","\",":",";","'","""","<",">",",",".","~?","/","~~","`"}, I11)))>0)=TRUE,"Special Characters Found in City","")} | Y11: {=IF((SUMPRODUCT(--ISNUMBER(SEARCH({"!","@","#","$","%","^","~*","(",")","_","+","=","{","}","[","]","|","\",":",";","'","""","<",">","~?","/","~~","`"},F11)))>0)=TRUE,"Special Characters Found in Account field","")} | Z11: {=IF(SUM(--ISNUMBER(SEARCH({1,2,3,4,5,6,7,8,9,0},MID(H11,(SEARCH(" E ",H11)-1),1))))+SUM(--ISNUMBER(SEARCH({1,2,3,4,5,6,7,8,9,0},MID(H11,(SEARCH(" E ",H11)+3),1))))=2,"",IF(SUM(--ISNUMBER(SEARCH({"Parte E","Apoquindo N"},H11)))>0,"",IF(OR(RIGHT(H11,3)=" NE",RIGHT(H11,3)=" NW",RIGHT(H11,3)=" SW",RIGHT(H11,3)=" SE",RIGHT(H11,2)=" N",RIGHT(H11,2)=" E",RIGHT(H11,2)=" W",RIGHT(H11,2)=" S",LEFT(H11,3)="NE ",LEFT(H11,3)="NW ",LEFT(H11,3)="SW ",LEFT(H11,3)="SE ",LEFT(H11,2)="N ",LEFT(H11,2)="E ",LEFT(H11,2)="W ",LEFT(H11,2)="S "),"Directional Check",IF(SUM(--ISNUMBER(SEARCH({" N "," E "," W "," S "," NE "," NW "," SW "," SE ","N.E","N.W","S.W","S.E","E.","N.","S.","W."},H11)))>0,"Directional Check",IF(SUM(--ISNUMBER(SEARCH({1,2,3,4,5,6,7,8,9,0},MID(H11,(SEARCH("nd ",H11)-1),1))))+SUM(--ISNUMBER(SEARCH({1,2,3,4,5,6,7,8,9,0},MID(H11,(SEARCH("rd ",H11)-1),1)))+SUM(--ISNUMBER(SEARCH({1,2,3,4,5,6,7,8,9,0},MID(H11,(SEARCH("st ",H11)-1),1))))+SUM(--ISNUMBER(SEARCH({1,2,3,4,5,6,7,8,9,0},MID(H11,(SEARCH("th ",H11)-1),1)))))>0,"","")))))} | AA11: =IF(IF(L11="US",IFERROR(VLOOKUP(J11,Country_Codes!$B:$B,1,0)=J11,"US State Code Error"),IF(L11="CA",IFERROR(VLOOKUP(J11,Country_Codes!$E:$E,1,0)=J11,"Canada State Code Error"),IF(L11="BR",IFERROR(VLOOKUP(J11,Country_Codes!$H:$H,1,0)=J11,"Brazil State Code Error"),IF(L11="AU",IFERROR(VLOOKUP(J11,Country_Codes!$K:$K,1,0)=J11,"Australia State Code Error"),""))))=TRUE,"",IF(L11="US",IFERROR(VLOOKUP(J11,Country_Codes!$B:$B,1,0)=J11,"US State Code Error"),IF(L11="CA",IFERROR(VLOOKUP(J11,Country_Codes!$E:$E,1,0)=J11,"Canada State Code Error"),IF(L11="BR",IFERROR(VLOOKUP(J11,Country_Codes!$H:$H,1,0)=J11,"Brazil State Code Error"),IF(L11="AU",IFERROR(VLOOKUP(J11,Country_Codes!$K:$K,1,0)=J11,"Australia State Code Error"),""))))) | AB11: =IF(OR(L11="US",L11="CA",L11="BR",L11="AU"),IF((EXACT(UPPER(J11),J11)),"","Country Code Casing"),IF(EXACT(J11,PROPER(J11)),"","Billing State casing")) | AC11: {=IFERROR(_xlfn.IFS(IF(AND(LEN(I11)=0,ISBLANK(I11)=FALSE),"",ISNUMBER(SEARCH(I11,H11))),"City/Postal Code/Country Found in Address",IF(AND(LEN(K11)=0,ISBLANK(K11)=FALSE),"",ISNUMBER(SEARCH(K11,H11))),"City/Postal Code/Country Found in Address",IF(AND(LEN(L11)=0,ISBLANK(L11)=FALSE),"",ISNUMBER(SEARCH(", "&L11,H11))),"City/Postal Code/Country Found in Address",IF(AND(LEN(J11)=0,ISBLANK(J11)=FALSE),"",ISNUMBER(SEARCH(", "&J11,H11))),"City/Postal Code/Country Found in Address",IF(AND(LEN(L11)=0,ISBLANK(L11)=FALSE),"",ISNUMBER(SEARCH(","&L11,H11))),"City/Postal Code/Country Found in Address",IF(AND(LEN(J11)=0,ISBLANK(J11)=FALSE),"",ISNUMBER(SEARCH(","&J11,H11))),"City/Postal Code/Country Found in Address"),"")} | AD11: =IF(ISNUMBER(SEARCH("PO",N11)),"PO# Entered in Tax ID Field","") | AE11: {=IFERROR(IF(VLOOKUP(LEFT(M11,MIN(SEARCH({1,2,3,4,5,6,7,8,9,0},M11&{1,2,3,4,5,6,7,8,9,0}))-1),Country_Codes!$N:$N,1,0)>0,"PO Number may be incorrect",""),"")} | AF11: =IF(N11="","",IF(EXACT(L11,LEFT(N11,2)),IF(EXACT(MID(N11,3,1)," "),"Check the Space inbetween County code & VAT",""),"Check the VAT Country Code Format")) | AG11: =IF((ISNUMBER(SEARCH("@",P11)))>0,"",IF(IF(--(ISNUMBER(SEARCH("'",P11)))>0,OR(EXACT(PROPER(P11),P11),EXACT((PROPER(LEFT(P11,FIND("'",P11)-2))&LOWER(MID(P11,FIND("'",P11)-1,1))&PROPER(MID(P11,FIND("'",P11)+0,LEN(P11)-FIND("'",P11)+1))),P11)),"Please check Billing Contact Casing")=TRUE,"","Please check Billing Contact casing")) | AH11: =IF(OR(L11="AS",L11="FM",L11="GU",L11="MH",L11="MP",L11="PW",L11="PR",L11="VI",L11="UM"),"US Territories Check","") | AI11: {=IF(G11="","",_xlfn.IFNA(_xlfn.IFS(L11=VLOOKUP(L11,Country_Codes!$M:$M,1,0)=TRUE,""),"Please check the country code"))} | AJ11: =IF(S11="","",S11&"; ")&IF(T11="","",T11&"; ")&IF(U11="","",U11&"; ")&IF(V11="","",V11&"; ")&IF(AF11="","",AF11&"; ")&IF(AG11="","",AG11&"; ")&IF(AH11="","",AH11&"; ")&IF(Z11="","",Z11&"; ")&IF(AA11="","",AA11&"; ")&IF(AB11="","",AB11&"; ")&IF(AC11="","",AC11&"; ")&IF(AD11="","",AD11&"; ")&IF(AE11="","",AE11&"; ")&IF(AI11="","",AI11&"; ")&IF(W11="","",W11&"; ")&IF(X11="","",X11&"; ")&IF(Y11="","",Y11&"; ") | AM11: =(COUNTA(S11:V11)-COUNTIFS((S11:V11),""))+(COUNTA(AB11)-COUNTIFS((AB11),""))+(COUNTA(AG11)-COUNTIFS((AG11),"")) -> 0 | AN11: =(COUNTA(W11)-COUNTIFS((W11),""))+(COUNTA(Z11)-COUNTIFS((Z11),"")) -> 0 | AO11: =(COUNTA(AA11)-COUNTIFS((AA11),""))+(COUNTA(AC11:AE11)-COUNTIFS((AC11:AE11),""))+(COUNTA(AH11:AI11)-COUNTIFS((AH11:AI11),"")) -> 0 | AP11: =(COUNTA(X11:Y11)-COUNTIFS((X11:Y11),""))+(COUNTA(AF11)-COUNTIFS((AF11),"")) -> 0 | AQ11: =SUM(AM11:AP11) -> 0 | AV11: 45428 | AW11: SampleCo Products, Inc.
A12: 45546 | B12: User 2 | C12: Billing Contact Name | E12: Accounts Payable | F12: Sample Technologies, Inc. | G12: ID_Num_6 | H12: 10000 Sample Way | I12: Redwood City | J12: CA | K12: 94063 | L12: US | P12: Accounts Payable | R12: =IF(G12=G11,"","Unique Record") | S12: =IF(F12="","",IF(EXACT(F12,(UPPER(F12))),"Account Upper Case","")) | T12: =IF(F12="","",IF(EXACT(F12,(LOWER(F12))),"Account Lower Case","")) | U12: =IF(EXACT(H12,PROPER(H12)),"","Billing Street - casing") | V12: =IF(EXACT(I12,PROPER(I12)),"","City - casing") | W12: =IF(OR(ISNUMBER(SEARCH("East",I12)),ISNUMBER(SEARCH("West",I12)),ISNUMBER(SEARCH("North",I12)),ISNUMBER(SEARCH("South",I12))),"",IF(OR(ISNUMBER(SEARCH("St.",I12)),ISNUMBER(SEARCH("St ",I12))),"Check St in city field",IF(RIGHT(I12,1)=".","Dot found in city field",""))) | X12: {=IF((SUMPRODUCT(--ISNUMBER(SEARCH({"!","@","#","$","%","^","&","~*","(",")","_","+","=","{","}","[","]","|","\",":",";","'","""","<",">",",",".","~?","/","~~","`"}, I12)))>0)=TRUE,"Special Characters Found in City","")} | Y12: {=IF((SUMPRODUCT(--ISNUMBER(SEARCH({"!","@","#","$","%","^","~*","(",")","_","+","=","{","}","[","]","|","\",":",";","'","""","<",">","~?","/","~~","`"},F12)))>0)=TRUE,"Special Characters Found in Account field","")} | Z12: {=IF(SUM(--ISNUMBER(SEARCH({1,2,3,4,5,6,7,8,9,0},MID(H12,(SEARCH(" E ",H12)-1),1))))+SUM(--ISNUMBER(SEARCH({1,2,3,4,5,6,7,8,9,0},MID(H12,(SEARCH(" E ",H12)+3),1))))=2,"",IF(SUM(--ISNUMBER(SEARCH({"Parte E","Apoquindo N"},H12)))>0,"",IF(OR(RIGHT(H12,3)=" NE",RIGHT(H12,3)=" NW",RIGHT(H12,3)=" SW",RIGHT(H12,3)=" SE",RIGHT(H12,2)=" N",RIGHT(H12,2)=" E",RIGHT(H12,2)=" W",RIGHT(H12,2)=" S",LEFT(H12,3)="NE ",LEFT(H12,3)="NW ",LEFT(H12,3)="SW ",LEFT(H12,3)="SE ",LEFT(H12,2)="N ",LEFT(H12,2)="E ",LEFT(H12,2)="W ",LEFT(H12,2)="S "),"Directional Check",IF(SUM(--ISNUMBER(SEARCH({" N "," E "," W "," S "," NE "," NW "," SW "," SE ","N.E","N.W","S.W","S.E","E.","N.","S.","W."},H12)))>0,"Directional Check",IF(SUM(--ISNUMBER(SEARCH({1,2,3,4,5,6,7,8,9,0},MID(H12,(SEARCH("nd ",H12)-1),1))))+SUM(--ISNUMBER(SEARCH({1,2,3,4,5,6,7,8,9,0},MID(H12,(SEARCH("rd ",H12)-1),1)))+SUM(--ISNUMBER(SEARCH({1,2,3,4,5,6,7,8,9,0},MID(H12,(SEARCH("st ",H12)-1),1))))+SUM(--ISNUMBER(SEARCH({1,2,3,4,5,6,7,8,9,0},MID(H12,(SEARCH("th ",H12)-1),1)))))>0,"","")))))} | AA12: =IF(IF(L12="US",IFERROR(VLOOKUP(J12,Country_Codes!$B:$B,1,0)=J12,"US State Code Error"),IF(L12="CA",IFERROR(VLOOKUP(J12,Country_Codes!$E:$E,1,0)=J12,"Canada State Code Error"),IF(L12="BR",IFERROR(VLOOKUP(J12,Country_Codes!$H:$H,1,0)=J12,"Brazil State Code Error"),IF(L12="AU",IFERROR(VLOOKUP(J12,Country_Codes!$K:$K,1,0)=J12,"Australia State Code Error"),""))))=TRUE,"",IF(L12="US",IFERROR(VLOOKUP(J12,Country_Codes!$B:$B,1,0)=J12,"US State Code Error"),IF(L12="CA",IFERROR(VLOOKUP(J12,Country_Codes!$E:$E,1,0)=J12,"Canada State Code Error"),IF(L12="BR",IFERROR(VLOOKUP(J12,Country_Codes!$H:$H,1,0)=J12,"Brazil State Code Error"),IF(L12="AU",IFERROR(VLOOKUP(J12,Country_Codes!$K:$K,1,0)=J12,"Australia State Code Error"),""))))) | AB12: =IF(OR(L12="US",L12="CA",L12="BR",L12="AU"),IF((EXACT(UPPER(J12),J12)),"","Country Code Casing"),IF(EXACT(J12,PROPER(J12)),"","Billing State casing")) | AC12: {=IFERROR(_xlfn.IFS(IF(AND(LEN(I12)=0,ISBLANK(I12)=FALSE),"",ISNUMBER(SEARCH(I12,H12))),"City/Postal Code/Country Found in Address",IF(AND(LEN(K12)=0,ISBLANK(K12)=FALSE),"",ISNUMBER(SEARCH(K12,H12))),"City/Postal Code/Country Found in Address",IF(AND(LEN(L12)=0,ISBLANK(L12)=FALSE),"",ISNUMBER(SEARCH(", "&L12,H12))),"City/Postal Code/Country Found in Address",IF(AND(LEN(J12)=0,ISBLANK(J12)=FALSE),"",ISNUMBER(SEARCH(", "&J12,H12))),"City/Postal Code/Country Found in Address",IF(AND(LEN(L12)=0,ISBLANK(L12)=FALSE),"",ISNUMBER(SEARCH(","&L12,H12))),"City/Postal Code/Country Found in Address",IF(AND(LEN(J12)=0,ISBLANK(J12)=FALSE),"",ISNUMBER(SEARCH(","&J12,H12))),"City/Postal Code/Country Found in Address"),"")} | AD12: =IF(ISNUMBER(SEARCH("PO",N12)),"PO# Entered in Tax ID Field","") | AE12: {=IFERROR(IF(VLOOKUP(LEFT(M12,MIN(SEARCH({1,2,3,4,5,6,7,8,9,0},M12&{1,2,3,4,5,6,7,8,9,0}))-1),Country_Codes!$N:$N,1,0)>0,"PO Number may be incorrect",""),"")} | AF12: =IF(N12="","",IF(EXACT(L12,LEFT(N12,2)),IF(EXACT(MID(N12,3,1)," "),"Check the Space inbetween County code & VAT",""),"Check the VAT Country Code Format")) | AG12: =IF((ISNUMBER(SEARCH("@",P12)))>0,"",IF(IF(--(ISNUMBER(SEARCH("'",P12)))>0,OR(EXACT(PROPER(P12),P12),EXACT((PROPER(LEFT(P12,FIND("'",P12)-2))&LOWER(MID(P12,FIND("'",P12)-1,1))&PROPER(MID(P12,FIND("'",P12)+0,LEN(P12)-FIND("'",P12)+1))),P12)),"Please check Billing Contact Casing")=TRUE,"","Please check Billing Contact casing")) | AH12: =IF(OR(L12="AS",L12="FM",L12="GU",L12="MH",L12="MP",L12="PW",L12="PR",L12="VI",L12="UM"),"US Territories Check","") | AI12: {=IF(G12="","",_xlfn.IFNA(_xlfn.IFS(L12=VLOOKUP(L12,Country_Codes!$M:$M,1,0)=TRUE,""),"Please check the country code"))} | AJ12: =IF(S12="","",S12&"; ")&IF(T12="","",T12&"; ")&IF(U12="","",U12&"; ")&IF(V12="","",V12&"; ")&IF(AF12="","",AF12&"; ")&IF(AG12="","",AG12&"; ")&IF(AH12="","",AH12&"; ")&IF(Z12="","",Z12&"; ")&IF(AA12="","",AA12&"; ")&IF(AB12="","",AB12&"; ")&IF(AC12="","",AC12&"; ")&IF(AD12="","",AD12&"; ")&IF(AE12="","",AE12&"; ")&IF(AI12="","",AI12&"; ")&IF(W12="","",W12&"; ")&IF(X12="","",X12&"; ")&IF(Y12="","",Y12&"; ") | AM12: =(COUNTA(S12:V12)-COUNTIFS((S12:V12),""))+(COUNTA(AB12)-COUNTIFS((AB12),""))+(COUNTA(AG12)-COUNTIFS((AG12),"")) -> 0 | AN12: =(COUNTA(W12)-COUNTIFS((W12),""))+(COUNTA(Z12)-COUNTIFS((Z12),"")) -> 0 | AO12: =(COUNTA(AA12)-COUNTIFS((AA12),""))+(COUNTA(AC12:AE12)-COUNTIFS((AC12:AE12),""))+(COUNTA(AH12:AI12)-COUNTIFS((AH12:AI12),"")) -> 0 | AP12: =(COUNTA(X12:Y12)-COUNTIFS((X12:Y12),""))+(COUNTA(AF12)-COUNTIFS((AF12),"")) -> 0 | AQ12: =SUM(AM12:AP12) -> 0 | AV12: 45429 | AW12: SampleCo Technologies, Inc.
A13: 45636 | B13: User 2 | C13: PO Number | E13: _00575 | F13: Sample Technologies, Inc. | G13: ID_Num_6 | H13: 10000 Sample Way | I13: Redwood City | J13: CA | K13: 94063 | L13: US | P13: Accounts Payable | R13: =IF(G13=G12,"","Unique Record") | S13: =IF(F13="","",IF(EXACT(F13,(UPPER(F13))),"Account Upper Case","")) | T13: =IF(F13="","",IF(EXACT(F13,(LOWER(F13))),"Account Lower Case","")) | U13: =IF(EXACT(H13,PROPER(H13)),"","Billing Street - casing") | V13: =IF(EXACT(I13,PROPER(I13)),"","City - casing") | W13: =IF(OR(ISNUMBER(SEARCH("East",I13)),ISNUMBER(SEARCH("West",I13)),ISNUMBER(SEARCH("North",I13)),ISNUMBER(SEARCH("South",I13))),"",IF(OR(ISNUMBER(SEARCH("St.",I13)),ISNUMBER(SEARCH("St ",I13))),"Check St in city field",IF(RIGHT(I13,1)=".","Dot found in city field",""))) | X13: {=IF((SUMPRODUCT(--ISNUMBER(SEARCH({"!","@","#","$","%","^","&","~*","(",")","_","+","=","{","}","[","]","|","\",":",";","'","""","<",">",",",".","~?","/","~~","`"}, I13)))>0)=TRUE,"Special Characters Found in City","")} | Y13: {=IF((SUMPRODUCT(--ISNUMBER(SEARCH({"!","@","#","$","%","^","~*","(",")","_","+","=","{","}","[","]","|","\",":",";","'","""","<",">","~?","/","~~","`"},F13)))>0)=TRUE,"Special Characters Found in Account field","")} | Z13: {=IF(SUM(--ISNUMBER(SEARCH({1,2,3,4,5,6,7,8,9,0},MID(H13,(SEARCH(" E ",H13)-1),1))))+SUM(--ISNUMBER(SEARCH({1,2,3,4,5,6,7,8,9,0},MID(H13,(SEARCH(" E ",H13)+3),1))))=2,"",IF(SUM(--ISNUMBER(SEARCH({"Parte E","Apoquindo N"},H13)))>0,"",IF(OR(RIGHT(H13,3)=" NE",RIGHT(H13,3)=" NW",RIGHT(H13,3)=" SW",RIGHT(H13,3)=" SE",RIGHT(H13,2)=" N",RIGHT(H13,2)=" E",RIGHT(H13,2)=" W",RIGHT(H13,2)=" S",LEFT(H13,3)="NE ",LEFT(H13,3)="NW ",LEFT(H13,3)="SW ",LEFT(H13,3)="SE ",LEFT(H13,2)="N ",LEFT(H13,2)="E ",LEFT(H13,2)="W ",LEFT(H13,2)="S "),"Directional Check",IF(SUM(--ISNUMBER(SEARCH({" N "," E "," W "," S "," NE "," NW "," SW "," SE ","N.E","N.W","S.W","S.E","E.","N.","S.","W."},H13)))>0,"Directional Check",IF(SUM(--ISNUMBER(SEARCH({1,2,3,4,5,6,7,8,9,0},MID(H13,(SEARCH("nd ",H13)-1),1))))+SUM(--ISNUMBER(SEARCH({1,2,3,4,5,6,7,8,9,0},MID(H13,(SEARCH("rd ",H13)-1),1)))+SUM(--ISNUMBER(SEARCH({1,2,3,4,5,6,7,8,9,0},MID(H13,(SEARCH("st ",H13)-1),1))))+SUM(--ISNUMBER(SEARCH({1,2,3,4,5,6,7,8,9,0},MID(H13,(SEARCH("th ",H13)-1),1)))))>0,"","")))))} | AA13: =IF(IF(L13="US",IFERROR(VLOOKUP(J13,Country_Codes!$B:$B,1,0)=J13,"US State Code Error"),IF(L13="CA",IFERROR(VLOOKUP(J13,Country_Codes!$E:$E,1,0)=J13,"Canada State Code Error"),IF(L13="BR",IFERROR(VLOOKUP(J13,Country_Codes!$H:$H,1,0)=J13,"Brazil State Code Error"),IF(L13="AU",IFERROR(VLOOKUP(J13,Country_Codes!$K:$K,1,0)=J13,"Australia State Code Error"),""))))=TRUE,"",IF(L13="US",IFERROR(VLOOKUP(J13,Country_Codes!$B:$B,1,0)=J13,"US State Code Error"),IF(L13="CA",IFERROR(VLOOKUP(J13,Country_Codes!$E:$E,1,0)=J13,"Canada State Code Error"),IF(L13="BR",IFERROR(VLOOKUP(J13,Country_Codes!$H:$H,1,0)=J13,"Brazil State Code Error"),IF(L13="AU",IFERROR(VLOOKUP(J13,Country_Codes!$K:$K,1,0)=J13,"Australia State Code Error"),""))))) | AB13: =IF(OR(L13="US",L13="CA",L13="BR",L13="AU"),IF((EXACT(UPPER(J13),J13)),"","Country Code Casing"),IF(EXACT(J13,PROPER(J13)),"","Billing State casing")) | AC13: {=IFERROR(_xlfn.IFS(IF(AND(LEN(I13)=0,ISBLANK(I13)=FALSE),"",ISNUMBER(SEARCH(I13,H13))),"City/Postal Code/Country Found in Address",IF(AND(LEN(K13)=0,ISBLANK(K13)=FALSE),"",ISNUMBER(SEARCH(K13,H13))),"City/Postal Code/Country Found in Address",IF(AND(LEN(L13)=0,ISBLANK(L13)=FALSE),"",ISNUMBER(SEARCH(", "&L13,H13))),"City/Postal Code/Country Found in Address",IF(AND(LEN(J13)=0,ISBLANK(J13)=FALSE),"",ISNUMBER(SEARCH(", "&J13,H13))),"City/Postal Code/Country Found in Address",IF(AND(LEN(L13)=0,ISBLANK(L13)=FALSE),"",ISNUMBER(SEARCH(","&L13,H13))),"City/Postal Code/Country Found in Address",IF(AND(LEN(J13)=0,ISBLANK(J13)=FALSE),"",ISNUMBER(SEARCH(","&J13,H13))),"City/Postal Code/Country Found in Address"),"")} | AD13: =IF(ISNUMBER(SEARCH("PO",N13)),"PO# Entered in Tax ID Field","") | AE13: {=IFERROR(IF(VLOOKUP(LEFT(M13,MIN(SEARCH({1,2,3,4,5,6,7,8,9,0},M13&{1,2,3,4,5,6,7,8,9,0}))-1),Country_Codes!$N:$N,1,0)>0,"PO Number may be incorrect",""),"")} | AF13: =IF(N13="","",IF(EXACT(L13,LEFT(N13,2)),IF(EXACT(MID(N13,3,1)," "),"Check the Space inbetween County code & VAT",""),"Check the VAT Country Code Format")) | AG13: =IF((ISNUMBER(SEARCH("@",P13)))>0,"",IF(IF(--(ISNUMBER(SEARCH("'",P13)))>0,OR(EXACT(PROPER(P13),P13),EXACT((PROPER(LEFT(P13,FIND("'",P13)-2))&LOWER(MID(P13,FIND("'",P13)-1,1))&PROPER(MID(P13,FIND("'",P13)+0,LEN(P13)-FIND("'",P13)+1))),P13)),"Please check Billing Contact Casing")=TRUE,"","Please check Billing Contact casing")) | AH13: =IF(OR(L13="AS",L13="FM",L13="GU",L13="MH",L13="MP",L13="PW",L13="PR",L13="VI",L13="UM"),"US Territories Check","") | AI13: {=IF(G13="","",_xlfn.IFNA(_xlfn.IFS(L13=VLOOKUP(L13,Country_Codes!$M:$M,1,0)=TRUE,""),"Please check the country code"))} | AJ13: =IF(S13="","",S13&"; ")&IF(T13="","",T13&"; ")&IF(U13="","",U13&"; ")&IF(V13="","",V13&"; ")&IF(AF13="","",AF13&"; ")&IF(AG13="","",AG13&"; ")&IF(AH13="","",AH13&"; ")&IF(Z13="","",Z13&"; ")&IF(AA13="","",AA13&"; ")&IF(AB13="","",AB13&"; ")&IF(AC13="","",AC13&"; ")&IF(AD13="","",AD13&"; ")&IF(AE13="","",AE13&"; ")&IF(AI13="","",AI13&"; ")&IF(W13="","",W13&"; ")&IF(X13="","",X13&"; ")&IF(Y13="","",Y13&"; ") | AM13: =(COUNTA(S13:V13)-COUNTIFS((S13:V13),""))+(COUNTA(AB13)-COUNTIFS((AB13),""))+(COUNTA(AG13)-COUNTIFS((AG13),"")) -> 0 | AN13: =(COUNTA(W13)-COUNTIFS((W13),""))+(COUNTA(Z13)-COUNTIFS((Z13),"")) -> 0 | AO13: =(COUNTA(AA13)-COUNTIFS((AA13),""))+(COUNTA(AC13:AE13)-COUNTIFS((AC13:AE13),""))+(COUNTA(AH13:AI13)-COUNTIFS((AH13:AI13),"")) -> 0 | AP13: =(COUNTA(X13:Y13)-COUNTIFS((X13:Y13),""))+(COUNTA(AF13)-COUNTIFS((AF13),"")) -> 0 | AQ13: =SUM(AM13:AP13) -> 0 | AV13: 45430 | AW13: SampleCo, Inc.
A14: 45590 | B14: User 1 | C14: PO Number | D14: PO-007496 | E14: PO-017004 | F14: Sample, Inc. | G14: ID_Num_1 | H14: Suite 30000A, Street | I14: Bozeman! | J14: MT | K14: 59715 | L14: US | M14: PO-017 | P14: Accounts Payable | R14: =IF(G14=G13,"","Unique Record") -> Unique Record | S14: =IF(F14="","",IF(EXACT(F14,(UPPER(F14))),"Account Upper Case","")) | T14: =IF(F14="","",IF(EXACT(F14,(LOWER(F14))),"Account Lower Case","")) | U14: =IF(EXACT(H14,PROPER(H14)),"","Billing Street - casing") | V14: =IF(EXACT(I14,PROPER(I14)),"","City - casing") | W14: =IF(OR(ISNUMBER(SEARCH("East",I14)),ISNUMBER(SEARCH("West",I14)),ISNUMBER(SEARCH("North",I14)),ISNUMBER(SEARCH("South",I14))),"",IF(OR(ISNUMBER(SEARCH("St.",I14)),ISNUMBER(SEARCH("St ",I14))),"Check St in city field",IF(RIGHT(I14,1)=".","Dot found in city field",""))) | X14: {=IF((SUMPRODUCT(--ISNUMBER(SEARCH({"!","@","#","$","%","^","&","~*","(",")","_","+","=","{","}","[","]","|","\",":",";","'","""","<",">",",",".","~?","/","~~","`"}, I14)))>0)=TRUE,"Special Characters Found in City","")} -> Special Characters Found in City | Y14: {=IF((SUMPRODUCT(--ISNUMBER(SEARCH({"!","@","#","$","%","^","~*","(",")","_","+","=","{","}","[","]","|","\",":",";","'","""","<",">","~?","/","~~","`"},F14)))>0)=TRUE,"Special Characters Found in Account field","")} | Z14: {=IF(SUM(--ISNUMBER(SEARCH({1,2,3,4,5,6,7,8,9,0},MID(H14,(SEARCH(" E ",H14)-1),1))))+SUM(--ISNUMBER(SEARCH({1,2,3,4,5,6,7,8,9,0},MID(H14,(SEARCH(" E ",H14)+3),1))))=2,"",IF(SUM(--ISNUMBER(SEARCH({"Parte E","Apoquindo N"},H14)))>0,"",IF(OR(RIGHT(H14,3)=" NE",RIGHT(H14,3)=" NW",RIGHT(H14,3)=" SW",RIGHT(H14,3)=" SE",RIGHT(H14,2)=" N",RIGHT(H14,2)=" E",RIGHT(H14,2)=" W",RIGHT(H14,2)=" S",LEFT(H14,3)="NE ",LEFT(H14,3)="NW ",LEFT(H14,3)="SW ",LEFT(H14,3)="SE ",LEFT(H14,2)="N ",LEFT(H14,2)="E ",LEFT(H14,2)="W ",LEFT(H14,2)="S "),"Directional Check",IF(SUM(--ISNUMBER(SEARCH({" N "," E "," W "," S "," NE "," NW "," SW "," SE ","N.E","N.W","S.W","S.E","E.","N.","S.","W."},H14)))>0,"Directional Check",IF(SUM(--ISNUMBER(SEARCH({1,2,3,4,5,6,7,8,9,0},MID(H14,(SEARCH("nd ",H14)-1),1))))+SUM(--ISNUMBER(SEARCH({1,2,3,4,5,6,7,8,9,0},MID(H14,(SEARCH("rd ",H14)-1),1)))+SUM(--ISNUMBER(SEARCH({1,2,3,4,5,6,7,8,9,0},MID(H14,(SEARCH("st ",H14)-1),1))))+SUM(--ISNUMBER(SEARCH({1,2,3,4,5,6,7,8,9,0},MID(H14,(SEARCH("th ",H14)-1),1)))))>0,"","")))))} | AA14: =IF(IF(L14="US",IFERROR(VLOOKUP(J14,Country_Codes!$B:$B,1,0)=J14,"US State Code Error"),IF(L14="CA",IFERROR(VLOOKUP(J14,Country_Codes!$E:$E,1,0)=J14,"Canada State Code Error"),IF(L14="BR",IFERROR(VLOOKUP(J14,Country_Codes!$H:$H,1,0)=J14,"Brazil State Code Error"),IF(L14="AU",IFERROR(VLOOKUP(J14,Country_Codes!$K:$K,1,0)=J14,"Australia State Code Error"),""))))=TRUE,"",IF(L14="US",IFERROR(VLOOKUP(J14,Country_Codes!$B:$B,1,0)=J14,"US State Code Error"),IF(L14="CA",IFERROR(VLOOKUP(J14,Country_Codes!$E:$E,1,0)=J14,"Canada State Code Error"),IF(L14="BR",IFERROR(VLOOKUP(J14,Country_Codes!$H:$H,1,0)=J14,"Brazil State Code Error"),IF(L14="AU",IFERROR(VLOOKUP(J14,Country_Codes!$K:$K,1,0)=J14,"Australia State Code Error"),""))))) | AB14: =IF(OR(L14="US",L14="CA",L14="BR",L14="AU"),IF((EXACT(UPPER(J14),J14)),"","Country Code Casing"),IF(EXACT(J14,PROPER(J14)),"","Billing State casing")) | AC14: {=IFERROR(_xlfn.IFS(IF(AND(LEN(I14)=0,ISBLANK(I14)=FALSE),"",ISNUMBER(SEARCH(I14,H14))),"City/Postal Code/Country Found in Address",IF(AND(LEN(K14)=0,ISBLANK(K14)=FALSE),"",ISNUMBER(SEARCH(K14,H14))),"City/Postal Code/Country Found in Address",IF(AND(LEN(L14)=0,ISBLANK(L14)=FALSE),"",ISNUMBER(SEARCH(", "&L14,H14))),"City/Postal Code/Country Found in Address",IF(AND(LEN(J14)=0,ISBLANK(J14)=FALSE),"",ISNUMBER(SEARCH(", "&J14,H14))),"City/Postal Code/Country Found in Address",IF(AND(LEN(L14)=0,ISBLANK(L14)=FALSE),"",ISNUMBER(SEARCH(","&L14,H14))),"City/Postal Code/Country Found in Address",IF(AND(LEN(J14)=0,ISBLANK(J14)=FALSE),"",ISNUMBER(SEARCH(","&J14,H14))),"City/Postal Code/Country Found in Address"),"")} | AD14: =IF(ISNUMBER(SEARCH("PO",N14)),"PO# Entered in Tax ID Field","") | AE14: {=IFERROR(IF(VLOOKUP(LEFT(M14,MIN(SEARCH({1,2,3,4,5,6,7,8,9,0},M14&{1,2,3,4,5,6,7,8,9,0}))-1),Country_Codes!$N:$N,1,0)>0,"PO Number may be incorrect",""),"")} | AF14: =IF(N14="","",IF(EXACT(L14,LEFT(N14,2)),IF(EXACT(MID(N14,3,1)," "),"Check the Space inbetween County code & VAT",""),"Check the VAT Country Code Format")) | AG14: =IF((ISNUMBER(SEARCH("@",P14)))>0,"",IF(IF(--(ISNUMBER(SEARCH("'",P14)))>0,OR(EXACT(PROPER(P14),P14),EXACT((PROPER(LEFT(P14,FIND("'",P14)-2))&LOWER(MID(P14,FIND("'",P14)-1,1))&PROPER(MID(P14,FIND("'",P14)+0,LEN(P14)-FIND("'",P14)+1))),P14)),"Please check Billing Contact Casing")=TRUE,"","Please check Billing Contact casing")) | AH14: =IF(OR(L14="AS",L14="FM",L14="GU",L14="MH",L14="MP",L14="PW",L14="PR",L14="VI",L14="UM"),"US Territories Check","") | AI14: {=IF(G14="","",_xlfn.IFNA(_xlfn.IFS(L14=VLOOKUP(L14,Country_Codes!$M:$M,1,0)=TRUE,""),"Please check the country code"))} | AJ14: =IF(S14="","",S14&"; ")&IF(T14="","",T14&"; ")&IF(U14="","",U14&"; ")&IF(V14="","",V14&"; ")&IF(AF14="","",AF14&"; ")&IF(AG14="","",AG14&"; ")&IF(AH14="","",AH14&"; ")&IF(Z14="","",Z14&"; ")&IF(AA14="","",AA14&"; ")&IF(AB14="","",AB14&"; ")&IF(AC14="","",AC14&"; ")&IF(AD14="","",AD14&"; ")&IF(AE14="","",AE14&"; ")&IF(AI14="","",AI14&"; ")&IF(W14="","",W14&"; ")&IF(X14="","",X14&"; ")&IF(Y14="","",Y14&"; ") -> Special Characters Found in City; | AM14: =(COUNTA(S14:V14)-COUNTIFS((S14:V14),""))+(COUNTA(AB14)-COUNTIFS((AB14),""))+(COUNTA(AG14)-COUNTIFS((AG14),"")) -> 0 | AN14: =(COUNTA(W14)-COUNTIFS((W14),""))+(COUNTA(Z14)-COUNTIFS((Z14),"")) -> 0 | AO14: =(COUNTA(AA14)-COUNTIFS((AA14),""))+(COUNTA(AC14:AE14)-COUNTIFS((AC14:AE14),""))+(COUNTA(AH14:AI14)-COUNTIFS((AH14:AI14),"")) -> 0 | AP14: =(COUNTA(X14:Y14)-COUNTIFS((X14:Y14),""))+(COUNTA(AF14)-COUNTIFS((AF14),"")) -> 1 | AQ14: =SUM(AM14:AP14) -> 1 | AV14: 45431 | AW14: SampleCorp Ltd
A15: 45594 | B15: User 1 | C15: Account Name | D15: Sample Inc. | E15: Sample, Inc. | F15: Sample, Inc. | G15: ID_Num_1 | H15: Suite 30000A, Street | I15: Bozeman | J15: MT | K15: 59715 | L15: US | M15: PO-017 | P15: Accounts Payable | R15: =IF(G15=G14,"","Unique Record") | S15: =IF(F15="","",IF(EXACT(F15,(UPPER(F15))),"Account Upper Case","")) | T15: =IF(F15="","",IF(EXACT(F15,(LOWER(F15))),"Account Lower Case","")) | U15: =IF(EXACT(H15,PROPER(H15)),"","Billing Street - casing") | V15: =IF(EXACT(I15,PROPER(I15)),"","City - casing") | W15: =IF(OR(ISNUMBER(SEARCH("East",I15)),ISNUMBER(SEARCH("West",I15)),ISNUMBER(SEARCH("North",I15)),ISNUMBER(SEARCH("South",I15))),"",IF(OR(ISNUMBER(SEARCH("St.",I15)),ISNUMBER(SEARCH("St ",I15))),"Check St in city field",IF(RIGHT(I15,1)=".","Dot found in city field",""))) | X15: {=IF((SUMPRODUCT(--ISNUMBER(SEARCH({"!","@","#","$","%","^","&","~*","(",")","_","+","=","{","}","[","]","|","\",":",";","'","""","<",">",",",".","~?","/","~~","`"}, I15)))>0)=TRUE,"Special Characters Found in City","")} | Y15: {=IF((SUMPRODUCT(--ISNUMBER(SEARCH({"!","@","#","$","%","^","~*","(",")","_","+","=","{","}","[","]","|","\",":",";","'","""","<",">","~?","/","~~","`"},F15)))>0)=TRUE,"Special Characters Found in Account field","")} | Z15: {=IF(SUM(--ISNUMBER(SEARCH({1,2,3,4,5,6,7,8,9,0},MID(H15,(SEARCH(" E ",H15)-1),1))))+SUM(--ISNUMBER(SEARCH({1,2,3,4,5,6,7,8,9,0},MID(H15,(SEARCH(" E ",H15)+3),1))))=2,"",IF(SUM(--ISNUMBER(SEARCH({"Parte E","Apoquindo N"},H15)))>0,"",IF(OR(RIGHT(H15,3)=" NE",RIGHT(H15,3)=" NW",RIGHT(H15,3)=" SW",RIGHT(H15,3)=" SE",RIGHT(H15,2)=" N",RIGHT(H15,2)=" E",RIGHT(H15,2)=" W",RIGHT(H15,2)=" S",LEFT(H15,3)="NE ",LEFT(H15,3)="NW ",LEFT(H15,3)="SW ",LEFT(H15,3)="SE ",LEFT(H15,2)="N ",LEFT(H15,2)="E ",LEFT(H15,2)="W ",LEFT(H15,2)="S "),"Directional Check",IF(SUM(--ISNUMBER(SEARCH({" N "," E "," W "," S "," NE "," NW "," SW "," SE ","N.E","N.W","S.W","S.E","E.","N.","S.","W."},H15)))>0,"Directional Check",IF(SUM(--ISNUMBER(SEARCH({1,2,3,4,5,6,7,8,9,0},MID(H15,(SEARCH("nd ",H15)-1),1))))+SUM(--ISNUMBER(SEARCH({1,2,3,4,5,6,7,8,9,0},MID(H15,(SEARCH("rd ",H15)-1),1)))+SUM(--ISNUMBER(SEARCH({1,2,3,4,5,6,7,8,9,0},MID(H15,(SEARCH("st ",H15)-1),1))))+SUM(--ISNUMBER(SEARCH({1,2,3,4,5,6,7,8,9,0},MID(H15,(SEARCH("th ",H15)-1),1)))))>0,"","")))))} | AA15: =IF(IF(L15="US",IFERROR(VLOOKUP(J15,Country_Codes!$B:$B,1,0)=J15,"US State Code Error"),IF(L15="CA",IFERROR(VLOOKUP(J15,Country_Codes!$E:$E,1,0)=J15,"Canada State Code Error"),IF(L15="BR",IFERROR(VLOOKUP(J15,Country_Codes!$H:$H,1,0)=J15,"Brazil State Code Error"),IF(L15="AU",IFERROR(VLOOKUP(J15,Country_Codes!$K:$K,1,0)=J15,"Australia State Code Error"),""))))=TRUE,"",IF(L15="US",IFERROR(VLOOKUP(J15,Country_Codes!$B:$B,1,0)=J15,"US State Code Error"),IF(L15="CA",IFERROR(VLOOKUP(J15,Country_Codes!$E:$E,1,0)=J15,"Canada State Code Error"),IF(L15="BR",IFERROR(VLOOKUP(J15,Country_Codes!$H:$H,1,0)=J15,"Brazil State Code Error"),IF(L15="AU",IFERROR(VLOOKUP(J15,Country_Codes!$K:$K,1,0)=J15,"Australia State Code Error"),""))))) | AB15: =IF(OR(L15="US",L15="CA",L15="BR",L15="AU"),IF((EXACT(UPPER(J15),J15)),"","Country Code Casing"),IF(EXACT(J15,PROPER(J15)),"","Billing State casing")) | AC15: {=IFERROR(_xlfn.IFS(IF(AND(LEN(I15)=0,ISBLANK(I15)=FALSE),"",ISNUMBER(SEARCH(I15,H15))),"City/Postal Code/Country Found in Address",IF(AND(LEN(K15)=0,ISBLANK(K15)=FALSE),"",ISNUMBER(SEARCH(K15,H15))),"City/Postal Code/Country Found in Address",IF(AND(LEN(L15)=0,ISBLANK(L15)=FALSE),"",ISNUMBER(SEARCH(", "&L15,H15))),"City/Postal Code/Country Found in Address",IF(AND(LEN(J15)=0,ISBLANK(J15)=FALSE),"",ISNUMBER(SEARCH(", "&J15,H15))),"City/Postal Code/Country Found in Address",IF(AND(LEN(L15)=0,ISBLANK(L15)=FALSE),"",ISNUMBER(SEARCH(","&L15,H15))),"City/Postal Code/Country Found in Address",IF(AND(LEN(J15)=0,ISBLANK(J15)=FALSE),"",ISNUMBER(SEARCH(","&J15,H15))),"City/Postal Code/Country Found in Address"),"")} | AD15: =IF(ISNUMBER(SEARCH("PO",N15)),"PO# Entered in Tax ID Field","") | AE15: {=IFERROR(IF(VLOOKUP(LEFT(M15,MIN(SEARCH({1,2,3,4,5,6,7,8,9,0},M15&{1,2,3,4,5,6,7,8,9,0}))-1),Country_Codes!$N:$N,1,0)>0,"PO Number may be incorrect",""),"")} | AF15: =IF(N15="","",IF(EXACT(L15,LEFT(N15,2)),IF(EXACT(MID(N15,3,1)," "),"Check the Space inbetween County code & VAT",""),"Check the VAT Country Code Format")) | AG15: =IF((ISNUMBER(SEARCH("@",P15)))>0,"",IF(IF(--(ISNUMBER(SEARCH("'",P15)))>0,OR(EXACT(PROPER(P15),P15),EXACT((PROPER(LEFT(P15,FIND("'",P15)-2))&LOWER(MID(P15,FIND("'",P15)-1,1))&PROPER(MID(P15,FIND("'",P15)+0,LEN(P15)-FIND("'",P15)+1))),P15)),"Please check Billing Contact Casing")=TRUE,"","Please check Billing Contact casing")) | AH15: =IF(OR(L15="AS",L15="FM",L15="GU",L15="MH",L15="MP",L15="PW",L15="PR",L15="VI",L15="UM"),"US Territories Check","") | AI15: {=IF(G15="","",_xlfn.IFNA(_xlfn.IFS(L15=VLOOKUP(L15,Country_Codes!$M:$M,1,0)=TRUE,""),"Please check the country code"))} | AJ15: =IF(S15="","",S15&"; ")&IF(T15="","",T15&"; ")&IF(U15="","",U15&"; ")&IF(V15="","",V15&"; ")&IF(AF15="","",AF15&"; ")&IF(AG15="","",AG15&"; ")&IF(AH15="","",AH15&"; ")&IF(Z15="","",Z15&"; ")&IF(AA15="","",AA15&"; ")&IF(AB15="","",AB15&"; ")&IF(AC15="","",AC15&"; ")&IF(AD15="","",AD15&"; ")&IF(AE15="","",AE15&"; ")&IF(AI15="","",AI15&"; ")&IF(W15="","",W15&"; ")&IF(X15="","",X15&"; ")&IF(Y15="","",Y15&"; ") | AM15: =(COUNTA(S15:V15)-COUNTIFS((S15:V15),""))+(COUNTA(AB15)-COUNTIFS((AB15),""))+(COUNTA(AG15)-COUNTIFS((AG15),"")) -> 0 | AN15: =(COUNTA(W15)-COUNTIFS((W15),""))+(COUNTA(Z15)-COUNTIFS((Z15),"")) -> 0 | AO15: =(COUNTA(AA15)-COUNTIFS((AA15),""))+(COUNTA(AC15:AE15)-COUNTIFS((AC15:AE15),""))+(COUNTA(AH15:AI15)-COUNTIFS((AH15:AI15),"")) -> 0 | AP15: =(COUNTA(X15:Y15)-COUNTIFS((X15:Y15),""))+(COUNTA(AF15)-COUNTIFS((AF15),"")) -> 0 | AQ15: =SUM(AM15:AP15) -> 0 | AV15: 45432 | AW15: SampleCorp Partners
A16: 45596 | B16: User 2 | C16: Bill To Contact | D16: ID-0001a000 | E16: ID-0002a000 | F16: Sample Partners | G16: ID_Num_2 | H16: 50000 Street | I16: Dallas | J16: TX | K16: 75201 | L16: US | O16: Justin Frank | R16: =IF(G16=G15,"","Unique Record") -> Unique Record | S16: =IF(F16="","",IF(EXACT(F16,(UPPER(F16))),"Account Upper Case","")) | T16: =IF(F16="","",IF(EXACT(F16,(LOWER(F16))),"Account Lower Case","")) | U16: =IF(EXACT(H16,PROPER(H16)),"","Billing Street - casing") | V16: =IF(EXACT(I16,PROPER(I16)),"","City - casing") | W16: =IF(OR(ISNUMBER(SEARCH("East",I16)),ISNUMBER(SEARCH("West",I16)),ISNUMBER(SEARCH("North",I16)),ISNUMBER(SEARCH("South",I16))),"",IF(OR(ISNUMBER(SEARCH("St.",I16)),ISNUMBER(SEARCH("St ",I16))),"Check St in city field",IF(RIGHT(I16,1)=".","Dot found in city field",""))) | X16: {=IF((SUMPRODUCT(--ISNUMBER(SEARCH({"!","@","#","$","%","^","&","~*","(",")","_","+","=","{","}","[","]","|","\",":",";","'","""","<",">",",",".","~?","/","~~","`"}, I16)))>0)=TRUE,"Special Characters Found in City","")} | Y16: {=IF((SUMPRODUCT(--ISNUMBER(SEARCH({"!","@","#","$","%","^","~*","(",")","_","+","=","{","}","[","]","|","\",":",";","'","""","<",">","~?","/","~~","`"},F16)))>0)=TRUE,"Special Characters Found in Account field","")} | Z16: {=IF(SUM(--ISNUMBER(SEARCH({1,2,3,4,5,6,7,8,9,0},MID(H16,(SEARCH(" E ",H16)-1),1))))+SUM(--ISNUMBER(SEARCH({1,2,3,4,5,6,7,8,9,0},MID(H16,(SEARCH(" E ",H16)+3),1))))=2,"",IF(SUM(--ISNUMBER(SEARCH({"Parte E","Apoquindo N"},H16)))>0,"",IF(OR(RIGHT(H16,3)=" NE",RIGHT(H16,3)=" NW",RIGHT(H16,3)=" SW",RIGHT(H16,3)=" SE",RIGHT(H16,2)=" N",RIGHT(H16,2)=" E",RIGHT(H16,2)=" W",RIGHT(H16,2)=" S",LEFT(H16,3)="NE ",LEFT(H16,3)="NW ",LEFT(H16,3)="SW ",LEFT(H16,3)="SE ",LEFT(H16,2)="N ",LEFT(H16,2)="E ",LEFT(H16,2)="W ",LEFT(H16,2)="S "),"Directional Check",IF(SUM(--ISNUMBER(SEARCH({" N "," E "," W "," S "," NE "," NW "," SW "," SE ","N.E","N.W","S.W","S.E","E.","N.","S.","W."},H16)))>0,"Directional Check",IF(SUM(--ISNUMBER(SEARCH({1,2,3,4,5,6,7,8,9,0},MID(H16,(SEARCH("nd ",H16)-1),1))))+SUM(--ISNUMBER(SEARCH({1,2,3,4,5,6,7,8,9,0},MID(H16,(SEARCH("rd ",H16)-1),1)))+SUM(--ISNUMBER(SEARCH({1,2,3,4,5,6,7,8,9,0},MID(H16,(SEARCH("st ",H16)-1),1))))+SUM(--ISNUMBER(SEARCH({1,2,3,4,5,6,7,8,9,0},MID(H16,(SEARCH("th ",H16)-1),1)))))>0,"","")))))} | AA16: =IF(IF(L16="US",IFERROR(VLOOKUP(J16,Country_Codes!$B:$B,1,0)=J16,"US State Code Error"),IF(L16="CA",IFERROR(VLOOKUP(J16,Country_Codes!$E:$E,1,0)=J16,"Canada State Code Error"),IF(L16="BR",IFERROR(VLOOKUP(J16,Country_Codes!$H:$H,1,0)=J16,"Brazil State Code Error"),IF(L16="AU",IFERROR(VLOOKUP(J16,Country_Codes!$K:$K,1,0)=J16,"Australia State Code Error"),""))))=TRUE,"",IF(L16="US",IFERROR(VLOOKUP(J16,Country_Codes!$B:$B,1,0)=J16,"US State Code Error"),IF(L16="CA",IFERROR(VLOOKUP(J16,Country_Codes!$E:$E,1,0)=J16,"Canada State Code Error"),IF(L16="BR",IFERROR(VLOOKUP(J16,Country_Codes!$H:$H,1,0)=J16,"Brazil State Code Error"),IF(L16="AU",IFERROR(VLOOKUP(J16,Country_Codes!$K:$K,1,0)=J16,"Australia State Code Error"),""))))) | AB16: =IF(OR(L16="US",L16="CA",L16="BR",L16="AU"),IF((EXACT(UPPER(J16),J16)),"","Country Code Casing"),IF(EXACT(J16,PROPER(J16)),"","Billing State casing")) | AC16: {=IFERROR(_xlfn.IFS(IF(AND(LEN(I16)=0,ISBLANK(I16)=FALSE),"",ISNUMBER(SEARCH(I16,H16))),"City/Postal Code/Country Found in Address",IF(AND(LEN(K16)=0,ISBLANK(K16)=FALSE),"",ISNUMBER(SEARCH(K16,H16))),"City/Postal Code/Country Found in Address",IF(AND(LEN(L16)=0,ISBLANK(L16)=FALSE),"",ISNUMBER(SEARCH(", "&L16,H16))),"City/Postal Code/Country Found in Address",IF(AND(LEN(J16)=0,ISBLANK(J16)=FALSE),"",ISNUMBER(SEARCH(", "&J16,H16))),"City/Postal Code/Country Found in Address",IF(AND(LEN(L16)=0,ISBLANK(L16)=FALSE),"",ISNUMBER(SEARCH(","&L16,H16))),"City/Postal Code/Country Found in Address",IF(AND(LEN(J16)=0,ISBLANK(J16)=FALSE),"",ISNUMBER(SEARCH(","&J16,H16))),"City/Postal Code/Country Found in Address"),"")} | AD16: =IF(ISNUMBER(SEARCH("PO",N16)),"PO# Entered in Tax ID Field","") | AE16: {=IFERROR(IF(VLOOKUP(LEFT(M16,MIN(SEARCH({1,2,3,4,5,6,7,8,9,0},M16&{1,2,3,4,5,6,7,8,9,0}))-1),Country_Codes!$N:$N,1,0)>0,"PO Number may be incorrect",""),"")} | AF16: =IF(N16="","",IF(EXACT(L16,LEFT(N16,2)),IF(EXACT(MID(N16,3,1)," "),"Check the Space inbetween County code & VAT",""),"Check the VAT Country Code Format")) | AG16: =IF((ISNUMBER(SEARCH("@",P16)))>0,"",IF(IF(--(ISNUMBER(SEARCH("'",P16)))>0,OR(EXACT(PROPER(P16),P16),EXACT((PROPER(LEFT(P16,FIND("'",P16)-2))&LOWER(MID(P16,FIND("'",P16)-1,1))&PROPER(MID(P16,FIND("'",P16)+0,LEN(P16)-FIND("'",P16)+1))),P16)),"Please check Billing Contact Casing")=TRUE,"","Please check Billing Contact casing")) | AH16: =IF(OR(L16="AS",L16="FM",L16="GU",L16="MH",L16="MP",L16="PW",L16="PR",L16="VI",L16="UM"),"US Territories Check","") | AI16: {=IF(G16="","",_xlfn.IFNA(_xlfn.IFS(L16=VLOOKUP(L16,Country_Codes!$M:$M,1,0)=TRUE,""),"Please check the country code"))} | AJ16: =IF(S16="","",S16&"; ")&IF(T16="","",T16&"; ")&IF(U16="","",U16&"; ")&IF(V16="","",V16&"; ")&IF(AF16="","",AF16&"; ")&IF(AG16="","",AG16&"; ")&IF(AH16="","",AH16&"; ")&IF(Z16="","",Z16&"; ")&IF(AA16="","",AA16&"; ")&IF(AB16="","",AB16&"; ")&IF(AC16="","",AC16&"; ")&IF(AD16="","",AD16&"; ")&IF(AE16="","",AE16&"; ")&IF(AI16="","",AI16&"; ")&IF(W16="","",W16&"; ")&IF(X16="","",X16&"; ")&IF(Y16="","",Y16&"; ") | AM16: =(COUNTA(S16:V16)-COUNTIFS((S16:V16),""))+(COUNTA(AB16)-COUNTIFS((AB16),""))+(COUNTA(AG16)-COUNTIFS((AG16),"")) -> 0 | AN16: =(COUNTA(W16)-COUNTIFS((W16),""))+(COUNTA(Z16)-COUNTIFS((Z16),"")) -> 0 | AO16: =(COUNTA(AA16)-COUNTIFS((AA16),""))+(COUNTA(AC16:AE16)-COUNTIFS((AC16:AE16),""))+(COUNTA(AH16:AI16)-COUNTIFS((AH16:AI16),"")) -> 0 | AP16: =(COUNTA(X16:Y16)-COUNTIFS((X16:Y16),""))+(COUNTA(AF16)-COUNTIFS((AF16),"")) -> 0 | AQ16: =SUM(AM16:AP16) -> 0 | AV16: 45433 | AW16: SampleCorp Products, Inc.
A17: 45574 | B17: User 1 | C17: Bill To Contact | D17: ID-0003a000 | E17: ID-0004a000 | F17: Sample Products, Inc. | G17: ID_Num_3 | H17: 10000 Sample Court, Suite 200 | I17: Mississauga | J17: ON | K17: L5N 5R5 | L17: CA | M17: 5600004 | O17: Smith Frank | R17: =IF(G17=G16,"","Unique Record") -> Unique Record | S17: =IF(F17="","",IF(EXACT(F17,(UPPER(F17))),"Account Upper Case","")) | T17: =IF(F17="","",IF(EXACT(F17,(LOWER(F17))),"Account Lower Case","")) | U17: =IF(EXACT(H17,PROPER(H17)),"","Billing Street - casing") | V17: =IF(EXACT(I17,PROPER(I17)),"","City - casing") | W17: =IF(OR(ISNUMBER(SEARCH("East",I17)),ISNUMBER(SEARCH("West",I17)),ISNUMBER(SEARCH("North",I17)),ISNUMBER(SEARCH("South",I17))),"",IF(OR(ISNUMBER(SEARCH("St.",I17)),ISNUMBER(SEARCH("St ",I17))),"Check St in city field",IF(RIGHT(I17,1)=".","Dot found in city field",""))) | X17: {=IF((SUMPRODUCT(--ISNUMBER(SEARCH({"!","@","#","$","%","^","&","~*","(",")","_","+","=","{","}","[","]","|","\",":",";","'","""","<",">",",",".","~?","/","~~","`"}, I17)))>0)=TRUE,"Special Characters Found in City","")} | Y17: {=IF((SUMPRODUCT(--ISNUMBER(SEARCH({"!","@","#","$","%","^","~*","(",")","_","+","=","{","}","[","]","|","\",":",";","'","""","<",">","~?","/","~~","`"},F17)))>0)=TRUE,"Special Characters Found in Account field","")} | Z17: {=IF(SUM(--ISNUMBER(SEARCH({1,2,3,4,5,6,7,8,9,0},MID(H17,(SEARCH(" E ",H17)-1),1))))+SUM(--ISNUMBER(SEARCH({1,2,3,4,5,6,7,8,9,0},MID(H17,(SEARCH(" E ",H17)+3),1))))=2,"",IF(SUM(--ISNUMBER(SEARCH({"Parte E","Apoquindo N"},H17)))>0,"",IF(OR(RIGHT(H17,3)=" NE",RIGHT(H17,3)=" NW",RIGHT(H17,3)=" SW",RIGHT(H17,3)=" SE",RIGHT(H17,2)=" N",RIGHT(H17,2)=" E",RIGHT(H17,2)=" W",RIGHT(H17,2)=" S",LEFT(H17,3)="NE ",LEFT(H17,3)="NW ",LEFT(H17,3)="SW ",LEFT(H17,3)="SE ",LEFT(H17,2)="N ",LEFT(H17,2)="E ",LEFT(H17,2)="W ",LEFT(H17,2)="S "),"Directional Check",IF(SUM(--ISNUMBER(SEARCH({" N "," E "," W "," S "," NE "," NW "," SW "," SE ","N.E","N.W","S.W","S.E","E.","N.","S.","W."},H17)))>0,"Directional Check",IF(SUM(--ISNUMBER(SEARCH({1,2,3,4,5,6,7,8,9,0},MID(H17,(SEARCH("nd ",H17)-1),1))))+SUM(--ISNUMBER(SEARCH({1,2,3,4,5,6,7,8,9,0},MID(H17,(SEARCH("rd ",H17)-1),1)))+SUM(--ISNUMBER(SEARCH({1,2,3,4,5,6,7,8,9,0},MID(H17,(SEARCH("st ",H17)-1),1))))+SUM(--ISNUMBER(SEARCH({1,2,3,4,5,6,7,8,9,0},MID(H17,(SEARCH("th ",H17)-1),1)))))>0,"","")))))} | AA17: =IF(IF(L17="US",IFERROR(VLOOKUP(J17,Country_Codes!$B:$B,1,0)=J17,"US State Code Error"),IF(L17="CA",IFERROR(VLOOKUP(J17,Country_Codes!$E:$E,1,0)=J17,"Canada State Code Error"),IF(L17="BR",IFERROR(VLOOKUP(J17,Country_Codes!$H:$H,1,0)=J17,"Brazil State Code Error"),IF(L17="AU",IFERROR(VLOOKUP(J17,Country_Codes!$K:$K,1,0)=J17,"Australia State Code Error"),""))))=TRUE,"",IF(L17="US",IFERROR(VLOOKUP(J17,Country_Codes!$B:$B,1,0)=J17,"US State Code Error"),IF(L17="CA",IFERROR(VLOOKUP(J17,Country_Codes!$E:$E,1,0)=J17,"Canada State Code Error"),IF(L17="BR",IFERROR(VLOOKUP(J17,Country_Codes!$H:$H,1,0)=J17,"Brazil State Code Error"),IF(L17="AU",IFERROR(VLOOKUP(J17,Country_Codes!$K:$K,1,0)=J17,"Australia State Code Error"),""))))) | AB17: =IF(OR(L17="US",L17="CA",L17="BR",L17="AU"),IF((EXACT(UPPER(J17),J17)),"","Country Code Casing"),IF(EXACT(J17,PROPER(J17)),"","Billing State casing")) | AC17: {=IFERROR(_xlfn.IFS(IF(AND(LEN(I17)=0,ISBLANK(I17)=FALSE),"",ISNUMBER(SEARCH(I17,H17))),"City/Postal Code/Country Found in Address",IF(AND(LEN(K17)=0,ISBLANK(K17)=FALSE),"",ISNUMBER(SEARCH(K17,H17))),"City/Postal Code/Country Found in Address",IF(AND(LEN(L17)=0,ISBLANK(L17)=FALSE),"",ISNUMBER(SEARCH(", "&L17,H17))),"City/Postal Code/Country Found in Address",IF(AND(LEN(J17)=0,ISBLANK(J17)=FALSE),"",ISNUMBER(SEARCH(", "&J17,H17))),"City/Postal Code/Country Found in Address",IF(AND(LEN(L17)=0,ISBLANK(L17)=FALSE),"",ISNUMBER(SEARCH(","&L17,H17))),"City/Postal Code/Country Found in Address",IF(AND(LEN(J17)=0,ISBLANK(J17)=FALSE),"",ISNUMBER(SEARCH(","&J17,H17))),"City/Postal Code/Country Found in Address"),"")} | AD17: =IF(ISNUMBER(SEARCH("PO",N17)),"PO# Entered in Tax ID Field","") | AE17: {=IFERROR(IF(VLOOKUP(LEFT(M17,MIN(SEARCH({1,2,3,4,5,6,7,8,9,0},M17&{1,2,3,4,5,6,7,8,9,0}))-1),Country_Codes!$N:$N,1,0)>0,"PO Number may be incorrect",""),"")} | AF17: =IF(N17="","",IF(EXACT(L17,LEFT(N17,2)),IF(EXACT(MID(N17,3,1)," "),"Check the Space inbetween County code & VAT",""),"Check the VAT Country Code Format")) | AG17: =IF((ISNUMBER(SEARCH("@",P17)))>0,"",IF(IF(--(ISNUMBER(SEARCH("'",P17)))>0,OR(EXACT(PROPER(P17),P17),EXACT((PROPER(LEFT(P17,FIND("'",P17)-2))&LOWER(MID(P17,FIND("'",P17)-1,1))&PROPER(MID(P17,FIND("'",P17)+0,LEN(P17)-FIND("'",P17)+1))),P17)),"Please check Billing Contact Casing")=TRUE,"","Please check Billing Contact casing")) | AH17: =IF(OR(L17="AS",L17="FM",L17="GU",L17="MH",L17="MP",L17="PW",L17="PR",L17="VI",L17="UM"),"US Territories Check","") | AI17: {=IF(G17="","",_xlfn.IFNA(_xlfn.IFS(L17=VLOOKUP(L17,Country_Codes!$M:$M,1,0)=TRUE,""),"Please check the country code"))} | AJ17: =IF(S17="","",S17&"; ")&IF(T17="","",T17&"; ")&IF(U17="","",U17&"; ")&IF(V17="","",V17&"; ")&IF(AF17="","",AF17&"; ")&IF(AG17="","",AG17&"; ")&IF(AH17="","",AH17&"; ")&IF(Z17="","",Z17&"; ")&IF(AA17="","",AA17&"; ")&IF(AB17="","",AB17&"; ")&IF(AC17="","",AC17&"; ")&IF(AD17="","",AD17&"; ")&IF(AE17="","",AE17&"; ")&IF(AI17="","",AI17&"; ")&IF(W17="","",W17&"; ")&IF(X17="","",X17&"; ")&IF(Y17="","",Y17&"; ") | AM17: =(COUNTA(S17:V17)-COUNTIFS((S17:V17),""))+(COUNTA(AB17)-COUNTIFS((AB17),""))+(COUNTA(AG17)-COUNTIFS((AG17),"")) -> 0 | AN17: =(COUNTA(W17)-COUNTIFS((W17),""))+(COUNTA(Z17)-COUNTIFS((Z17),"")) -> 0 | AO17: =(COUNTA(AA17)-COUNTIFS((AA17),""))+(COUNTA(AC17:AE17)-COUNTIFS((AC17:AE17),""))+(COUNTA(AH17:AI17)-COUNTIFS((AH17:AI17),"")) -> 0 | AP17: =(COUNTA(X17:Y17)-COUNTIFS((X17:Y17),""))+(COUNTA(AF17)-COUNTIFS((AF17),"")) -> 0 | AQ17: =SUM(AM17:AP17) -> 0 | AV17: 45434 | AW17: SampleCorp Technologies, Inc.
A18: 45393 | B18: User 3 | C18: PO Number | D18: 3587 | E18: 4490 | F18: Sample Products, Inc. | G18: ID_Num_3 | H18: 10000 Sample Court, Suite 200 | I18: Mississauga | J18: ON | K18: L5N 5R5 | L18: CA | M18: 5600004 | O18: Smith Frank | R18: =IF(G18=G17,"","Unique Record") | S18: =IF(F18="","",IF(EXACT(F18,(UPPER(F18))),"Account Upper Case","")) | T18: =IF(F18="","",IF(EXACT(F18,(LOWER(F18))),"Account Lower Case","")) | U18: =IF(EXACT(H18,PROPER(H18)),"","Billing Street - casing") | V18: =IF(EXACT(I18,PROPER(I18)),"","City - casing") | W18: =IF(OR(ISNUMBER(SEARCH("East",I18)),ISNUMBER(SEARCH("West",I18)),ISNUMBER(SEARCH("North",I18)),ISNUMBER(SEARCH("South",I18))),"",IF(OR(ISNUMBER(SEARCH("St.",I18)),ISNUMBER(SEARCH("St ",I18))),"Check St in city field",IF(RIGHT(I18,1)=".","Dot found in city field",""))) | X18: {=IF((SUMPRODUCT(--ISNUMBER(SEARCH({"!","@","#","$","%","^","&","~*","(",")","_","+","=","{","}","[","]","|","\",":",";","'","""","<",">",",",".","~?","/","~~","`"}, I18)))>0)=TRUE,"Special Characters Found in City","")} | Y18: {=IF((SUMPRODUCT(--ISNUMBER(SEARCH({"!","@","#","$","%","^","~*","(",")","_","+","=","{","}","[","]","|","\",":",";","'","""","<",">","~?","/","~~","`"},F18)))>0)=TRUE,"Special Characters Found in Account field","")} | Z18: {=IF(SUM(--ISNUMBER(SEARCH({1,2,3,4,5,6,7,8,9,0},MID(H18,(SEARCH(" E ",H18)-1),1))))+SUM(--ISNUMBER(SEARCH({1,2,3,4,5,6,7,8,9,0},MID(H18,(SEARCH(" E ",H18)+3),1))))=2,"",IF(SUM(--ISNUMBER(SEARCH({"Parte E","Apoquindo N"},H18)))>0,"",IF(OR(RIGHT(H18,3)=" NE",RIGHT(H18,3)=" NW",RIGHT(H18,3)=" SW",RIGHT(H18,3)=" SE",RIGHT(H18,2)=" N",RIGHT(H18,2)=" E",RIGHT(H18,2)=" W",RIGHT(H18,2)=" S",LEFT(H18,3)="NE ",LEFT(H18,3)="NW ",LEFT(H18,3)="SW ",LEFT(H18,3)="SE ",LEFT(H18,2)="N ",LEFT(H18,2)="E ",LEFT(H18,2)="W ",LEFT(H18,2)="S "),"Directional Check",IF(SUM(--ISNUMBER(SEARCH({" N "," E "," W "," S "," NE "," NW "," SW "," SE ","N.E","N.W","S.W","S.E","E.","N.","S.","W."},H18)))>0,"Directional Check",IF(SUM(--ISNUMBER(SEARCH({1,2,3,4,5,6,7,8,9,0},MID(H18,(SEARCH("nd ",H18)-1),1))))+SUM(--ISNUMBER(SEARCH({1,2,3,4,5,6,7,8,9,0},MID(H18,(SEARCH("rd ",H18)-1),1)))+SUM(--ISNUMBER(SEARCH({1,2,3,4,5,6,7,8,9,0},MID(H18,(SEARCH("st ",H18)-1),1))))+SUM(--ISNUMBER(SEARCH({1,2,3,4,5,6,7,8,9,0},MID(H18,(SEARCH("th ",H18)-1),1)))))>0,"","")))))} | AA18: =IF(IF(L18="US",IFERROR(VLOOKUP(J18,Country_Codes!$B:$B,1,0)=J18,"US State Code Error"),IF(L18="CA",IFERROR(VLOOKUP(J18,Country_Codes!$E:$E,1,0)=J18,"Canada State Code Error"),IF(L18="BR",IFERROR(VLOOKUP(J18,Country_Codes!$H:$H,1,0)=J18,"Brazil State Code Error"),IF(L18="AU",IFERROR(VLOOKUP(J18,Country_Codes!$K:$K,1,0)=J18,"Australia State Code Error"),""))))=TRUE,"",IF(L18="US",IFERROR(VLOOKUP(J18,Country_Codes!$B:$B,1,0)=J18,"US State Code Error"),IF(L18="CA",IFERROR(VLOOKUP(J18,Country_Codes!$E:$E,1,0)=J18,"Canada State Code Error"),IF(L18="BR",IFERROR(VLOOKUP(J18,Country_Codes!$H:$H,1,0)=J18,"Brazil State Code Error"),IF(L18="AU",IFERROR(VLOOKUP(J18,Country_Codes!$K:$K,1,0)=J18,"Australia State Code Error"),""))))) | AB18: =IF(OR(L18="US",L18="CA",L18="BR",L18="AU"),IF((EXACT(UPPER(J18),J18)),"","Country Code Casing"),IF(EXACT(J18,PROPER(J18)),"","Billing State casing")) | AC18: {=IFERROR(_xlfn.IFS(IF(AND(LEN(I18)=0,ISBLANK(I18)=FALSE),"",ISNUMBER(SEARCH(I18,H18))),"City/Postal Code/Country Found in Address",IF(AND(LEN(K18)=0,ISBLANK(K18)=FALSE),"",ISNUMBER(SEARCH(K18,H18))),"City/Postal Code/Country Found in Address",IF(AND(LEN(L18)=0,ISBLANK(L18)=FALSE),"",ISNUMBER(SEARCH(", "&L18,H18))),"City/Postal Code/Country Found in Address",IF(AND(LEN(J18)=0,ISBLANK(J18)=FALSE),"",ISNUMBER(SEARCH(", "&J18,H18))),"City/Postal Code/Country Found in Address",IF(AND(LEN(L18)=0,ISBLANK(L18)=FALSE),"",ISNUMBER(SEARCH(","&L18,H18))),"City/Postal Code/Country Found in Address",IF(AND(LEN(J18)=0,ISBLANK(J18)=FALSE),"",ISNUMBER(SEARCH(","&J18,H18))),"City/Postal Code/Country Found in Address"),"")} | AD18: =IF(ISNUMBER(SEARCH("PO",N18)),"PO# Entered in Tax ID Field","") | AE18: {=IFERROR(IF(VLOOKUP(LEFT(M18,MIN(SEARCH({1,2,3,4,5,6,7,8,9,0},M18&{1,2,3,4,5,6,7,8,9,0}))-1),Country_Codes!$N:$N,1,0)>0,"PO Number may be incorrect",""),"")} | AF18: =IF(N18="","",IF(EXACT(L18,LEFT(N18,2)),IF(EXACT(MID(N18,3,1)," "),"Check the Space inbetween County code & VAT",""),"Check the VAT Country Code Format")) | AG18: =IF((ISNUMBER(SEARCH("@",P18)))>0,"",IF(IF(--(ISNUMBER(SEARCH("'",P18)))>0,OR(EXACT(PROPER(P18),P18),EXACT((PROPER(LEFT(P18,FIND("'",P18)-2))&LOWER(MID(P18,FIND("'",P18)-1,1))&PROPER(MID(P18,FIND("'",P18)+0,LEN(P18)-FIND("'",P18)+1))),P18)),"Please check Billing Contact Casing")=TRUE,"","Please check Billing Contact casing")) | AH18: =IF(OR(L18="AS",L18="FM",L18="GU",L18="MH",L18="MP",L18="PW",L18="PR",L18="VI",L18="UM"),"US Territories Check","") | AI18: {=IF(G18="","",_xlfn.IFNA(_xlfn.IFS(L18=VLOOKUP(L18,Country_Codes!$M:$M,1,0)=TRUE,""),"Please check the country code"))} | AJ18: =IF(S18="","",S18&"; ")&IF(T18="","",T18&"; ")&IF(U18="","",U18&"; ")&IF(V18="","",V18&"; ")&IF(AF18="","",AF18&"; ")&IF(AG18="","",AG18&"; ")&IF(AH18="","",AH18&"; ")&IF(Z18="","",Z18&"; ")&IF(AA18="","",AA18&"; ")&IF(AB18="","",AB18&"; ")&IF(AC18="","",AC18&"; ")&IF(AD18="","",AD18&"; ")&IF(AE18="","",AE18&"; ")&IF(AI18="","",AI18&"; ")&IF(W18="","",W18&"; ")&IF(X18="","",X18&"; ")&IF(Y18="","",Y18&"; ") | AM18: =(COUNTA(S18:V18)-COUNTIFS((S18:V18),""))+(COUNTA(AB18)-COUNTIFS((AB18),""))+(COUNTA(AG18)-COUNTIFS((AG18),"")) -> 0 | AN18: =(COUNTA(W18)-COUNTIFS((W18),""))+(COUNTA(Z18)-COUNTIFS((Z18),"")) -> 0 | AO18: =(COUNTA(AA18)-COUNTIFS((AA18),""))+(COUNTA(AC18:AE18)-COUNTIFS((AC18:AE18),""))+(COUNTA(AH18:AI18)-COUNTIFS((AH18:AI18),"")) -> 0 | AP18: =(COUNTA(X18:Y18)-COUNTIFS((X18:Y18),""))+(COUNTA(AF18)-COUNTIFS((AF18),"")) -> 0 | AQ18: =SUM(AM18:AP18) -> 0 | AV18: 45435 | AW18: SampleCorp, Inc.
A19: 45315 | B19: User 1 | C19: Bill To Contact | D19: ID-0005a000 | E19: ID-0006a000 | F19: sample flow, inc. | G19: ID_Num_4 | H19: 11111 Sample Place | I19: Charlotte | J19: NC | K19: 28277 | L19: US | O19: Tony Frank | R19: =IF(G19=G18,"","Unique Record") -> Unique Record | S19: =IF(F19="","",IF(EXACT(F19,(UPPER(F19))),"Account Upper Case","")) | T19: =IF(F19="","",IF(EXACT(F19,(LOWER(F19))),"Account Lower Case","")) -> Account Lower Case | U19: =IF(EXACT(H19,PROPER(H19)),"","Billing Street - casing") | V19: =IF(EXACT(I19,PROPER(I19)),"","City - casing") | W19: =IF(OR(ISNUMBER(SEARCH("East",I19)),ISNUMBER(SEARCH("West",I19)),ISNUMBER(SEARCH("North",I19)),ISNUMBER(SEARCH("South",I19))),"",IF(OR(ISNUMBER(SEARCH("St.",I19)),ISNUMBER(SEARCH("St ",I19))),"Check St in city field",IF(RIGHT(I19,1)=".","Dot found in city field",""))) | X19: {=IF((SUMPRODUCT(--ISNUMBER(SEARCH({"!","@","#","$","%","^","&","~*","(",")","_","+","=","{","}","[","]","|","\",":",";","'","""","<",">",",",".","~?","/","~~","`"}, I19)))>0)=TRUE,"Special Characters Found in City","")} | Y19: {=IF((SUMPRODUCT(--ISNUMBER(SEARCH({"!","@","#","$","%","^","~*","(",")","_","+","=","{","}","[","]","|","\",":",";","'","""","<",">","~?","/","~~","`"},F19)))>0)=TRUE,"Special Characters Found in Account field","")} | Z19: {=IF(SUM(--ISNUMBER(SEARCH({1,2,3,4,5,6,7,8,9,0},MID(H19,(SEARCH(" E ",H19)-1),1))))+SUM(--ISNUMBER(SEARCH({1,2,3,4,5,6,7,8,9,0},MID(H19,(SEARCH(" E ",H19)+3),1))))=2,"",IF(SUM(--ISNUMBER(SEARCH({"Parte E","Apoquindo N"},H19)))>0,"",IF(OR(RIGHT(H19,3)=" NE",RIGHT(H19,3)=" NW",RIGHT(H19,3)=" SW",RIGHT(H19,3)=" SE",RIGHT(H19,2)=" N",RIGHT(H19,2)=" E",RIGHT(H19,2)=" W",RIGHT(H19,2)=" S",LEFT(H19,3)="NE ",LEFT(H19,3)="NW ",LEFT(H19,3)="SW ",LEFT(H19,3)="SE ",LEFT(H19,2)="N ",LEFT(H19,2)="E ",LEFT(H19,2)="W ",LEFT(H19,2)="S "),"Directional Check",IF(SUM(--ISNUMBER(SEARCH({" N "," E "," W "," S "," NE "," NW "," SW "," SE ","N.E","N.W","S.W","S.E","E.","N.","S.","W."},H19)))>0,"Directional Check",IF(SUM(--ISNUMBER(SEARCH({1,2,3,4,5,6,7,8,9,0},MID(H19,(SEARCH("nd ",H19)-1),1))))+SUM(--ISNUMBER(SEARCH({1,2,3,4,5,6,7,8,9,0},MID(H19,(SEARCH("rd ",H19)-1),1)))+SUM(--ISNUMBER(SEARCH({1,2,3,4,5,6,7,8,9,0},MID(H19,(SEARCH("st ",H19)-1),1))))+SUM(--ISNUMBER(SEARCH({1,2,3,4,5,6,7,8,9,0},MID(H19,(SEARCH("th ",H19)-1),1)))))>0,"","")))))} | AA19: =IF(IF(L19="US",IFERROR(VLOOKUP(J19,Country_Codes!$B:$B,1,0)=J19,"US State Code Error"),IF(L19="CA",IFERROR(VLOOKUP(J19,Country_Codes!$E:$E,1,0)=J19,"Canada State Code Error"),IF(L19="BR",IFERROR(VLOOKUP(J19,Country_Codes!$H:$H,1,0)=J19,"Brazil State Code Error"),IF(L19="AU",IFERROR(VLOOKUP(J19,Country_Codes!$K:$K,1,0)=J19,"Australia State Code Error"),""))))=TRUE,"",IF(L19="US",IFERROR(VLOOKUP(J19,Country_Codes!$B:$B,1,0)=J19,"US State Code Error"),IF(L19="CA",IFERROR(VLOOKUP(J19,Country_Codes!$E:$E,1,0)=J19,"Canada State Code Error"),IF(L19="BR",IFERROR(VLOOKUP(J19,Country_Codes!$H:$H,1,0)=J19,"Brazil State Code Error"),IF(L19="AU",IFERROR(VLOOKUP(J19,Country_Codes!$K:$K,1,0)=J19,"Australia State Code Error"),""))))) | AB19: =IF(OR(L19="US",L19="CA",L19="BR",L19="AU"),IF((EXACT(UPPER(J19),J19)),"","Country Code Casing"),IF(EXACT(J19,PROPER(J19)),"","Billing State casing")) | AC19: {=IFERROR(_xlfn.IFS(IF(AND(LEN(I19)=0,ISBLANK(I19)=FALSE),"",ISNUMBER(SEARCH(I19,H19))),"City/Postal Code/Country Found in Address",IF(AND(LEN(K19)=0,ISBLANK(K19)=FALSE),"",ISNUMBER(SEARCH(K19,H19))),"City/Postal Code/Country Found in Address",IF(AND(LEN(L19)=0,ISBLANK(L19)=FALSE),"",ISNUMBER(SEARCH(", "&L19,H19))),"City/Postal Code/Country Found in Address",IF(AND(LEN(J19)=0,ISBLANK(J19)=FALSE),"",ISNUMBER(SEARCH(", "&J19,H19))),"City/Postal Code/Country Found in Address",IF(AND(LEN(L19)=0,ISBLANK(L19)=FALSE),"",ISNUMBER(SEARCH(","&L19,H19))),"City/Postal Code/Country Found in Address",IF(AND(LEN(J19)=0,ISBLANK(J19)=FALSE),"",ISNUMBER(SEARCH(","&J19,H19))),"City/Postal Code/Country Found in Address"),"")} | AD19: =IF(ISNUMBER(SEARCH("PO",N19)),"PO# Entered in Tax ID Field","") | AE19: {=IFERROR(IF(VLOOKUP(LEFT(M19,MIN(SEARCH({1,2,3,4,5,6,7,8,9,0},M19&{1,2,3,4,5,6,7,8,9,0}))-1),Country_Codes!$N:$N,1,0)>0,"PO Number may be incorrect",""),"")} | AF19: =IF(N19="","",IF(EXACT(L19,LEFT(N19,2)),IF(EXACT(MID(N19,3,1)," "),"Check the Space inbetween County code & VAT",""),"Check the VAT Country Code Format")) | AG19: =IF((ISNUMBER(SEARCH("@",P19)))>0,"",IF(IF(--(ISNUMBER(SEARCH("'",P19)))>0,OR(EXACT(PROPER(P19),P19),EXACT((PROPER(LEFT(P19,FIND("'",P19)-2))&LOWER(MID(P19,FIND("'",P19)-1,1))&PROPER(MID(P19,FIND("'",P19)+0,LEN(P19)-FIND("'",P19)+1))),P19)),"Please check Billing Contact Casing")=TRUE,"","Please check Billing Contact casing")) | AH19: =IF(OR(L19="AS",L19="FM",L19="GU",L19="MH",L19="MP",L19="PW",L19="PR",L19="VI",L19="UM"),"US Territories Check","") | AI19: {=IF(G19="","",_xlfn.IFNA(_xlfn.IFS(L19=VLOOKUP(L19,Country_Codes!$M:$M,1,0)=TRUE,""),"Please check the country code"))} | AJ19: =IF(S19="","",S19&"; ")&IF(T19="","",T19&"; ")&IF(U19="","",U19&"; ")&IF(V19="","",V19&"; ")&IF(AF19="","",AF19&"; ")&IF(AG19="","",AG19&"; ")&IF(AH19="","",AH19&"; ")&IF(Z19="","",Z19&"; ")&IF(AA19="","",AA19&"; ")&IF(AB19="","",AB19&"; ")&IF(AC19="","",AC19&"; ")&IF(AD19="","",AD19&"; ")&IF(AE19="","",AE19&"; ")&IF(AI19="","",AI19&"; ")&IF(W19="","",W19&"; ")&IF(X19="","",X19&"; ")&IF(Y19="","",Y19&"; ") -> Account Lower Case; | AM19: =(COUNTA(S19:V19)-COUNTIFS((S19:V19),""))+(COUNTA(AB19)-COUNTIFS((AB19),""))+(COUNTA(AG19)-COUNTIFS((AG19),"")) -> 1 | AN19: =(COUNTA(W19)-COUNTIFS((W19),""))+(COUNTA(Z19)-COUNTIFS((Z19),"")) -> 0 | AO19: =(COUNTA(AA19)-COUNTIFS((AA19),""))+(COUNTA(AC19:AE19)-COUNTIFS((AC19:AE19),""))+(COUNTA(AH19:AI19)-COUNTIFS((AH19:AI19),"")) -> 0 | AP19: =(COUNTA(X19:Y19)-COUNTIFS((X19:Y19),""))+(COUNTA(AF19)-COUNTIFS((AF19),"")) -> 0 | AQ19: =SUM(AM19:AP19) -> 1 | AV19: 45437 | AW19: 0
A20: 45622 | B20: User 1 | C20: Bill To Contact | D20: ID-0006a000 | F20: Sample Ltd | G20: ID_Num_5 | H20: Main Street | I20: London | K20: EC2V 7EE | L20: GB | M20: PO 030 | P20: Smith Frank | R20: =IF(G20=G19,"","Unique Record") -> Unique Record | S20: =IF(F20="","",IF(EXACT(F20,(UPPER(F20))),"Account Upper Case","")) | T20: =IF(F20="","",IF(EXACT(F20,(LOWER(F20))),"Account Lower Case","")) | U20: =IF(EXACT(H20,PROPER(H20)),"","Billing Street - casing") | V20: =IF(EXACT(I20,PROPER(I20)),"","City - casing") | W20: =IF(OR(ISNUMBER(SEARCH("East",I20)),ISNUMBER(SEARCH("West",I20)),ISNUMBER(SEARCH("North",I20)),ISNUMBER(SEARCH("South",I20))),"",IF(OR(ISNUMBER(SEARCH("St.",I20)),ISNUMBER(SEARCH("St ",I20))),"Check St in city field",IF(RIGHT(I20,1)=".","Dot found in city field",""))) | X20: {=IF((SUMPRODUCT(--ISNUMBER(SEARCH({"!","@","#","$","%","^","&","~*","(",")","_","+","=","{","}","[","]","|","\",":",";","'","""","<",">",",",".","~?","/","~~","`"}, I20)))>0)=TRUE,"Special Characters Found in City","")} | Y20: {=IF((SUMPRODUCT(--ISNUMBER(SEARCH({"!","@","#","$","%","^","~*","(",")","_","+","=","{","}","[","]","|","\",":",";","'","""","<",">","~?","/","~~","`"},F20)))>0)=TRUE,"Special Characters Found in Account field","")} | Z20: {=IF(SUM(--ISNUMBER(SEARCH({1,2,3,4,5,6,7,8,9,0},MID(H20,(SEARCH(" E ",H20)-1),1))))+SUM(--ISNUMBER(SEARCH({1,2,3,4,5,6,7,8,9,0},MID(H20,(SEARCH(" E ",H20)+3),1))))=2,"",IF(SUM(--ISNUMBER(SEARCH({"Parte E","Apoquindo N"},H20)))>0,"",IF(OR(RIGHT(H20,3)=" NE",RIGHT(H20,3)=" NW",RIGHT(H20,3)=" SW",RIGHT(H20,3)=" SE",RIGHT(H20,2)=" N",RIGHT(H20,2)=" E",RIGHT(H20,2)=" W",RIGHT(H20,2)=" S",LEFT(H20,3)="NE ",LEFT(H20,3)="NW ",LEFT(H20,3)="SW ",LEFT(H20,3)="SE ",LEFT(H20,2)="N ",LEFT(H20,2)="E ",LEFT(H20,2)="W ",LEFT(H20,2)="S "),"Directional Check",IF(SUM(--ISNUMBER(SEARCH({" N "," E "," W "," S "," NE "," NW "," SW "," SE ","N.E","N.W","S.W","S.E","E.","N.","S.","W."},H20)))>0,"Directional Check",IF(SUM(--ISNUMBER(SEARCH({1,2,3,4,5,6,7,8,9,0},MID(H20,(SEARCH("nd ",H20)-1),1))))+SUM(--ISNUMBER(SEARCH({1,2,3,4,5,6,7,8,9,0},MID(H20,(SEARCH("rd ",H20)-1),1)))+SUM(--ISNUMBER(SEARCH({1,2,3,4,5,6,7,8,9,0},MID(H20,(SEARCH("st ",H20)-1),1))))+SUM(--ISNUMBER(SEARCH({1,2,3,4,5,6,7,8,9,0},MID(H20,(SEARCH("th ",H20)-1),1)))))>0,"","")))))} | AA20: =IF(IF(L20="US",IFERROR(VLOOKUP(J20,Country_Codes!$B:$B,1,0)=J20,"US State Code Error"),IF(L20="CA",IFERROR(VLOOKUP(J20,Country_Codes!$E:$E,1,0)=J20,"Canada State Code Error"),IF(L20="BR",IFERROR(VLOOKUP(J20,Country_Codes!$H:$H,1,0)=J20,"Brazil State Code Error"),IF(L20="AU",IFERROR(VLOOKUP(J20,Country_Codes!$K:$K,1,0)=J20,"Australia State Code Error"),""))))=TRUE,"",IF(L20="US",IFERROR(VLOOKUP(J20,Country_Codes!$B:$B,1,0)=J20,"US State Code Error"),IF(L20="CA",IFERROR(VLOOKUP(J20,Country_Codes!$E:$E,1,0)=J20,"Canada State Code Error"),IF(L20="BR",IFERROR(VLOOKUP(J20,Country_Codes!$H:$H,1,0)=J20,"Brazil State Code Error"),IF(L20="AU",IFERROR(VLOOKUP(J20,Country_Codes!$K:$K,1,0)=J20,"Australia State Code Error"),""))))) | AB20: =IF(OR(L20="US",L20="CA",L20="BR",L20="AU"),IF((EXACT(UPPER(J20),J20)),"","Country Code Casing"),IF(EXACT(J20,PROPER(J20)),"","Billing State casing")) | AC20: {=IFERROR(_xlfn.IFS(IF(AND(LEN(I20)=0,ISBLANK(I20)=FALSE),"",ISNUMBER(SEARCH(I20,H20))),"City/Postal Code/Country Found in Address",IF(AND(LEN(K20)=0,ISBLANK(K20)=FALSE),"",ISNUMBER(SEARCH(K20,H20))),"City/Postal Code/Country Found in Address",IF(AND(LEN(L20)=0,ISBLANK(L20)=FALSE),"",ISNUMBER(SEARCH(", "&L20,H20))),"City/Postal Code/Country Found in Address",IF(AND(LEN(J20)=0,ISBLANK(J20)=FALSE),"",ISNUMBER(SEARCH(", "&J20,H20))),"City/Postal Code/Country Found in Address",IF(AND(LEN(L20)=0,ISBLANK(L20)=FALSE),"",ISNUMBER(SEARCH(","&L20,H20))),"City/Postal Code/Country Found in Address",IF(AND(LEN(J20)=0,ISBLANK(J20)=FALSE),"",ISNUMBER(SEARCH(","&J20,H20))),"City/Postal Code/Country Found in Address"),"")} | AD20: =IF(ISNUMBER(SEARCH("PO",N20)),"PO# Entered in Tax ID Field","") | AE20: {=IFERROR(IF(VLOOKUP(LEFT(M20,MIN(SEARCH({1,2,3,4,5,6,7,8,9,0},M20&{1,2,3,4,5,6,7,8,9,0}))-1),Country_Codes!$N:$N,1,0)>0,"PO Number may be incorrect",""),"")} | AF20: =IF(N20="","",IF(EXACT(L20,LEFT(N20,2)),IF(EXACT(MID(N20,3,1)," "),"Check the Space inbetween County code & VAT",""),"Check the VAT Country Code Format")) | AG20: =IF((ISNUMBER(SEARCH("@",P20)))>0,"",IF(IF(--(ISNUMBER(SEARCH("'",P20)))>0,OR(EXACT(PROPER(P20),P20),EXACT((PROPER(LEFT(P20,FIND("'",P20)-2))&LOWER(MID(P20,FIND("'",P20)-1,1))&PROPER(MID(P20,FIND("'",P20)+0,LEN(P20)-FIND("'",P20)+1))),P20)),"Please check Billing Contact Casing")=TRUE,"","Please check Billing Contact casing")) | AH20: =IF(OR(L20="AS",L20="FM",L20="GU",L20="MH",L20="MP",L20="PW",L20="PR",L20="VI",L20="UM"),"US Territories Check","") | AI20: {=IF(G20="","",_xlfn.IFNA(_xlfn.IFS(L20=VLOOKUP(L20,Country_Codes!$M:$M,1,0)=TRUE,""),"Please check the country code"))} | AJ20: =IF(S20="","",S20&"; ")&IF(T20="","",T20&"; ")&IF(U20="","",U20&"; ")&IF(V20="","",V20&"; ")&IF(AF20="","",AF20&"; ")&IF(AG20="","",AG20&"; ")&IF(AH20="","",AH20&"; ")&IF(Z20="","",Z20&"; ")&IF(AA20="","",AA20&"; ")&IF(AB20="","",AB20&"; ")&IF(AC20="","",AC20&"; ")&IF(AD20="","",AD20&"; ")&IF(AE20="","",AE20&"; ")&IF(AI20="","",AI20&"; ")&IF(W20="","",W20&"; ")&IF(X20="","",X20&"; ")&IF(Y20="","",Y20&"; ") | AM20: =(COUNTA(S20:V20)-COUNTIFS((S20:V20),""))+(COUNTA(AB20)-COUNTIFS((AB20),""))+(COUNTA(AG20)-COUNTIFS((AG20),"")) -> 0 | AN20: =(COUNTA(W20)-COUNTIFS((W20),""))+(COUNTA(Z20)-COUNTIFS((Z20),"")) -> 0 | AO20: =(COUNTA(AA20)-COUNTIFS((AA20),""))+(COUNTA(AC20:AE20)-COUNTIFS((AC20:AE20),""))+(COUNTA(AH20:AI20)-COUNTIFS((AH20:AI20),"")) -> 0 | AP20: =(COUNTA(X20:Y20)-COUNTIFS((X20:Y20),""))+(COUNTA(AF20)-COUNTIFS((AF20),"")) -> 0 | AQ20: =SUM(AM20:AP20) -> 0 | AV20: 45439
A21: 45622 | B21: User 1 | C21: Billing Contact Name | E21: Smith Francis | F21: Sample Ltd | G21: ID_Num_5 | H21: Main Street | I21: London | K21: EC2V 7EE | L21: GB | M21: PO 030 | P21: Smith Frank | R21: =IF(G21=G20,"","Unique Record") | S21: =IF(F21="","",IF(EXACT(F21,(UPPER(F21))),"Account Upper Case","")) | T21: =IF(F21="","",IF(EXACT(F21,(LOWER(F21))),"Account Lower Case","")) | U21: =IF(EXACT(H21,PROPER(H21)),"","Billing Street - casing") | V21: =IF(EXACT(I21,PROPER(I21)),"","City - casing") | W21: =IF(OR(ISNUMBER(SEARCH("East",I21)),ISNUMBER(SEARCH("West",I21)),ISNUMBER(SEARCH("North",I21)),ISNUMBER(SEARCH("South",I21))),"",IF(OR(ISNUMBER(SEARCH("St.",I21)),ISNUMBER(SEARCH("St ",I21))),"Check St in city field",IF(RIGHT(I21,1)=".","Dot found in city field",""))) | X21: {=IF((SUMPRODUCT(--ISNUMBER(SEARCH({"!","@","#","$","%","^","&","~*","(",")","_","+","=","{","}","[","]","|","\",":",";","'","""","<",">",",",".","~?","/","~~","`"}, I21)))>0)=TRUE,"Special Characters Found in City","")} | Y21: {=IF((SUMPRODUCT(--ISNUMBER(SEARCH({"!","@","#","$","%","^","~*","(",")","_","+","=","{","}","[","]","|","\",":",";","'","""","<",">","~?","/","~~","`"},F21)))>0)=TRUE,"Special Characters Found in Account field","")} | Z21: {=IF(SUM(--ISNUMBER(SEARCH({1,2,3,4,5,6,7,8,9,0},MID(H21,(SEARCH(" E ",H21)-1),1))))+SUM(--ISNUMBER(SEARCH({1,2,3,4,5,6,7,8,9,0},MID(H21,(SEARCH(" E ",H21)+3),1))))=2,"",IF(SUM(--ISNUMBER(SEARCH({"Parte E","Apoquindo N"},H21)))>0,"",IF(OR(RIGHT(H21,3)=" NE",RIGHT(H21,3)=" NW",RIGHT(H21,3)=" SW",RIGHT(H21,3)=" SE",RIGHT(H21,2)=" N",RIGHT(H21,2)=" E",RIGHT(H21,2)=" W",RIGHT(H21,2)=" S",LEFT(H21,3)="NE ",LEFT(H21,3)="NW ",LEFT(H21,3)="SW ",LEFT(H21,3)="SE ",LEFT(H21,2)="N ",LEFT(H21,2)="E ",LEFT(H21,2)="W ",LEFT(H21,2)="S "),"Directional Check",IF(SUM(--ISNUMBER(SEARCH({" N "," E "," W "," S "," NE "," NW "," SW "," SE ","N.E","N.W","S.W","S.E","E.","N.","S.","W."},H21)))>0,"Directional Check",IF(SUM(--ISNUMBER(SEARCH({1,2,3,4,5,6,7,8,9,0},MID(H21,(SEARCH("nd ",H21)-1),1))))+SUM(--ISNUMBER(SEARCH({1,2,3,4,5,6,7,8,9,0},MID(H21,(SEARCH("rd ",H21)-1),1)))+SUM(--ISNUMBER(SEARCH({1,2,3,4,5,6,7,8,9,0},MID(H21,(SEARCH("st ",H21)-1),1))))+SUM(--ISNUMBER(SEARCH({1,2,3,4,5,6,7,8,9,0},MID(H21,(SEARCH("th ",H21)-1),1)))))>0,"","")))))} | AA21: =IF(IF(L21="US",IFERROR(VLOOKUP(J21,Country_Codes!$B:$B,1,0)=J21,"US State Code Error"),IF(L21="CA",IFERROR(VLOOKUP(J21,Country_Codes!$E:$E,1,0)=J21,"Canada State Code Error"),IF(L21="BR",IFERROR(VLOOKUP(J21,Country_Codes!$H:$H,1,0)=J21,"Brazil State Code Error"),IF(L21="AU",IFERROR(VLOOKUP(J21,Country_Codes!$K:$K,1,0)=J21,"Australia State Code Error"),""))))=TRUE,"",IF(L21="US",IFERROR(VLOOKUP(J21,Country_Codes!$B:$B,1,0)=J21,"US State Code Error"),IF(L21="CA",IFERROR(VLOOKUP(J21,Country_Codes!$E:$E,1,0)=J21,"Canada State Code Error"),IF(L21="BR",IFERROR(VLOOKUP(J21,Country_Codes!$H:$H,1,0)=J21,"Brazil State Code Error"),IF(L21="AU",IFERROR(VLOOKUP(J21,Country_Codes!$K:$K,1,0)=J21,"Australia State Code Error"),""))))) | AB21: =IF(OR(L21="US",L21="CA",L21="BR",L21="AU"),IF((EXACT(UPPER(J21),J21)),"","Country Code Casing"),IF(EXACT(J21,PROPER(J21)),"","Billing State casing")) | AC21: {=IFERROR(_xlfn.IFS(IF(AND(LEN(I21)=0,ISBLANK(I21)=FALSE),"",ISNUMBER(SEARCH(I21,H21))),"City/Postal Code/Country Found in Address",IF(AND(LEN(K21)=0,ISBLANK(K21)=FALSE),"",ISNUMBER(SEARCH(K21,H21))),"City/Postal Code/Country Found in Address",IF(AND(LEN(L21)=0,ISBLANK(L21)=FALSE),"",ISNUMBER(SEARCH(", "&L21,H21))),"City/Postal Code/Country Found in Address",IF(AND(LEN(J21)=0,ISBLANK(J21)=FALSE),"",ISNUMBER(SEARCH(", "&J21,H21))),"City/Postal Code/Country Found in Address",IF(AND(LEN(L21)=0,ISBLANK(L21)=FALSE),"",ISNUMBER(SEARCH(","&L21,H21))),"City/Postal Code/Country Found in Address",IF(AND(LEN(J21)=0,ISBLANK(J21)=FALSE),"",ISNUMBER(SEARCH(","&J21,H21))),"City/Postal Code/Country Found in Address"),"")} | AD21: =IF(ISNUMBER(SEARCH("PO",N21)),"PO# Entered in Tax ID Field","") | AE21: {=IFERROR(IF(VLOOKUP(LEFT(M21,MIN(SEARCH({1,2,3,4,5,6,7,8,9,0},M21&{1,2,3,4,5,6,7,8,9,0}))-1),Country_Codes!$N:$N,1,0)>0,"PO Number may be incorrect",""),"")} | AF21: =IF(N21="","",IF(EXACT(L21,LEFT(N21,2)),IF(EXACT(MID(N21,3,1)," "),"Check the Space inbetween County code & VAT",""),"Check the VAT Country Code Format")) | AG21: =IF((ISNUMBER(SEARCH("@",P21)))>0,"",IF(IF(--(ISNUMBER(SEARCH("'",P21)))>0,OR(EXACT(PROPER(P21),P21),EXACT((PROPER(LEFT(P21,FIND("'",P21)-2))&LOWER(MID(P21,FIND("'",P21)-1,1))&PROPER(MID(P21,FIND("'",P21)+0,LEN(P21)-FIND("'",P21)+1))),P21)),"Please check Billing Contact Casing")=TRUE,"","Please check Billing Contact casing")) | AH21: =IF(OR(L21="AS",L21="FM",L21="GU",L21="MH",L21="MP",L21="PW",L21="PR",L21="VI",L21="UM"),"US Territories Check","") | AI21: {=IF(G21="","",_xlfn.IFNA(_xlfn.IFS(L21=VLOOKUP(L21,Country_Codes!$M:$M,1,0)=TRUE,""),"Please check the country code"))} | AJ21: =IF(S21="","",S21&"; ")&IF(T21="","",T21&"; ")&IF(U21="","",U21&"; ")&IF(V21="","",V21&"; ")&IF(AF21="","",AF21&"; ")&IF(AG21="","",AG21&"; ")&IF(AH21="","",AH21&"; ")&IF(Z21="","",Z21&"; ")&IF(AA21="","",AA21&"; ")&IF(AB21="","",AB21&"; ")&IF(AC21="","",AC21&"; ")&IF(AD21="","",AD21&"; ")&IF(AE21="","",AE21&"; ")&IF(AI21="","",AI21&"; ")&IF(W21="","",W21&"; ")&IF(X21="","",X21&"; ")&IF(Y21="","",Y21&"; ") | AM21: =(COUNTA(S21:V21)-COUNTIFS((S21:V21),""))+(COUNTA(AB21)-COUNTIFS((AB21),""))+(COUNTA(AG21)-COUNTIFS((AG21),"")) -> 0 | AN21: =(COUNTA(W21)-COUNTIFS((W21),""))+(COUNTA(Z21)-COUNTIFS((Z21),"")) -> 0 | AO21: =(COUNTA(AA21)-COUNTIFS((AA21),""))+(COUNTA(AC21:AE21)-COUNTIFS((AC21:AE21),""))+(COUNTA(AH21:AI21)-COUNTIFS((AH21:AI21),"")) -> 0 | AP21: =(COUNTA(X21:Y21)-COUNTIFS((X21:Y21),""))+(COUNTA(AF21)-COUNTIFS((AF21),"")) -> 0 | AQ21: =SUM(AM21:AP21) -> 0 | AV21: 45440
A22: 45546 | B22: User 2 | C22: Bill To Contact | D22: ID-0006a000 | F22: Sample Technologies, Inc. | G22: ID_Num_6 | H22: 10000 Sample Way | I22: Redwood City | J22: CA | K22: 94063 | L22: US | P22: Accounts Payable | R22: =IF(G22=G21,"","Unique Record") -> Unique Record | S22: =IF(F22="","",IF(EXACT(F22,(UPPER(F22))),"Account Upper Case","")) | T22: =IF(F22="","",IF(EXACT(F22,(LOWER(F22))),"Account Lower Case","")) | U22: =IF(EXACT(H22,PROPER(H22)),"","Billing Street - casing") | V22: =IF(EXACT(I22,PROPER(I22)),"","City - casing") | W22: =IF(OR(ISNUMBER(SEARCH("East",I22)),ISNUMBER(SEARCH("West",I22)),ISNUMBER(SEARCH("North",I22)),ISNUMBER(SEARCH("South",I22))),"",IF(OR(ISNUMBER(SEARCH("St.",I22)),ISNUMBER(SEARCH("St ",I22))),"Check St in city field",IF(RIGHT(I22,1)=".","Dot found in city field",""))) | X22: {=IF((SUMPRODUCT(--ISNUMBER(SEARCH({"!","@","#","$","%","^","&","~*","(",")","_","+","=","{","}","[","]","|","\",":",";","'","""","<",">",",",".","~?","/","~~","`"}, I22)))>0)=TRUE,"Special Characters Found in City","")} | Y22: {=IF((SUMPRODUCT(--ISNUMBER(SEARCH({"!","@","#","$","%","^","~*","(",")","_","+","=","{","}","[","]","|","\",":",";","'","""","<",">","~?","/","~~","`"},F22)))>0)=TRUE,"Special Characters Found in Account field","")} | Z22: {=IF(SUM(--ISNUMBER(SEARCH({1,2,3,4,5,6,7,8,9,0},MID(H22,(SEARCH(" E ",H22)-1),1))))+SUM(--ISNUMBER(SEARCH({1,2,3,4,5,6,7,8,9,0},MID(H22,(SEARCH(" E ",H22)+3),1))))=2,"",IF(SUM(--ISNUMBER(SEARCH({"Parte E","Apoquindo N"},H22)))>0,"",IF(OR(RIGHT(H22,3)=" NE",RIGHT(H22,3)=" NW",RIGHT(H22,3)=" SW",RIGHT(H22,3)=" SE",RIGHT(H22,2)=" N",RIGHT(H22,2)=" E",RIGHT(H22,2)=" W",RIGHT(H22,2)=" S",LEFT(H22,3)="NE ",LEFT(H22,3)="NW ",LEFT(H22,3)="SW ",LEFT(H22,3)="SE ",LEFT(H22,2)="N ",LEFT(H22,2)="E ",LEFT(H22,2)="W ",LEFT(H22,2)="S "),"Directional Check",IF(SUM(--ISNUMBER(SEARCH({" N "," E "," W "," S "," NE "," NW "," SW "," SE ","N.E","N.W","S.W","S.E","E.","N.","S.","W."},H22)))>0,"Directional Check",IF(SUM(--ISNUMBER(SEARCH({1,2,3,4,5,6,7,8,9,0},MID(H22,(SEARCH("nd ",H22)-1),1))))+SUM(--ISNUMBER(SEARCH({1,2,3,4,5,6,7,8,9,0},MID(H22,(SEARCH("rd ",H22)-1),1)))+SUM(--ISNUMBER(SEARCH({1,2,3,4,5,6,7,8,9,0},MID(H22,(SEARCH("st ",H22)-1),1))))+SUM(--ISNUMBER(SEARCH({1,2,3,4,5,6,7,8,9,0},MID(H22,(SEARCH("th ",H22)-1),1)))))>0,"","")))))} | AA22: =IF(IF(L22="US",IFERROR(VLOOKUP(J22,Country_Codes!$B:$B,1,0)=J22,"US State Code Error"),IF(L22="CA",IFERROR(VLOOKUP(J22,Country_Codes!$E:$E,1,0)=J22,"Canada State Code Error"),IF(L22="BR",IFERROR(VLOOKUP(J22,Country_Codes!$H:$H,1,0)=J22,"Brazil State Code Error"),IF(L22="AU",IFERROR(VLOOKUP(J22,Country_Codes!$K:$K,1,0)=J22,"Australia State Code Error"),""))))=TRUE,"",IF(L22="US",IFERROR(VLOOKUP(J22,Country_Codes!$B:$B,1,0)=J22,"US State Code Error"),IF(L22="CA",IFERROR(VLOOKUP(J22,Country_Codes!$E:$E,1,0)=J22,"Canada State Code Error"),IF(L22="BR",IFERROR(VLOOKUP(J22,Country_Codes!$H:$H,1,0)=J22,"Brazil State Code Error"),IF(L22="AU",IFERROR(VLOOKUP(J22,Country_Codes!$K:$K,1,0)=J22,"Australia State Code Error"),""))))) | AB22: =IF(OR(L22="US",L22="CA",L22="BR",L22="AU"),IF((EXACT(UPPER(J22),J22)),"","Country Code Casing"),IF(EXACT(J22,PROPER(J22)),"","Billing State casing")) | AC22: {=IFERROR(_xlfn.IFS(IF(AND(LEN(I22)=0,ISBLANK(I22)=FALSE),"",ISNUMBER(SEARCH(I22,H22))),"City/Postal Code/Country Found in Address",IF(AND(LEN(K22)=0,ISBLANK(K22)=FALSE),"",ISNUMBER(SEARCH(K22,H22))),"City/Postal Code/Country Found in Address",IF(AND(LEN(L22)=0,ISBLANK(L22)=FALSE),"",ISNUMBER(SEARCH(", "&L22,H22))),"City/Postal Code/Country Found in Address",IF(AND(LEN(J22)=0,ISBLANK(J22)=FALSE),"",ISNUMBER(SEARCH(", "&J22,H22))),"City/Postal Code/Country Found in Address",IF(AND(LEN(L22)=0,ISBLANK(L22)=FALSE),"",ISNUMBER(SEARCH(","&L22,H22))),"City/Postal Code/Country Found in Address",IF(AND(LEN(J22)=0,ISBLANK(J22)=FALSE),"",ISNUMBER(SEARCH(","&J22,H22))),"City/Postal Code/Country Found in Address"),"")} | AD22: =IF(ISNUMBER(SEARCH("PO",N22)),"PO# Entered in Tax ID Field","") | AE22: {=IFERROR(IF(VLOOKUP(LEFT(M22,MIN(SEARCH({1,2,3,4,5,6,7,8,9,0},M22&{1,2,3,4,5,6,7,8,9,0}))-1),Country_Codes!$N:$N,1,0)>0,"PO Number may be incorrect",""),"")} | AF22: =IF(N22="","",IF(EXACT(L22,LEFT(N22,2)),IF(EXACT(MID(N22,3,1)," "),"Check the Space inbetween County code & VAT",""),"Check the VAT Country Code Format")) | AG22: =IF((ISNUMBER(SEARCH("@",P22)))>0,"",IF(IF(--(ISNUMBER(SEARCH("'",P22)))>0,OR(EXACT(PROPER(P22),P22),EXACT((PROPER(LEFT(P22,FIND("'",P22)-2))&LOWER(MID(P22,FIND("'",P22)-1,1))&PROPER(MID(P22,FIND("'",P22)+0,LEN(P22)-FIND("'",P22)+1))),P22)),"Please check Billing Contact Casing")=TRUE,"","Please check Billing Contact casing")) | AH22: =IF(OR(L22="AS",L22="FM",L22="GU",L22="MH",L22="MP",L22="PW",L22="PR",L22="VI",L22="UM"),"US Territories Check","") | AI22: {=IF(G22="","",_xlfn.IFNA(_xlfn.IFS(L22=VLOOKUP(L22,Country_Codes!$M:$M,1,0)=TRUE,""),"Please check the country code"))} | AJ22: =IF(S22="","",S22&"; ")&IF(T22="","",T22&"; ")&IF(U22="","",U22&"; ")&IF(V22="","",V22&"; ")&IF(AF22="","",AF22&"; ")&IF(AG22="","",AG22&"; ")&IF(AH22="","",AH22&"; ")&IF(Z22="","",Z22&"; ")&IF(AA22="","",AA22&"; ")&IF(AB22="","",AB22&"; ")&IF(AC22="","",AC22&"; ")&IF(AD22="","",AD22&"; ")&IF(AE22="","",AE22&"; ")&IF(AI22="","",AI22&"; ")&IF(W22="","",W22&"; ")&IF(X22="","",X22&"; ")&IF(Y22="","",Y22&"; ") | AM22: =(COUNTA(S22:V22)-COUNTIFS((S22:V22),""))+(COUNTA(AB22)-COUNTIFS((AB22),""))+(COUNTA(AG22)-COUNTIFS((AG22),"")) -> 0 | AN22: =(COUNTA(W22)-COUNTIFS((W22),""))+(COUNTA(Z22)-COUNTIFS((Z22),"")) -> 0 | AO22: =(COUNTA(AA22)-COUNTIFS((AA22),""))+(COUNTA(AC22:AE22)-COUNTIFS((AC22:AE22),""))+(COUNTA(AH22:AI22)-COUNTIFS((AH22:AI22),"")) -> 0 | AP22: =(COUNTA(X22:Y22)-COUNTIFS((X22:Y22),""))+(COUNTA(AF22)-COUNTIFS((AF22),"")) -> 0 | AQ22: =SUM(AM22:AP22) -> 0 | AV22: 45442
A23: 45546 | B23: User 2 | C23: Billing Contact Name | E23: Accounts Payable | F23: Sample Technologies, Inc. | G23: ID_Num_6 | H23: 10000 Sample Way | I23: Redwood City | J23: CA | K23: 94063 | L23: US | P23: Accounts Payable | R23: =IF(G23=G22,"","Unique Record") | S23: =IF(F23="","",IF(EXACT(F23,(UPPER(F23))),"Account Upper Case","")) | T23: =IF(F23="","",IF(EXACT(F23,(LOWER(F23))),"Account Lower Case","")) | U23: =IF(EXACT(H23,PROPER(H23)),"","Billing Street - casing") | V23: =IF(EXACT(I23,PROPER(I23)),"","City - casing") | W23: =IF(OR(ISNUMBER(SEARCH("East",I23)),ISNUMBER(SEARCH("West",I23)),ISNUMBER(SEARCH("North",I23)),ISNUMBER(SEARCH("South",I23))),"",IF(OR(ISNUMBER(SEARCH("St.",I23)),ISNUMBER(SEARCH("St ",I23))),"Check St in city field",IF(RIGHT(I23,1)=".","Dot found in city field",""))) | X23: {=IF((SUMPRODUCT(--ISNUMBER(SEARCH({"!","@","#","$","%","^","&","~*","(",")","_","+","=","{","}","[","]","|","\",":",";","'","""","<",">",",",".","~?","/","~~","`"}, I23)))>0)=TRUE,"Special Characters Found in City","")} | Y23: {=IF((SUMPRODUCT(--ISNUMBER(SEARCH({"!","@","#","$","%","^","~*","(",")","_","+","=","{","}","[","]","|","\",":",";","'","""","<",">","~?","/","~~","`"},F23)))>0)=TRUE,"Special Characters Found in Account field","")} | Z23: {=IF(SUM(--ISNUMBER(SEARCH({1,2,3,4,5,6,7,8,9,0},MID(H23,(SEARCH(" E ",H23)-1),1))))+SUM(--ISNUMBER(SEARCH({1,2,3,4,5,6,7,8,9,0},MID(H23,(SEARCH(" E ",H23)+3),1))))=2,"",IF(SUM(--ISNUMBER(SEARCH({"Parte E","Apoquindo N"},H23)))>0,"",IF(OR(RIGHT(H23,3)=" NE",RIGHT(H23,3)=" NW",RIGHT(H23,3)=" SW",RIGHT(H23,3)=" SE",RIGHT(H23,2)=" N",RIGHT(H23,2)=" E",RIGHT(H23,2)=" W",RIGHT(H23,2)=" S",LEFT(H23,3)="NE ",LEFT(H23,3)="NW ",LEFT(H23,3)="SW ",LEFT(H23,3)="SE ",LEFT(H23,2)="N ",LEFT(H23,2)="E ",LEFT(H23,2)="W ",LEFT(H23,2)="S "),"Directional Check",IF(SUM(--ISNUMBER(SEARCH({" N "," E "," W "," S "," NE "," NW "," SW "," SE ","N.E","N.W","S.W","S.E","E.","N.","S.","W."},H23)))>0,"Directional Check",IF(SUM(--ISNUMBER(SEARCH({1,2,3,4,5,6,7,8,9,0},MID(H23,(SEARCH("nd ",H23)-1),1))))+SUM(--ISNUMBER(SEARCH({1,2,3,4,5,6,7,8,9,0},MID(H23,(SEARCH("rd ",H23)-1),1)))+SUM(--ISNUMBER(SEARCH({1,2,3,4,5,6,7,8,9,0},MID(H23,(SEARCH("st ",H23)-1),1))))+SUM(--ISNUMBER(SEARCH({1,2,3,4,5,6,7,8,9,0},MID(H23,(SEARCH("th ",H23)-1),1)))))>0,"","")))))} | AA23: =IF(IF(L23="US",IFERROR(VLOOKUP(J23,Country_Codes!$B:$B,1,0)=J23,"US State Code Error"),IF(L23="CA",IFERROR(VLOOKUP(J23,Country_Codes!$E:$E,1,0)=J23,"Canada State Code Error"),IF(L23="BR",IFERROR(VLOOKUP(J23,Country_Codes!$H:$H,1,0)=J23,"Brazil State Code Error"),IF(L23="AU",IFERROR(VLOOKUP(J23,Country_Codes!$K:$K,1,0)=J23,"Australia State Code Error"),""))))=TRUE,"",IF(L23="US",IFERROR(VLOOKUP(J23,Country_Codes!$B:$B,1,0)=J23,"US State Code Error"),IF(L23="CA",IFERROR(VLOOKUP(J23,Country_Codes!$E:$E,1,0)=J23,"Canada State Code Error"),IF(L23="BR",IFERROR(VLOOKUP(J23,Country_Codes!$H:$H,1,0)=J23,"Brazil State Code Error"),IF(L23="AU",IFERROR(VLOOKUP(J23,Country_Codes!$K:$K,1,0)=J23,"Australia State Code Error"),""))))) | AB23: =IF(OR(L23="US",L23="CA",L23="BR",L23="AU"),IF((EXACT(UPPER(J23),J23)),"","Country Code Casing"),IF(EXACT(J23,PROPER(J23)),"","Billing State casing")) | AC23: {=IFERROR(_xlfn.IFS(IF(AND(LEN(I23)=0,ISBLANK(I23)=FALSE),"",ISNUMBER(SEARCH(I23,H23))),"City/Postal Code/Country Found in Address",IF(AND(LEN(K23)=0,ISBLANK(K23)=FALSE),"",ISNUMBER(SEARCH(K23,H23))),"City/Postal Code/Country Found in Address",IF(AND(LEN(L23)=0,ISBLANK(L23)=FALSE),"",ISNUMBER(SEARCH(", "&L23,H23))),"City/Postal Code/Country Found in Address",IF(AND(LEN(J23)=0,ISBLANK(J23)=FALSE),"",ISNUMBER(SEARCH(", "&J23,H23))),"City/Postal Code/Country Found in Address",IF(AND(LEN(L23)=0,ISBLANK(L23)=FALSE),"",ISNUMBER(SEARCH(","&L23,H23))),"City/Postal Code/Country Found in Address",IF(AND(LEN(J23)=0,ISBLANK(J23)=FALSE),"",ISNUMBER(SEARCH(","&J23,H23))),"City/Postal Code/Country Found in Address"),"")} | AD23: =IF(ISNUMBER(SEARCH("PO",N23)),"PO# Entered in Tax ID Field","") | AE23: {=IFERROR(IF(VLOOKUP(LEFT(M23,MIN(SEARCH({1,2,3,4,5,6,7,8,9,0},M23&{1,2,3,4,5,6,7,8,9,0}))-1),Country_Codes!$N:$N,1,0)>0,"PO Number may be incorrect",""),"")} | AF23: =IF(N23="","",IF(EXACT(L23,LEFT(N23,2)),IF(EXACT(MID(N23,3,1)," "),"Check the Space inbetween County code & VAT",""),"Check the VAT Country Code Format")) | AG23: =IF((ISNUMBER(SEARCH("@",P23)))>0,"",IF(IF(--(ISNUMBER(SEARCH("'",P23)))>0,OR(EXACT(PROPER(P23),P23),EXACT((PROPER(LEFT(P23,FIND("'",P23)-2))&LOWER(MID(P23,FIND("'",P23)-1,1))&PROPER(MID(P23,FIND("'",P23)+0,LEN(P23)-FIND("'",P23)+1))),P23)),"Please check Billing Contact Casing")=TRUE,"","Please check Billing Contact casing")) | AH23: =IF(OR(L23="AS",L23="FM",L23="GU",L23="MH",L23="MP",L23="PW",L23="PR",L23="VI",L23="UM"),"US Territories Check","") | AI23: {=IF(G23="","",_xlfn.IFNA(_xlfn.IFS(L23=VLOOKUP(L23,Country_Codes!$M:$M,1,0)=TRUE,""),"Please check the country code"))} | AJ23: =IF(S23="","",S23&"; ")&IF(T23="","",T23&"; ")&IF(U23="","",U23&"; ")&IF(V23="","",V23&"; ")&IF(AF23="","",AF23&"; ")&IF(AG23="","",AG23&"; ")&IF(AH23="","",AH23&"; ")&IF(Z23="","",Z23&"; ")&IF(AA23="","",AA23&"; ")&IF(AB23="","",AB23&"; ")&IF(AC23="","",AC23&"; ")&IF(AD23="","",AD23&"; ")&IF(AE23="","",AE23&"; ")&IF(AI23="","",AI23&"; ")&IF(W23="","",W23&"; ")&IF(X23="","",X23&"; ")&IF(Y23="","",Y23&"; ") | AM23: =(COUNTA(S23:V23)-COUNTIFS((S23:V23),""))+(COUNTA(AB23)-COUNTIFS((AB23),""))+(COUNTA(AG23)-COUNTIFS((AG23),"")) -> 0 | AN23: =(COUNTA(W23)-COUNTIFS((W23),""))+(COUNTA(Z23)-COUNTIFS((Z23),"")) -> 0 | AO23: =(COUNTA(AA23)-COUNTIFS((AA23),""))+(COUNTA(AC23:AE23)-COUNTIFS((AC23:AE23),""))+(COUNTA(AH23:AI23)-COUNTIFS((AH23:AI23),"")) -> 0 | AP23: =(COUNTA(X23:Y23)-COUNTIFS((X23:Y23),""))+(COUNTA(AF23)-COUNTIFS((AF23),"")) -> 0 | AQ23: =SUM(AM23:AP23) -> 0 | AV23: 45443
A24: 45636 | B24: User 2 | C24: PO Number | E24: _00575 | F24: Sample Technologies, Inc. | G24: ID_Num_6 | H24: 10000 Sample Way | I24: Redwood City | J24: CA | K24: 94063 | L24: US | P24: Accounts Payable | R24: =IF(G24=G23,"","Unique Record") | S24: =IF(F24="","",IF(EXACT(F24,(UPPER(F24))),"Account Upper Case","")) | T24: =IF(F24="","",IF(EXACT(F24,(LOWER(F24))),"Account Lower Case","")) | U24: =IF(EXACT(H24,PROPER(H24)),"","Billing Street - casing") | V24: =IF(EXACT(I24,PROPER(I24)),"","City - casing") | W24: =IF(OR(ISNUMBER(SEARCH("East",I24)),ISNUMBER(SEARCH("West",I24)),ISNUMBER(SEARCH("North",I24)),ISNUMBER(SEARCH("South",I24))),"",IF(OR(ISNUMBER(SEARCH("St.",I24)),ISNUMBER(SEARCH("St ",I24))),"Check St in city field",IF(RIGHT(I24,1)=".","Dot found in city field",""))) | X24: {=IF((SUMPRODUCT(--ISNUMBER(SEARCH({"!","@","#","$","%","^","&","~*","(",")","_","+","=","{","}","[","]","|","\",":",";","'","""","<",">",",",".","~?","/","~~","`"}, I24)))>0)=TRUE,"Special Characters Found in City","")} | Y24: {=IF((SUMPRODUCT(--ISNUMBER(SEARCH({"!","@","#","$","%","^","~*","(",")","_","+","=","{","}","[","]","|","\",":",";","'","""","<",">","~?","/","~~","`"},F24)))>0)=TRUE,"Special Characters Found in Account field","")} | Z24: {=IF(SUM(--ISNUMBER(SEARCH({1,2,3,4,5,6,7,8,9,0},MID(H24,(SEARCH(" E ",H24)-1),1))))+SUM(--ISNUMBER(SEARCH({1,2,3,4,5,6,7,8,9,0},MID(H24,(SEARCH(" E ",H24)+3),1))))=2,"",IF(SUM(--ISNUMBER(SEARCH({"Parte E","Apoquindo N"},H24)))>0,"",IF(OR(RIGHT(H24,3)=" NE",RIGHT(H24,3)=" NW",RIGHT(H24,3)=" SW",RIGHT(H24,3)=" SE",RIGHT(H24,2)=" N",RIGHT(H24,2)=" E",RIGHT(H24,2)=" W",RIGHT(H24,2)=" S",LEFT(H24,3)="NE ",LEFT(H24,3)="NW ",LEFT(H24,3)="SW ",LEFT(H24,3)="SE ",LEFT(H24,2)="N ",LEFT(H24,2)="E ",LEFT(H24,2)="W ",LEFT(H24,2)="S "),"Directional Check",IF(SUM(--ISNUMBER(SEARCH({" N "," E "," W "," S "," NE "," NW "," SW "," SE ","N.E","N.W","S.W","S.E","E.","N.","S.","W."},H24)))>0,"Directional Check",IF(SUM(--ISNUMBER(SEARCH({1,2,3,4,5,6,7,8,9,0},MID(H24,(SEARCH("nd ",H24)-1),1))))+SUM(--ISNUMBER(SEARCH({1,2,3,4,5,6,7,8,9,0},MID(H24,(SEARCH("rd ",H24)-1),1)))+SUM(--ISNUMBER(SEARCH({1,2,3,4,5,6,7,8,9,0},MID(H24,(SEARCH("st ",H24)-1),1))))+SUM(--ISNUMBER(SEARCH({1,2,3,4,5,6,7,8,9,0},MID(H24,(SEARCH("th ",H24)-1),1)))))>0,"","")))))} | AA24: =IF(IF(L24="US",IFERROR(VLOOKUP(J24,Country_Codes!$B:$B,1,0)=J24,"US State Code Error"),IF(L24="CA",IFERROR(VLOOKUP(J24,Country_Codes!$E:$E,1,0)=J24,"Canada State Code Error"),IF(L24="BR",IFERROR(VLOOKUP(J24,Country_Codes!$H:$H,1,0)=J24,"Brazil State Code Error"),IF(L24="AU",IFERROR(VLOOKUP(J24,Country_Codes!$K:$K,1,0)=J24,"Australia State Code Error"),""))))=TRUE,"",IF(L24="US",IFERROR(VLOOKUP(J24,Country_Codes!$B:$B,1,0)=J24,"US State Code Error"),IF(L24="CA",IFERROR(VLOOKUP(J24,Country_Codes!$E:$E,1,0)=J24,"Canada State Code Error"),IF(L24="BR",IFERROR(VLOOKUP(J24,Country_Codes!$H:$H,1,0)=J24,"Brazil State Code Error"),IF(L24="AU",IFERROR(VLOOKUP(J24,Country_Codes!$K:$K,1,0)=J24,"Australia State Code Error"),""))))) | AB24: =IF(OR(L24="US",L24="CA",L24="BR",L24="AU"),IF((EXACT(UPPER(J24),J24)),"","Country Code Casing"),IF(EXACT(J24,PROPER(J24)),"","Billing State casing")) | AC24: {=IFERROR(_xlfn.IFS(IF(AND(LEN(I24)=0,ISBLANK(I24)=FALSE),"",ISNUMBER(SEARCH(I24,H24))),"City/Postal Code/Country Found in Address",IF(AND(LEN(K24)=0,ISBLANK(K24)=FALSE),"",ISNUMBER(SEARCH(K24,H24))),"City/Postal Code/Country Found in Address",IF(AND(LEN(L24)=0,ISBLANK(L24)=FALSE),"",ISNUMBER(SEARCH(", "&L24,H24))),"City/Postal Code/Country Found in Address",IF(AND(LEN(J24)=0,ISBLANK(J24)=FALSE),"",ISNUMBER(SEARCH(", "&J24,H24))),"City/Postal Code/Country Found in Address",IF(AND(LEN(L24)=0,ISBLANK(L24)=FALSE),"",ISNUMBER(SEARCH(","&L24,H24))),"City/Postal Code/Country Found in Address",IF(AND(LEN(J24)=0,ISBLANK(J24)=FALSE),"",ISNUMBER(SEARCH(","&J24,H24))),"City/Postal Code/Country Found in Address"),"")} | AD24: =IF(ISNUMBER(SEARCH("PO",N24)),"PO# Entered in Tax ID Field","") | AE24: {=IFERROR(IF(VLOOKUP(LEFT(M24,MIN(SEARCH({1,2,3,4,5,6,7,8,9,0},M24&{1,2,3,4,5,6,7,8,9,0}))-1),Country_Codes!$N:$N,1,0)>0,"PO Number may be incorrect",""),"")} | AF24: =IF(N24="","",IF(EXACT(L24,LEFT(N24,2)),IF(EXACT(MID(N24,3,1)," "),"Check the Space inbetween County code & VAT",""),"Check the VAT Country Code Format")) | AG24: =IF((ISNUMBER(SEARCH("@",P24)))>0,"",IF(IF(--(ISNUMBER(SEARCH("'",P24)))>0,OR(EXACT(PROPER(P24),P24),EXACT((PROPER(LEFT(P24,FIND("'",P24)-2))&LOWER(MID(P24,FIND("'",P24)-1,1))&PROPER(MID(P24,FIND("'",P24)+0,LEN(P24)-FIND("'",P24)+1))),P24)),"Please check Billing Contact Casing")=TRUE,"","Please check Billing Contact casing")) | AH24: =IF(OR(L24="AS",L24="FM",L24="GU",L24="MH",L24="MP",L24="PW",L24="PR",L24="VI",L24="UM"),"US Territories Check","") | AI24: {=IF(G24="","",_xlfn.IFNA(_xlfn.IFS(L24=VLOOKUP(L24,Country_Codes!$M:$M,1,0)=TRUE,""),"Please check the country code"))} | AJ24: =IF(S24="","",S24&"; ")&IF(T24="","",T24&"; ")&IF(U24="","",U24&"; ")&IF(V24="","",V24&"; ")&IF(AF24="","",AF24&"; ")&IF(AG24="","",AG24&"; ")&IF(AH24="","",AH24&"; ")&IF(Z24="","",Z24&"; ")&IF(AA24="","",AA24&"; ")&IF(AB24="","",AB24&"; ")&IF(AC24="","",AC24&"; ")&IF(AD24="","",AD24&"; ")&IF(AE24="","",AE24&"; ")&IF(AI24="","",AI24&"; ")&IF(W24="","",W24&"; ")&IF(X24="","",X24&"; ")&IF(Y24="","",Y24&"; ") | AM24: =(COUNTA(S24:V24)-COUNTIFS((S24:V24),""))+(COUNTA(AB24)-COUNTIFS((AB24),""))+(COUNTA(AG24)-COUNTIFS((AG24),"")) -> 0 | AN24: =(COUNTA(W24)-COUNTIFS((W24),""))+(COUNTA(Z24)-COUNTIFS((Z24),"")) -> 0 | AO24: =(COUNTA(AA24)-COUNTIFS((AA24),""))+(COUNTA(AC24:AE24)-COUNTIFS((AC24:AE24),""))+(COUNTA(AH24:AI24)-COUNTIFS((AH24:AI24),"")) -> 0 | AP24: =(COUNTA(X24:Y24)-COUNTIFS((X24:Y24),""))+(COUNTA(AF24)-COUNTIFS((AF24),"")) -> 0 | AQ24: =SUM(AM24:AP24) -> 0 | AV24: 45444
A25: 45590 | B25: User 1 | C25: PO Number | D25: PO-007496 | E25: PO-017004 | F25: Sample, Inc. | G25: ID_Num_1 | H25: Suite 30000A, Street | I25: bozeman | J25: MT | K25: 59715 | L25: US | M25: PO-017 | P25: Accounts Payable | R25: =IF(G25=G24,"","Unique Record") -> Unique Record | S25: =IF(F25="","",IF(EXACT(F25,(UPPER(F25))),"Account Upper Case","")) | T25: =IF(F25="","",IF(EXACT(F25,(LOWER(F25))),"Account Lower Case","")) | U25: =IF(EXACT(H25,PROPER(H25)),"","Billing Street - casing") | V25: =IF(EXACT(I25,PROPER(I25)),"","City - casing") -> City - casing | W25: =IF(OR(ISNUMBER(SEARCH("East",I25)),ISNUMBER(SEARCH("West",I25)),ISNUMBER(SEARCH("North",I25)),ISNUMBER(SEARCH("South",I25))),"",IF(OR(ISNUMBER(SEARCH("St.",I25)),ISNUMBER(SEARCH("St ",I25))),"Check St in city field",IF(RIGHT(I25,1)=".","Dot found in city field",""))) | X25: {=IF((SUMPRODUCT(--ISNUMBER(SEARCH({"!","@","#","$","%","^","&","~*","(",")","_","+","=","{","}","[","]","|","\",":",";","'","""","<",">",",",".","~?","/","~~","`"}, I25)))>0)=TRUE,"Special Characters Found in City","")} | Y25: {=IF((SUMPRODUCT(--ISNUMBER(SEARCH({"!","@","#","$","%","^","~*","(",")","_","+","=","{","}","[","]","|","\",":",";","'","""","<",">","~?","/","~~","`"},F25)))>0)=TRUE,"Special Characters Found in Account field","")} | Z25: {=IF(SUM(--ISNUMBER(SEARCH({1,2,3,4,5,6,7,8,9,0},MID(H25,(SEARCH(" E ",H25)-1),1))))+SUM(--ISNUMBER(SEARCH({1,2,3,4,5,6,7,8,9,0},MID(H25,(SEARCH(" E ",H25)+3),1))))=2,"",IF(SUM(--ISNUMBER(SEARCH({"Parte E","Apoquindo N"},H25)))>0,"",IF(OR(RIGHT(H25,3)=" NE",RIGHT(H25,3)=" NW",RIGHT(H25,3)=" SW",RIGHT(H25,3)=" SE",RIGHT(H25,2)=" N",RIGHT(H25,2)=" E",RIGHT(H25,2)=" W",RIGHT(H25,2)=" S",LEFT(H25,3)="NE ",LEFT(H25,3)="NW ",LEFT(H25,3)="SW ",LEFT(H25,3)="SE ",LEFT(H25,2)="N ",LEFT(H25,2)="E ",LEFT(H25,2)="W ",LEFT(H25,2)="S "),"Directional Check",IF(SUM(--ISNUMBER(SEARCH({" N "," E "," W "," S "," NE "," NW "," SW "," SE ","N.E","N.W","S.W","S.E","E.","N.","S.","W."},H25)))>0,"Directional Check",IF(SUM(--ISNUMBER(SEARCH({1,2,3,4,5,6,7,8,9,0},MID(H25,(SEARCH("nd ",H25)-1),1))))+SUM(--ISNUMBER(SEARCH({1,2,3,4,5,6,7,8,9,0},MID(H25,(SEARCH("rd ",H25)-1),1)))+SUM(--ISNUMBER(SEARCH({1,2,3,4,5,6,7,8,9,0},MID(H25,(SEARCH("st ",H25)-1),1))))+SUM(--ISNUMBER(SEARCH({1,2,3,4,5,6,7,8,9,0},MID(H25,(SEARCH("th ",H25)-1),1)))))>0,"","")))))} | AA25: =IF(IF(L25="US",IFERROR(VLOOKUP(J25,Country_Codes!$B:$B,1,0)=J25,"US State Code Error"),IF(L25="CA",IFERROR(VLOOKUP(J25,Country_Codes!$E:$E,1,0)=J25,"Canada State Code Error"),IF(L25="BR",IFERROR(VLOOKUP(J25,Country_Codes!$H:$H,1,0)=J25,"Brazil State Code Error"),IF(L25="AU",IFERROR(VLOOKUP(J25,Country_Codes!$K:$K,1,0)=J25,"Australia State Code Error"),""))))=TRUE,"",IF(L25="US",IFERROR(VLOOKUP(J25,Country_Codes!$B:$B,1,0)=J25,"US State Code Error"),IF(L25="CA",IFERROR(VLOOKUP(J25,Country_Codes!$E:$E,1,0)=J25,"Canada State Code Error"),IF(L25="BR",IFERROR(VLOOKUP(J25,Country_Codes!$H:$H,1,0)=J25,"Brazil State Code Error"),IF(L25="AU",IFERROR(VLOOKUP(J25,Country_Codes!$K:$K,1,0)=J25,"Australia State Code Error"),""))))) | AB25: =IF(OR(L25="US",L25="CA",L25="BR",L25="AU"),IF((EXACT(UPPER(J25),J25)),"","Country Code Casing"),IF(EXACT(J25,PROPER(J25)),"","Billing State casing")) | AC25: {=IFERROR(_xlfn.IFS(IF(AND(LEN(I25)=0,ISBLANK(I25)=FALSE),"",ISNUMBER(SEARCH(I25,H25))),"City/Postal Code/Country Found in Address",IF(AND(LEN(K25)=0,ISBLANK(K25)=FALSE),"",ISNUMBER(SEARCH(K25,H25))),"City/Postal Code/Country Found in Address",IF(AND(LEN(L25)=0,ISBLANK(L25)=FALSE),"",ISNUMBER(SEARCH(", "&L25,H25))),"City/Postal Code/Country Found in Address",IF(AND(LEN(J25)=0,ISBLANK(J25)=FALSE),"",ISNUMBER(SEARCH(", "&J25,H25))),"City/Postal Code/Country Found in Address",IF(AND(LEN(L25)=0,ISBLANK(L25)=FALSE),"",ISNUMBER(SEARCH(","&L25,H25))),"City/Postal Code/Country Found in Address",IF(AND(LEN(J25)=0,ISBLANK(J25)=FALSE),"",ISNUMBER(SEARCH(","&J25,H25))),"City/Postal Code/Country Found in Address"),"")} | AD25: =IF(ISNUMBER(SEARCH("PO",N25)),"PO# Entered in Tax ID Field","") | AE25: {=IFERROR(IF(VLOOKUP(LEFT(M25,MIN(SEARCH({1,2,3,4,5,6,7,8,9,0},M25&{1,2,3,4,5,6,7,8,9,0}))-1),Country_Codes!$N:$N,1,0)>0,"PO Number may be incorrect",""),"")} | AF25: =IF(N25="","",IF(EXACT(L25,LEFT(N25,2)),IF(EXACT(MID(N25,3,1)," "),"Check the Space inbetween County code & VAT",""),"Check the VAT Country Code Format")) | AG25: =IF((ISNUMBER(SEARCH("@",P25)))>0,"",IF(IF(--(ISNUMBER(SEARCH("'",P25)))>0,OR(EXACT(PROPER(P25),P25),EXACT((PROPER(LEFT(P25,FIND("'",P25)-2))&LOWER(MID(P25,FIND("'",P25)-1,1))&PROPER(MID(P25,FIND("'",P25)+0,LEN(P25)-FIND("'",P25)+1))),P25)),"Please check Billing Contact Casing")=TRUE,"","Please check Billing Contact casing")) | AH25: =IF(OR(L25="AS",L25="FM",L25="GU",L25="MH",L25="MP",L25="PW",L25="PR",L25="VI",L25="UM"),"US Territories Check","") | AI25: {=IF(G25="","",_xlfn.IFNA(_xlfn.IFS(L25=VLOOKUP(L25,Country_Codes!$M:$M,1,0)=TRUE,""),"Please check the country code"))} | AJ25: =IF(S25="","",S25&"; ")&IF(T25="","",T25&"; ")&IF(U25="","",U25&"; ")&IF(V25="","",V25&"; ")&IF(AF25="","",AF25&"; ")&IF(AG25="","",AG25&"; ")&IF(AH25="","",AH25&"; ")&IF(Z25="","",Z25&"; ")&IF(AA25="","",AA25&"; ")&IF(AB25="","",AB25&"; ")&IF(AC25="","",AC25&"; ")&IF(AD25="","",AD25&"; ")&IF(AE25="","",AE25&"; ")&IF(AI25="","",AI25&"; ")&IF(W25="","",W25&"; ")&IF(X25="","",X25&"; ")&IF(Y25="","",Y25&"; ") -> City - casing; | AM25: =(COUNTA(S25:V25)-COUNTIFS((S25:V25),""))+(COUNTA(AB25)-COUNTIFS((AB25),""))+(COUNTA(AG25)-COUNTIFS((AG25),"")) -> 1 | AN25: =(COUNTA(W25)-COUNTIFS((W25),""))+(COUNTA(Z25)-COUNTIFS((Z25),"")) -> 0 | AO25: =(COUNTA(AA25)-COUNTIFS((AA25),""))+(COUNTA(AC25:AE25)-COUNTIFS((AC25:AE25),""))+(COUNTA(AH25:AI25)-COUNTIFS((AH25:AI25),"")) -> 0 | AP25: =(COUNTA(X25:Y25)-COUNTIFS((X25:Y25),""))+(COUNTA(AF25)-COUNTIFS((AF25),"")) -> 0 | AQ25: =SUM(AM25:AP25) -> 1 | AV25: 45445
A26: 45594 | B26: User 1 | C26: Account Name | D26: Sample Inc. | E26: Sample, Inc. | F26: Sample, Inc. | G26: ID_Num_1 | H26: Suite 30000A, Street | I26: Bozeman | J26: MT | K26: 59715 | L26: US | M26: PO-017 | P26: Accounts Payable | R26: =IF(G26=G25,"","Unique Record") | S26: =IF(F26="","",IF(EXACT(F26,(UPPER(F26))),"Account Upper Case","")) | T26: =IF(F26="","",IF(EXACT(F26,(LOWER(F26))),"Account Lower Case","")) | U26: =IF(EXACT(H26,PROPER(H26)),"","Billing Street - casing") | V26: =IF(EXACT(I26,PROPER(I26)),"","City - casing") | W26: =IF(OR(ISNUMBER(SEARCH("East",I26)),ISNUMBER(SEARCH("West",I26)),ISNUMBER(SEARCH("North",I26)),ISNUMBER(SEARCH("South",I26))),"",IF(OR(ISNUMBER(SEARCH("St.",I26)),ISNUMBER(SEARCH("St ",I26))),"Check St in city field",IF(RIGHT(I26,1)=".","Dot found in city field",""))) | X26: {=IF((SUMPRODUCT(--ISNUMBER(SEARCH({"!","@","#","$","%","^","&","~*","(",")","_","+","=","{","}","[","]","|","\",":",";","'","""","<",">",",",".","~?","/","~~","`"}, I26)))>0)=TRUE,"Special Characters Found in City","")} | Y26: {=IF((SUMPRODUCT(--ISNUMBER(SEARCH({"!","@","#","$","%","^","~*","(",")","_","+","=","{","}","[","]","|","\",":",";","'","""","<",">","~?","/","~~","`"},F26)))>0)=TRUE,"Special Characters Found in Account field","")} | Z26: {=IF(SUM(--ISNUMBER(SEARCH({1,2,3,4,5,6,7,8,9,0},MID(H26,(SEARCH(" E ",H26)-1),1))))+SUM(--ISNUMBER(SEARCH({1,2,3,4,5,6,7,8,9,0},MID(H26,(SEARCH(" E ",H26)+3),1))))=2,"",IF(SUM(--ISNUMBER(SEARCH({"Parte E","Apoquindo N"},H26)))>0,"",IF(OR(RIGHT(H26,3)=" NE",RIGHT(H26,3)=" NW",RIGHT(H26,3)=" SW",RIGHT(H26,3)=" SE",RIGHT(H26,2)=" N",RIGHT(H26,2)=" E",RIGHT(H26,2)=" W",RIGHT(H26,2)=" S",LEFT(H26,3)="NE ",LEFT(H26,3)="NW ",LEFT(H26,3)="SW ",LEFT(H26,3)="SE ",LEFT(H26,2)="N ",LEFT(H26,2)="E ",LEFT(H26,2)="W ",LEFT(H26,2)="S "),"Directional Check",IF(SUM(--ISNUMBER(SEARCH({" N "," E "," W "," S "," NE "," NW "," SW "," SE ","N.E","N.W","S.W","S.E","E.","N.","S.","W."},H26)))>0,"Directional Check",IF(SUM(--ISNUMBER(SEARCH({1,2,3,4,5,6,7,8,9,0},MID(H26,(SEARCH("nd ",H26)-1),1))))+SUM(--ISNUMBER(SEARCH({1,2,3,4,5,6,7,8,9,0},MID(H26,(SEARCH("rd ",H26)-1),1)))+SUM(--ISNUMBER(SEARCH({1,2,3,4,5,6,7,8,9,0},MID(H26,(SEARCH("st ",H26)-1),1))))+SUM(--ISNUMBER(SEARCH({1,2,3,4,5,6,7,8,9,0},MID(H26,(SEARCH("th ",H26)-1),1)))))>0,"","")))))} | AA26: =IF(IF(L26="US",IFERROR(VLOOKUP(J26,Country_Codes!$B:$B,1,0)=J26,"US State Code Error"),IF(L26="CA",IFERROR(VLOOKUP(J26,Country_Codes!$E:$E,1,0)=J26,"Canada State Code Error"),IF(L26="BR",IFERROR(VLOOKUP(J26,Country_Codes!$H:$H,1,0)=J26,"Brazil State Code Error"),IF(L26="AU",IFERROR(VLOOKUP(J26,Country_Codes!$K:$K,1,0)=J26,"Australia State Code Error"),""))))=TRUE,"",IF(L26="US",IFERROR(VLOOKUP(J26,Country_Codes!$B:$B,1,0)=J26,"US State Code Error"),IF(L26="CA",IFERROR(VLOOKUP(J26,Country_Codes!$E:$E,1,0)=J26,"Canada State Code Error"),IF(L26="BR",IFERROR(VLOOKUP(J26,Country_Codes!$H:$H,1,0)=J26,"Brazil State Code Error"),IF(L26="AU",IFERROR(VLOOKUP(J26,Country_Codes!$K:$K,1,0)=J26,"Australia State Code Error"),""))))) | AB26: =IF(OR(L26="US",L26="CA",L26="BR",L26="AU"),IF((EXACT(UPPER(J26),J26)),"","Country Code Casing"),IF(EXACT(J26,PROPER(J26)),"","Billing State casing")) | AC26: {=IFERROR(_xlfn.IFS(IF(AND(LEN(I26)=0,ISBLANK(I26)=FALSE),"",ISNUMBER(SEARCH(I26,H26))),"City/Postal Code/Country Found in Address",IF(AND(LEN(K26)=0,ISBLANK(K26)=FALSE),"",ISNUMBER(SEARCH(K26,H26))),"City/Postal Code/Country Found in Address",IF(AND(LEN(L26)=0,ISBLANK(L26)=FALSE),"",ISNUMBER(SEARCH(", "&L26,H26))),"City/Postal Code/Country Found in Address",IF(AND(LEN(J26)=0,ISBLANK(J26)=FALSE),"",ISNUMBER(SEARCH(", "&J26,H26))),"City/Postal Code/Country Found in Address",IF(AND(LEN(L26)=0,ISBLANK(L26)=FALSE),"",ISNUMBER(SEARCH(","&L26,H26))),"City/Postal Code/Country Found in Address",IF(AND(LEN(J26)=0,ISBLANK(J26)=FALSE),"",ISNUMBER(SEARCH(","&J26,H26))),"City/Postal Code/Country Found in Address"),"")} | AD26: =IF(ISNUMBER(SEARCH("PO",N26)),"PO# Entered in Tax ID Field","") | AE26: {=IFERROR(IF(VLOOKUP(LEFT(M26,MIN(SEARCH({1,2,3,4,5,6,7,8,9,0},M26&{1,2,3,4,5,6,7,8,9,0}))-1),Country_Codes!$N:$N,1,0)>0,"PO Number may be incorrect",""),"")} | AF26: =IF(N26="","",IF(EXACT(L26,LEFT(N26,2)),IF(EXACT(MID(N26,3,1)," "),"Check the Space inbetween County code & VAT",""),"Check the VAT Country Code Format")) | AG26: =IF((ISNUMBER(SEARCH("@",P26)))>0,"",IF(IF(--(ISNUMBER(SEARCH("'",P26)))>0,OR(EXACT(PROPER(P26),P26),EXACT((PROPER(LEFT(P26,FIND("'",P26)-2))&LOWER(MID(P26,FIND("'",P26)-1,1))&PROPER(MID(P26,FIND("'",P26)+0,LEN(P26)-FIND("'",P26)+1))),P26)),"Please check Billing Contact Casing")=TRUE,"","Please check Billing Contact casing")) | AH26: =IF(OR(L26="AS",L26="FM",L26="GU",L26="MH",L26="MP",L26="PW",L26="PR",L26="VI",L26="UM"),"US Territories Check","") | AI26: {=IF(G26="","",_xlfn.IFNA(_xlfn.IFS(L26=VLOOKUP(L26,Country_Codes!$M:$M,1,0)=TRUE,""),"Please check the country code"))} | AJ26: =IF(S26="","",S26&"; ")&IF(T26="","",T26&"; ")&IF(U26="","",U26&"; ")&IF(V26="","",V26&"; ")&IF(AF26="","",AF26&"; ")&IF(AG26="","",AG26&"; ")&IF(AH26="","",AH26&"; ")&IF(Z26="","",Z26&"; ")&IF(AA26="","",AA26&"; ")&IF(AB26="","",AB26&"; ")&IF(AC26="","",AC26&"; ")&IF(AD26="","",AD26&"; ")&IF(AE26="","",AE26&"; ")&IF(AI26="","",AI26&"; ")&IF(W26="","",W26&"; ")&IF(X26="","",X26&"; ")&IF(Y26="","",Y26&"; ") | AM26: =(COUNTA(S26:V26)-COUNTIFS((S26:V26),""))+(COUNTA(AB26)-COUNTIFS((AB26),""))+(COUNTA(AG26)-COUNTIFS((AG26),"")) -> 0 | AN26: =(COUNTA(W26)-COUNTIFS((W26),""))+(COUNTA(Z26)-COUNTIFS((Z26),"")) -> 0 | AO26: =(COUNTA(AA26)-COUNTIFS((AA26),""))+(COUNTA(AC26:AE26)-COUNTIFS((AC26:AE26),""))+(COUNTA(AH26:AI26)-COUNTIFS((AH26:AI26),"")) -> 0 | AP26: =(COUNTA(X26:Y26)-COUNTIFS((X26:Y26),""))+(COUNTA(AF26)-COUNTIFS((AF26),"")) -> 0 | AQ26: =SUM(AM26:AP26) -> 0 | AV26: 45446
A27: 45596 | B27: User 2 | C27: Bill To Contact | D27: ID-0001a000 | E27: ID-0002a000 | F27: Sample Partners | G27: ID_Num_2 | H27: 50000 Street | I27: Dallas | J27: TX | K27: 75201 | L27: US | O27: Justin Frank | R27: =IF(G27=G26,"","Unique Record") -> Unique Record | S27: =IF(F27="","",IF(EXACT(F27,(UPPER(F27))),"Account Upper Case","")) | T27: =IF(F27="","",IF(EXACT(F27,(LOWER(F27))),"Account Lower Case","")) | U27: =IF(EXACT(H27,PROPER(H27)),"","Billing Street - casing") | V27: =IF(EXACT(I27,PROPER(I27)),"","City - casing") | W27: =IF(OR(ISNUMBER(SEARCH("East",I27)),ISNUMBER(SEARCH("West",I27)),ISNUMBER(SEARCH("North",I27)),ISNUMBER(SEARCH("South",I27))),"",IF(OR(ISNUMBER(SEARCH("St.",I27)),ISNUMBER(SEARCH("St ",I27))),"Check St in city field",IF(RIGHT(I27,1)=".","Dot found in city field",""))) | X27: {=IF((SUMPRODUCT(--ISNUMBER(SEARCH({"!","@","#","$","%","^","&","~*","(",")","_","+","=","{","}","[","]","|","\",":",";","'","""","<",">",",",".","~?","/","~~","`"}, I27)))>0)=TRUE,"Special Characters Found in City","")} | Y27: {=IF((SUMPRODUCT(--ISNUMBER(SEARCH({"!","@","#","$","%","^","~*","(",")","_","+","=","{","}","[","]","|","\",":",";","'","""","<",">","~?","/","~~","`"},F27)))>0)=TRUE,"Special Characters Found in Account field","")} | Z27: {=IF(SUM(--ISNUMBER(SEARCH({1,2,3,4,5,6,7,8,9,0},MID(H27,(SEARCH(" E ",H27)-1),1))))+SUM(--ISNUMBER(SEARCH({1,2,3,4,5,6,7,8,9,0},MID(H27,(SEARCH(" E ",H27)+3),1))))=2,"",IF(SUM(--ISNUMBER(SEARCH({"Parte E","Apoquindo N"},H27)))>0,"",IF(OR(RIGHT(H27,3)=" NE",RIGHT(H27,3)=" NW",RIGHT(H27,3)=" SW",RIGHT(H27,3)=" SE",RIGHT(H27,2)=" N",RIGHT(H27,2)=" E",RIGHT(H27,2)=" W",RIGHT(H27,2)=" S",LEFT(H27,3)="NE ",LEFT(H27,3)="NW ",LEFT(H27,3)="SW ",LEFT(H27,3)="SE ",LEFT(H27,2)="N ",LEFT(H27,2)="E ",LEFT(H27,2)="W ",LEFT(H27,2)="S "),"Directional Check",IF(SUM(--ISNUMBER(SEARCH({" N "," E "," W "," S "," NE "," NW "," SW "," SE ","N.E","N.W","S.W","S.E","E.","N.","S.","W."},H27)))>0,"Directional Check",IF(SUM(--ISNUMBER(SEARCH({1,2,3,4,5,6,7,8,9,0},MID(H27,(SEARCH("nd ",H27)-1),1))))+SUM(--ISNUMBER(SEARCH({1,2,3,4,5,6,7,8,9,0},MID(H27,(SEARCH("rd ",H27)-1),1)))+SUM(--ISNUMBER(SEARCH({1,2,3,4,5,6,7,8,9,0},MID(H27,(SEARCH("st ",H27)-1),1))))+SUM(--ISNUMBER(SEARCH({1,2,3,4,5,6,7,8,9,0},MID(H27,(SEARCH("th ",H27)-1),1)))))>0,"","")))))} | AA27: =IF(IF(L27="US",IFERROR(VLOOKUP(J27,Country_Codes!$B:$B,1,0)=J27,"US State Code Error"),IF(L27="CA",IFERROR(VLOOKUP(J27,Country_Codes!$E:$E,1,0)=J27,"Canada State Code Error"),IF(L27="BR",IFERROR(VLOOKUP(J27,Country_Codes!$H:$H,1,0)=J27,"Brazil State Code Error"),IF(L27="AU",IFERROR(VLOOKUP(J27,Country_Codes!$K:$K,1,0)=J27,"Australia State Code Error"),""))))=TRUE,"",IF(L27="US",IFERROR(VLOOKUP(J27,Country_Codes!$B:$B,1,0)=J27,"US State Code Error"),IF(L27="CA",IFERROR(VLOOKUP(J27,Country_Codes!$E:$E,1,0)=J27,"Canada State Code Error"),IF(L27="BR",IFERROR(VLOOKUP(J27,Country_Codes!$H:$H,1,0)=J27,"Brazil State Code Error"),IF(L27="AU",IFERROR(VLOOKUP(J27,Country_Codes!$K:$K,1,0)=J27,"Australia State Code Error"),""))))) | AB27: =IF(OR(L27="US",L27="CA",L27="BR",L27="AU"),IF((EXACT(UPPER(J27),J27)),"","Country Code Casing"),IF(EXACT(J27,PROPER(J27)),"","Billing State casing")) | AC27: {=IFERROR(_xlfn.IFS(IF(AND(LEN(I27)=0,ISBLANK(I27)=FALSE),"",ISNUMBER(SEARCH(I27,H27))),"City/Postal Code/Country Found in Address",IF(AND(LEN(K27)=0,ISBLANK(K27)=FALSE),"",ISNUMBER(SEARCH(K27,H27))),"City/Postal Code/Country Found in Address",IF(AND(LEN(L27)=0,ISBLANK(L27)=FALSE),"",ISNUMBER(SEARCH(", "&L27,H27))),"City/Postal Code/Country Found in Address",IF(AND(LEN(J27)=0,ISBLANK(J27)=FALSE),"",ISNUMBER(SEARCH(", "&J27,H27))),"City/Postal Code/Country Found in Address",IF(AND(LEN(L27)=0,ISBLANK(L27)=FALSE),"",ISNUMBER(SEARCH(","&L27,H27))),"City/Postal Code/Country Found in Address",IF(AND(LEN(J27)=0,ISBLANK(J27)=FALSE),"",ISNUMBER(SEARCH(","&J27,H27))),"City/Postal Code/Country Found in Address"),"")} | AD27: =IF(ISNUMBER(SEARCH("PO",N27)),"PO# Entered in Tax ID Field","") | AE27: {=IFERROR(IF(VLOOKUP(LEFT(M27,MIN(SEARCH({1,2,3,4,5,6,7,8,9,0},M27&{1,2,3,4,5,6,7,8,9,0}))-1),Country_Codes!$N:$N,1,0)>0,"PO Number may be incorrect",""),"")} | AF27: =IF(N27="","",IF(EXACT(L27,LEFT(N27,2)),IF(EXACT(MID(N27,3,1)," "),"Check the Space inbetween County code & VAT",""),"Check the VAT Country Code Format")) | AG27: =IF((ISNUMBER(SEARCH("@",P27)))>0,"",IF(IF(--(ISNUMBER(SEARCH("'",P27)))>0,OR(EXACT(PROPER(P27),P27),EXACT((PROPER(LEFT(P27,FIND("'",P27)-2))&LOWER(MID(P27,FIND("'",P27)-1,1))&PROPER(MID(P27,FIND("'",P27)+0,LEN(P27)-FIND("'",P27)+1))),P27)),"Please check Billing Contact Casing")=TRUE,"","Please check Billing Contact casing")) | AH27: =IF(OR(L27="AS",L27="FM",L27="GU",L27="MH",L27="MP",L27="PW",L27="PR",L27="VI",L27="UM"),"US Territories Check","") | AI27: {=IF(G27="","",_xlfn.IFNA(_xlfn.IFS(L27=VLOOKUP(L27,Country_Codes!$M:$M,1,0)=TRUE,""),"Please check the country code"))} | AJ27: =IF(S27="","",S27&"; ")&IF(T27="","",T27&"; ")&IF(U27="","",U27&"; ")&IF(V27="","",V27&"; ")&IF(AF27="","",AF27&"; ")&IF(AG27="","",AG27&"; ")&IF(AH27="","",AH27&"; ")&IF(Z27="","",Z27&"; ")&IF(AA27="","",AA27&"; ")&IF(AB27="","",AB27&"; ")&IF(AC27="","",AC27&"; ")&IF(AD27="","",AD27&"; ")&IF(AE27="","",AE27&"; ")&IF(AI27="","",AI27&"; ")&IF(W27="","",W27&"; ")&IF(X27="","",X27&"; ")&IF(Y27="","",Y27&"; ") | AM27: =(COUNTA(S27:V27)-COUNTIFS((S27:V27),""))+(COUNTA(AB27)-COUNTIFS((AB27),""))+(COUNTA(AG27)-COUNTIFS((AG27),"")) -> 0 | AN27: =(COUNTA(W27)-COUNTIFS((W27),""))+(COUNTA(Z27)-COUNTIFS((Z27),"")) -> 0 | AO27: =(COUNTA(AA27)-COUNTIFS((AA27),""))+(COUNTA(AC27:AE27)-COUNTIFS((AC27:AE27),""))+(COUNTA(AH27:AI27)-COUNTIFS((AH27:AI27),"")) -> 0 | AP27: =(COUNTA(X27:Y27)-COUNTIFS((X27:Y27),""))+(COUNTA(AF27)-COUNTIFS((AF27),"")) -> 0 | AQ27: =SUM(AM27:AP27) -> 0 | AV27: 45448
A28: 45574 | B28: User 1 | C28: Bill To Contact | D28: ID-0003a000 | E28: ID-0004a000 | F28: Sample Products, Inc. | G28: ID_Num_3 | H28: 10000 Sample Court, Suite 200 | I28: Mississauga | J28: ON | K28: L5N 5R5 | L28: CA | M28: 5600004 | O28: Smith Frank | R28: =IF(G28=G27,"","Unique Record") -> Unique Record | S28: =IF(F28="","",IF(EXACT(F28,(UPPER(F28))),"Account Upper Case","")) | T28: =IF(F28="","",IF(EXACT(F28,(LOWER(F28))),"Account Lower Case","")) | U28: =IF(EXACT(H28,PROPER(H28)),"","Billing Street - casing") | V28: =IF(EXACT(I28,PROPER(I28)),"","City - casing") | W28: =IF(OR(ISNUMBER(SEARCH("East",I28)),ISNUMBER(SEARCH("West",I28)),ISNUMBER(SEARCH("North",I28)),ISNUMBER(SEARCH("South",I28))),"",IF(OR(ISNUMBER(SEARCH("St.",I28)),ISNUMBER(SEARCH("St ",I28))),"Check St in city field",IF(RIGHT(I28,1)=".","Dot found in city field",""))) | X28: {=IF((SUMPRODUCT(--ISNUMBER(SEARCH({"!","@","#","$","%","^","&","~*","(",")","_","+","=","{","}","[","]","|","\",":",";","'","""","<",">",",",".","~?","/","~~","`"}, I28)))>0)=TRUE,"Special Characters Found in City","")} | Y28: {=IF((SUMPRODUCT(--ISNUMBER(SEARCH({"!","@","#","$","%","^","~*","(",")","_","+","=","{","}","[","]","|","\",":",";","'","""","<",">","~?","/","~~","`"},F28)))>0)=TRUE,"Special Characters Found in Account field","")} | Z28: {=IF(SUM(--ISNUMBER(SEARCH({1,2,3,4,5,6,7,8,9,0},MID(H28,(SEARCH(" E ",H28)-1),1))))+SUM(--ISNUMBER(SEARCH({1,2,3,4,5,6,7,8,9,0},MID(H28,(SEARCH(" E ",H28)+3),1))))=2,"",IF(SUM(--ISNUMBER(SEARCH({"Parte E","Apoquindo N"},H28)))>0,"",IF(OR(RIGHT(H28,3)=" NE",RIGHT(H28,3)=" NW",RIGHT(H28,3)=" SW",RIGHT(H28,3)=" SE",RIGHT(H28,2)=" N",RIGHT(H28,2)=" E",RIGHT(H28,2)=" W",RIGHT(H28,2)=" S",LEFT(H28,3)="NE ",LEFT(H28,3)="NW ",LEFT(H28,3)="SW ",LEFT(H28,3)="SE ",LEFT(H28,2)="N ",LEFT(H28,2)="E ",LEFT(H28,2)="W ",LEFT(H28,2)="S "),"Directional Check",IF(SUM(--ISNUMBER(SEARCH({" N "," E "," W "," S "," NE "," NW "," SW "," SE ","N.E","N.W","S.W","S.E","E.","N.","S.","W."},H28)))>0,"Directional Check",IF(SUM(--ISNUMBER(SEARCH({1,2,3,4,5,6,7,8,9,0},MID(H28,(SEARCH("nd ",H28)-1),1))))+SUM(--ISNUMBER(SEARCH({1,2,3,4,5,6,7,8,9,0},MID(H28,(SEARCH("rd ",H28)-1),1)))+SUM(--ISNUMBER(SEARCH({1,2,3,4,5,6,7,8,9,0},MID(H28,(SEARCH("st ",H28)-1),1))))+SUM(--ISNUMBER(SEARCH({1,2,3,4,5,6,7,8,9,0},MID(H28,(SEARCH("th ",H28)-1),1)))))>0,"","")))))} | AA28: =IF(IF(L28="US",IFERROR(VLOOKUP(J28,Country_Codes!$B:$B,1,0)=J28,"US State Code Error"),IF(L28="CA",IFERROR(VLOOKUP(J28,Country_Codes!$E:$E,1,0)=J28,"Canada State Code Error"),IF(L28="BR",IFERROR(VLOOKUP(J28,Country_Codes!$H:$H,1,0)=J28,"Brazil State Code Error"),IF(L28="AU",IFERROR(VLOOKUP(J28,Country_Codes!$K:$K,1,0)=J28,"Australia State Code Error"),""))))=TRUE,"",IF(L28="US",IFERROR(VLOOKUP(J28,Country_Codes!$B:$B,1,0)=J28,"US State Code Error"),IF(L28="CA",IFERROR(VLOOKUP(J28,Country_Codes!$E:$E,1,0)=J28,"Canada State Code Error"),IF(L28="BR",IFERROR(VLOOKUP(J28,Country_Codes!$H:$H,1,0)=J28,"Brazil State Code Error"),IF(L28="AU",IFERROR(VLOOKUP(J28,Country_Codes!$K:$K,1,0)=J28,"Australia State Code Error"),""))))) | AB28: =IF(OR(L28="US",L28="CA",L28="BR",L28="AU"),IF((EXACT(UPPER(J28),J28)),"","Country Code Casing"),IF(EXACT(J28,PROPER(J28)),"","Billing State casing")) | AC28: {=IFERROR(_xlfn.IFS(IF(AND(LEN(I28)=0,ISBLANK(I28)=FALSE),"",ISNUMBER(SEARCH(I28,H28))),"City/Postal Code/Country Found in Address",IF(AND(LEN(K28)=0,ISBLANK(K28)=FALSE),"",ISNUMBER(SEARCH(K28,H28))),"City/Postal Code/Country Found in Address",IF(AND(LEN(L28)=0,ISBLANK(L28)=FALSE),"",ISNUMBER(SEARCH(", "&L28,H28))),"City/Postal Code/Country Found in Address",IF(AND(LEN(J28)=0,ISBLANK(J28)=FALSE),"",ISNUMBER(SEARCH(", "&J28,H28))),"City/Postal Code/Country Found in Address",IF(AND(LEN(L28)=0,ISBLANK(L28)=FALSE),"",ISNUMBER(SEARCH(","&L28,H28))),"City/Postal Code/Country Found in Address",IF(AND(LEN(J28)=0,ISBLANK(J28)=FALSE),"",ISNUMBER(SEARCH(","&J28,H28))),"City/Postal Code/Country Found in Address"),"")} | AD28: =IF(ISNUMBER(SEARCH("PO",N28)),"PO# Entered in Tax ID Field","") | AE28: {=IFERROR(IF(VLOOKUP(LEFT(M28,MIN(SEARCH({1,2,3,4,5,6,7,8,9,0},M28&{1,2,3,4,5,6,7,8,9,0}))-1),Country_Codes!$N:$N,1,0)>0,"PO Number may be incorrect",""),"")} | AF28: =IF(N28="","",IF(EXACT(L28,LEFT(N28,2)),IF(EXACT(MID(N28,3,1)," "),"Check the Space inbetween County code & VAT",""),"Check the VAT Country Code Format")) | AG28: =IF((ISNUMBER(SEARCH("@",P28)))>0,"",IF(IF(--(ISNUMBER(SEARCH("'",P28)))>0,OR(EXACT(PROPER(P28),P28),EXACT((PROPER(LEFT(P28,FIND("'",P28)-2))&LOWER(MID(P28,FIND("'",P28)-1,1))&PROPER(MID(P28,FIND("'",P28)+0,LEN(P28)-FIND("'",P28)+1))),P28)),"Please check Billing Contact Casing")=TRUE,"","Please check Billing Contact casing")) | AH28: =IF(OR(L28="AS",L28="FM",L28="GU",L28="MH",L28="MP",L28="PW",L28="PR",L28="VI",L28="UM"),"US Territories Check","") | AI28: {=IF(G28="","",_xlfn.IFNA(_xlfn.IFS(L28=VLOOKUP(L28,Country_Codes!$M:$M,1,0)=TRUE,""),"Please check the country code"))} | AJ28: =IF(S28="","",S28&"; ")&IF(T28="","",T28&"; ")&IF(U28="","",U28&"; ")&IF(V28="","",V28&"; ")&IF(AF28="","",AF28&"; ")&IF(AG28="","",AG28&"; ")&IF(AH28="","",AH28&"; ")&IF(Z28="","",Z28&"; ")&IF(AA28="","",AA28&"; ")&IF(AB28="","",AB28&"; ")&IF(AC28="","",AC28&"; ")&IF(AD28="","",AD28&"; ")&IF(AE28="","",AE28&"; ")&IF(AI28="","",AI28&"; ")&IF(W28="","",W28&"; ")&IF(X28="","",X28&"; ")&IF(Y28="","",Y28&"; ") | AM28: =(COUNTA(S28:V28)-COUNTIFS((S28:V28),""))+(COUNTA(AB28)-COUNTIFS((AB28),""))+(COUNTA(AG28)-COUNTIFS((AG28),"")) -> 0 | AN28: =(COUNTA(W28)-COUNTIFS((W28),""))+(COUNTA(Z28)-COUNTIFS((Z28),"")) -> 0 | AO28: =(COUNTA(AA28)-COUNTIFS((AA28),""))+(COUNTA(AC28:AE28)-COUNTIFS((AC28:AE28),""))+(COUNTA(AH28:AI28)-COUNTIFS((AH28:AI28),"")) -> 0 | AP28: =(COUNTA(X28:Y28)-COUNTIFS((X28:Y28),""))+(COUNTA(AF28)-COUNTIFS((AF28),"")) -> 0 | AQ28: =SUM(AM28:AP28) -> 0 | AV28: 45451
A29: 45393 | B29: User 3 | C29: PO Number | D29: 3587 | E29: 4490 | F29: Sample Products, Inc. | G29: ID_Num_3 | H29: 10000 Sample Court, Suite 200 | I29: Mississauga | J29: ON | K29: L5N 5R5 | L29: CA | M29: 5600004 | O29: Smith Frank | R29: =IF(G29=G28,"","Unique Record") | S29: =IF(F29="","",IF(EXACT(F29,(UPPER(F29))),"Account Upper Case","")) | T29: =IF(F29="","",IF(EXACT(F29,(LOWER(F29))),"Account Lower Case","")) | U29: =IF(EXACT(H29,PROPER(H29)),"","Billing Street - casing") | V29: =IF(EXACT(I29,PROPER(I29)),"","City - casing") | W29: =IF(OR(ISNUMBER(SEARCH("East",I29)),ISNUMBER(SEARCH("West",I29)),ISNUMBER(SEARCH("North",I29)),ISNUMBER(SEARCH("South",I29))),"",IF(OR(ISNUMBER(SEARCH("St.",I29)),ISNUMBER(SEARCH("St ",I29))),"Check St in city field",IF(RIGHT(I29,1)=".","Dot found in city field",""))) | X29: {=IF((SUMPRODUCT(--ISNUMBER(SEARCH({"!","@","#","$","%","^","&","~*","(",")","_","+","=","{","}","[","]","|","\",":",";","'","""","<",">",",",".","~?","/","~~","`"}, I29)))>0)=TRUE,"Special Characters Found in City","")} | Y29: {=IF((SUMPRODUCT(--ISNUMBER(SEARCH({"!","@","#","$","%","^","~*","(",")","_","+","=","{","}","[","]","|","\",":",";","'","""","<",">","~?","/","~~","`"},F29)))>0)=TRUE,"Special Characters Found in Account field","")} | Z29: {=IF(SUM(--ISNUMBER(SEARCH({1,2,3,4,5,6,7,8,9,0},MID(H29,(SEARCH(" E ",H29)-1),1))))+SUM(--ISNUMBER(SEARCH({1,2,3,4,5,6,7,8,9,0},MID(H29,(SEARCH(" E ",H29)+3),1))))=2,"",IF(SUM(--ISNUMBER(SEARCH({"Parte E","Apoquindo N"},H29)))>0,"",IF(OR(RIGHT(H29,3)=" NE",RIGHT(H29,3)=" NW",RIGHT(H29,3)=" SW",RIGHT(H29,3)=" SE",RIGHT(H29,2)=" N",RIGHT(H29,2)=" E",RIGHT(H29,2)=" W",RIGHT(H29,2)=" S",LEFT(H29,3)="NE ",LEFT(H29,3)="NW ",LEFT(H29,3)="SW ",LEFT(H29,3)="SE ",LEFT(H29,2)="N ",LEFT(H29,2)="E ",LEFT(H29,2)="W ",LEFT(H29,2)="S "),"Directional Check",IF(SUM(--ISNUMBER(SEARCH({" N "," E "," W "," S "," NE "," NW "," SW "," SE ","N.E","N.W","S.W","S.E","E.","N.","S.","W."},H29)))>0,"Directional Check",IF(SUM(--ISNUMBER(SEARCH({1,2,3,4,5,6,7,8,9,0},MID(H29,(SEARCH("nd ",H29)-1),1))))+SUM(--ISNUMBER(SEARCH({1,2,3,4,5,6,7,8,9,0},MID(H29,(SEARCH("rd ",H29)-1),1)))+SUM(--ISNUMBER(SEARCH({1,2,3,4,5,6,7,8,9,0},MID(H29,(SEARCH("st ",H29)-1),1))))+SUM(--ISNUMBER(SEARCH({1,2,3,4,5,6,7,8,9,0},MID(H29,(SEARCH("th ",H29)-1),1)))))>0,"","")))))} | AA29: =IF(IF(L29="US",IFERROR(VLOOKUP(J29,Country_Codes!$B:$B,1,0)=J29,"US State Code Error"),IF(L29="CA",IFERROR(VLOOKUP(J29,Country_Codes!$E:$E,1,0)=J29,"Canada State Code Error"),IF(L29="BR",IFERROR(VLOOKUP(J29,Country_Codes!$H:$H,1,0)=J29,"Brazil State Code Error"),IF(L29="AU",IFERROR(VLOOKUP(J29,Country_Codes!$K:$K,1,0)=J29,"Australia State Code Error"),""))))=TRUE,"",IF(L29="US",IFERROR(VLOOKUP(J29,Country_Codes!$B:$B,1,0)=J29,"US State Code Error"),IF(L29="CA",IFERROR(VLOOKUP(J29,Country_Codes!$E:$E,1,0)=J29,"Canada State Code Error"),IF(L29="BR",IFERROR(VLOOKUP(J29,Country_Codes!$H:$H,1,0)=J29,"Brazil State Code Error"),IF(L29="AU",IFERROR(VLOOKUP(J29,Country_Codes!$K:$K,1,0)=J29,"Australia State Code Error"),""))))) | AB29: =IF(OR(L29="US",L29="CA",L29="BR",L29="AU"),IF((EXACT(UPPER(J29),J29)),"","Country Code Casing"),IF(EXACT(J29,PROPER(J29)),"","Billing State casing")) | AC29: {=IFERROR(_xlfn.IFS(IF(AND(LEN(I29)=0,ISBLANK(I29)=FALSE),"",ISNUMBER(SEARCH(I29,H29))),"City/Postal Code/Country Found in Address",IF(AND(LEN(K29)=0,ISBLANK(K29)=FALSE),"",ISNUMBER(SEARCH(K29,H29))),"City/Postal Code/Country Found in Address",IF(AND(LEN(L29)=0,ISBLANK(L29)=FALSE),"",ISNUMBER(SEARCH(", "&L29,H29))),"City/Postal Code/Country Found in Address",IF(AND(LEN(J29)=0,ISBLANK(J29)=FALSE),"",ISNUMBER(SEARCH(", "&J29,H29))),"City/Postal Code/Country Found in Address",IF(AND(LEN(L29)=0,ISBLANK(L29)=FALSE),"",ISNUMBER(SEARCH(","&L29,H29))),"City/Postal Code/Country Found in Address",IF(AND(LEN(J29)=0,ISBLANK(J29)=FALSE),"",ISNUMBER(SEARCH(","&J29,H29))),"City/Postal Code/Country Found in Address"),"")} | AD29: =IF(ISNUMBER(SEARCH("PO",N29)),"PO# Entered in Tax ID Field","") | AE29: {=IFERROR(IF(VLOOKUP(LEFT(M29,MIN(SEARCH({1,2,3,4,5,6,7,8,9,0},M29&{1,2,3,4,5,6,7,8,9,0}))-1),Country_Codes!$N:$N,1,0)>0,"PO Number may be incorrect",""),"")} | AF29: =IF(N29="","",IF(EXACT(L29,LEFT(N29,2)),IF(EXACT(MID(N29,3,1)," "),"Check the Space inbetween County code & VAT",""),"Check the VAT Country Code Format")) | AG29: =IF((ISNUMBER(SEARCH("@",P29)))>0,"",IF(IF(--(ISNUMBER(SEARCH("'",P29)))>0,OR(EXACT(PROPER(P29),P29),EXACT((PROPER(LEFT(P29,FIND("'",P29)-2))&LOWER(MID(P29,FIND("'",P29)-1,1))&PROPER(MID(P29,FIND("'",P29)+0,LEN(P29)-FIND("'",P29)+1))),P29)),"Please check Billing Contact Casing")=TRUE,"","Please check Billing Contact casing")) | AH29: =IF(OR(L29="AS",L29="FM",L29="GU",L29="MH",L29="MP",L29="PW",L29="PR",L29="VI",L29="UM"),"US Territories Check","") | AI29: {=IF(G29="","",_xlfn.IFNA(_xlfn.IFS(L29=VLOOKUP(L29,Country_Codes!$M:$M,1,0)=TRUE,""),"Please check the country code"))} | AJ29: =IF(S29="","",S29&"; ")&IF(T29="","",T29&"; ")&IF(U29="","",U29&"; ")&IF(V29="","",V29&"; ")&IF(AF29="","",AF29&"; ")&IF(AG29="","",AG29&"; ")&IF(AH29="","",AH29&"; ")&IF(Z29="","",Z29&"; ")&IF(AA29="","",AA29&"; ")&IF(AB29="","",AB29&"; ")&IF(AC29="","",AC29&"; ")&IF(AD29="","",AD29&"; ")&IF(AE29="","",AE29&"; ")&IF(AI29="","",AI29&"; ")&IF(W29="","",W29&"; ")&IF(X29="","",X29&"; ")&IF(Y29="","",Y29&"; ") | AM29: =(COUNTA(S29:V29)-COUNTIFS((S29:V29),""))+(COUNTA(AB29)-COUNTIFS((AB29),""))+(COUNTA(AG29)-COUNTIFS((AG29),"")) -> 0 | AN29: =(COUNTA(W29)-COUNTIFS((W29),""))+(COUNTA(Z29)-COUNTIFS((Z29),"")) -> 0 | AO29: =(COUNTA(AA29)-COUNTIFS((AA29),""))+(COUNTA(AC29:AE29)-COUNTIFS((AC29:AE29),""))+(COUNTA(AH29:AI29)-COUNTIFS((AH29:AI29),"")) -> 0 | AP29: =(COUNTA(X29:Y29)-COUNTIFS((X29:Y29),""))+(COUNTA(AF29)-COUNTIFS((AF29),"")) -> 0 | AQ29: =SUM(AM29:AP29) -> 0 | AV29: 45452
A30: 45315 | B30: User 1 | C30: Bill To Contact | D30: ID-0005a000 | E30: ID-0006a000 | F30: Sample Flow, inc. | G30: ID_Num_4 | H30: 11111 Sample Place | I30: Charlotte | J30: NC | K30: 28277 | L30: US | O30: Tony Frank | R30: =IF(G30=G29,"","Unique Record") -> Unique Record | S30: =IF(F30="","",IF(EXACT(F30,(UPPER(F30))),"Account Upper Case","")) | T30: =IF(F30="","",IF(EXACT(F30,(LOWER(F30))),"Account Lower Case","")) | U30: =IF(EXACT(H30,PROPER(H30)),"","Billing Street - casing") | V30: =IF(EXACT(I30,PROPER(I30)),"","City - casing") | W30: =IF(OR(ISNUMBER(SEARCH("East",I30)),ISNUMBER(SEARCH("West",I30)),ISNUMBER(SEARCH("North",I30)),ISNUMBER(SEARCH("South",I30))),"",IF(OR(ISNUMBER(SEARCH("St.",I30)),ISNUMBER(SEARCH("St ",I30))),"Check St in city field",IF(RIGHT(I30,1)=".","Dot found in city field",""))) | X30: {=IF((SUMPRODUCT(--ISNUMBER(SEARCH({"!","@","#","$","%","^","&","~*","(",")","_","+","=","{","}","[","]","|","\",":",";","'","""","<",">",",",".","~?","/","~~","`"}, I30)))>0)=TRUE,"Special Characters Found in City","")} | Y30: {=IF((SUMPRODUCT(--ISNUMBER(SEARCH({"!","@","#","$","%","^","~*","(",")","_","+","=","{","}","[","]","|","\",":",";","'","""","<",">","~?","/","~~","`"},F30)))>0)=TRUE,"Special Characters Found in Account field","")} | Z30: {=IF(SUM(--ISNUMBER(SEARCH({1,2,3,4,5,6,7,8,9,0},MID(H30,(SEARCH(" E ",H30)-1),1))))+SUM(--ISNUMBER(SEARCH({1,2,3,4,5,6,7,8,9,0},MID(H30,(SEARCH(" E ",H30)+3),1))))=2,"",IF(SUM(--ISNUMBER(SEARCH({"Parte E","Apoquindo N"},H30)))>0,"",IF(OR(RIGHT(H30,3)=" NE",RIGHT(H30,3)=" NW",RIGHT(H30,3)=" SW",RIGHT(H30,3)=" SE",RIGHT(H30,2)=" N",RIGHT(H30,2)=" E",RIGHT(H30,2)=" W",RIGHT(H30,2)=" S",LEFT(H30,3)="NE ",LEFT(H30,3)="NW ",LEFT(H30,3)="SW ",LEFT(H30,3)="SE ",LEFT(H30,2)="N ",LEFT(H30,2)="E ",LEFT(H30,2)="W ",LEFT(H30,2)="S "),"Directional Check",IF(SUM(--ISNUMBER(SEARCH({" N "," E "," W "," S "," NE "," NW "," SW "," SE ","N.E","N.W","S.W","S.E","E.","N.","S.","W."},H30)))>0,"Directional Check",IF(SUM(--ISNUMBER(SEARCH({1,2,3,4,5,6,7,8,9,0},MID(H30,(SEARCH("nd ",H30)-1),1))))+SUM(--ISNUMBER(SEARCH({1,2,3,4,5,6,7,8,9,0},MID(H30,(SEARCH("rd ",H30)-1),1)))+SUM(--ISNUMBER(SEARCH({1,2,3,4,5,6,7,8,9,0},MID(H30,(SEARCH("st ",H30)-1),1))))+SUM(--ISNUMBER(SEARCH({1,2,3,4,5,6,7,8,9,0},MID(H30,(SEARCH("th ",H30)-1),1)))))>0,"","")))))} | AA30: =IF(IF(L30="US",IFERROR(VLOOKUP(J30,Country_Codes!$B:$B,1,0)=J30,"US State Code Error"),IF(L30="CA",IFERROR(VLOOKUP(J30,Country_Codes!$E:$E,1,0)=J30,"Canada State Code Error"),IF(L30="BR",IFERROR(VLOOKUP(J30,Country_Codes!$H:$H,1,0)=J30,"Brazil State Code Error"),IF(L30="AU",IFERROR(VLOOKUP(J30,Country_Codes!$K:$K,1,0)=J30,"Australia State Code Error"),""))))=TRUE,"",IF(L30="US",IFERROR(VLOOKUP(J30,Country_Codes!$B:$B,1,0)=J30,"US State Code Error"),IF(L30="CA",IFERROR(VLOOKUP(J30,Country_Codes!$E:$E,1,0)=J30,"Canada State Code Error"),IF(L30="BR",IFERROR(VLOOKUP(J30,Country_Codes!$H:$H,1,0)=J30,"Brazil State Code Error"),IF(L30="AU",IFERROR(VLOOKUP(J30,Country_Codes!$K:$K,1,0)=J30,"Australia State Code Error"),""))))) | AB30: =IF(OR(L30="US",L30="CA",L30="BR",L30="AU"),IF((EXACT(UPPER(J30),J30)),"","Country Code Casing"),IF(EXACT(J30,PROPER(J30)),"","Billing State casing")) | AC30: {=IFERROR(_xlfn.IFS(IF(AND(LEN(I30)=0,ISBLANK(I30)=FALSE),"",ISNUMBER(SEARCH(I30,H30))),"City/Postal Code/Country Found in Address",IF(AND(LEN(K30)=0,ISBLANK(K30)=FALSE),"",ISNUMBER(SEARCH(K30,H30))),"City/Postal Code/Country Found in Address",IF(AND(LEN(L30)=0,ISBLANK(L30)=FALSE),"",ISNUMBER(SEARCH(", "&L30,H30))),"City/Postal Code/Country Found in Address",IF(AND(LEN(J30)=0,ISBLANK(J30)=FALSE),"",ISNUMBER(SEARCH(", "&J30,H30))),"City/Postal Code/Country Found in Address",IF(AND(LEN(L30)=0,ISBLANK(L30)=FALSE),"",ISNUMBER(SEARCH(","&L30,H30))),"City/Postal Code/Country Found in Address",IF(AND(LEN(J30)=0,ISBLANK(J30)=FALSE),"",ISNUMBER(SEARCH(","&J30,H30))),"City/Postal Code/Country Found in Address"),"")} | AD30: =IF(ISNUMBER(SEARCH("PO",N30)),"PO# Entered in Tax ID Field","") | AE30: {=IFERROR(IF(VLOOKUP(LEFT(M30,MIN(SEARCH({1,2,3,4,5,6,7,8,9,0},M30&{1,2,3,4,5,6,7,8,9,0}))-1),Country_Codes!$N:$N,1,0)>0,"PO Number may be incorrect",""),"")} | AF30: =IF(N30="","",IF(EXACT(L30,LEFT(N30,2)),IF(EXACT(MID(N30,3,1)," "),"Check the Space inbetween County code & VAT",""),"Check the VAT Country Code Format")) | AG30: =IF((ISNUMBER(SEARCH("@",P30)))>0,"",IF(IF(--(ISNUMBER(SEARCH("'",P30)))>0,OR(EXACT(PROPER(P30),P30),EXACT((PROPER(LEFT(P30,FIND("'",P30)-2))&LOWER(MID(P30,FIND("'",P30)-1,1))&PROPER(MID(P30,FIND("'",P30)+0,LEN(P30)-FIND("'",P30)+1))),P30)),"Please check Billing Contact Casing")=TRUE,"","Please check Billing Contact casing")) | AH30: =IF(OR(L30="AS",L30="FM",L30="GU",L30="MH",L30="MP",L30="PW",L30="PR",L30="VI",L30="UM"),"US Territories Check","") | AI30: {=IF(G30="","",_xlfn.IFNA(_xlfn.IFS(L30=VLOOKUP(L30,Country_Codes!$M:$M,1,0)=TRUE,""),"Please check the country code"))} | AJ30: =IF(S30="","",S30&"; ")&IF(T30="","",T30&"; ")&IF(U30="","",U30&"; ")&IF(V30="","",V30&"; ")&IF(AF30="","",AF30&"; ")&IF(AG30="","",AG30&"; ")&IF(AH30="","",AH30&"; ")&IF(Z30="","",Z30&"; ")&IF(AA30="","",AA30&"; ")&IF(AB30="","",AB30&"; ")&IF(AC30="","",AC30&"; ")&IF(AD30="","",AD30&"; ")&IF(AE30="","",AE30&"; ")&IF(AI30="","",AI30&"; ")&IF(W30="","",W30&"; ")&IF(X30="","",X30&"; ")&IF(Y30="","",Y30&"; ") | AM30: =(COUNTA(S30:V30)-COUNTIFS((S30:V30),""))+(COUNTA(AB30)-COUNTIFS((AB30),""))+(COUNTA(AG30)-COUNTIFS((AG30),"")) -> 0 | AN30: =(COUNTA(W30)-COUNTIFS((W30),""))+(COUNTA(Z30)-COUNTIFS((Z30),"")) -> 0 | AO30: =(COUNTA(AA30)-COUNTIFS((AA30),""))+(COUNTA(AC30:AE30)-COUNTIFS((AC30:AE30),""))+(COUNTA(AH30:AI30)-COUNTIFS((AH30:AI30),"")) -> 0 | AP30: =(COUNTA(X30:Y30)-COUNTIFS((X30:Y30),""))+(COUNTA(AF30)-COUNTIFS((AF30),"")) -> 0 | AQ30: =SUM(AM30:AP30) -> 0 | AV30: 45454
A31: 45622 | B31: User 1 | C31: Bill To Contact | D31: ID-0006a000 | F31: Sample Ltd | G31: ID_Num_5 | H31: Main Street | I31: London | K31: EC2V 7EE | L31: GB | M31: PO 030 | P31: Smith Frank | R31: =IF(G31=G30,"","Unique Record") -> Unique Record | S31: =IF(F31="","",IF(EXACT(F31,(UPPER(F31))),"Account Upper Case","")) | T31: =IF(F31="","",IF(EXACT(F31,(LOWER(F31))),"Account Lower Case","")) | U31: =IF(EXACT(H31,PROPER(H31)),"","Billing Street - casing") | V31: =IF(EXACT(I31,PROPER(I31)),"","City - casing") | W31: =IF(OR(ISNUMBER(SEARCH("East",I31)),ISNUMBER(SEARCH("West",I31)),ISNUMBER(SEARCH("North",I31)),ISNUMBER(SEARCH("South",I31))),"",IF(OR(ISNUMBER(SEARCH("St.",I31)),ISNUMBER(SEARCH("St ",I31))),"Check St in city field",IF(RIGHT(I31,1)=".","Dot found in city field",""))) | X31: {=IF((SUMPRODUCT(--ISNUMBER(SEARCH({"!","@","#","$","%","^","&","~*","(",")","_","+","=","{","}","[","]","|","\",":",";","'","""","<",">",",",".","~?","/","~~","`"}, I31)))>0)=TRUE,"Special Characters Found in City","")} | Y31: {=IF((SUMPRODUCT(--ISNUMBER(SEARCH({"!","@","#","$","%","^","~*","(",")","_","+","=","{","}","[","]","|","\",":",";","'","""","<",">","~?","/","~~","`"},F31)))>0)=TRUE,"Special Characters Found in Account field","")} | Z31: {=IF(SUM(--ISNUMBER(SEARCH({1,2,3,4,5,6,7,8,9,0},MID(H31,(SEARCH(" E ",H31)-1),1))))+SUM(--ISNUMBER(SEARCH({1,2,3,4,5,6,7,8,9,0},MID(H31,(SEARCH(" E ",H31)+3),1))))=2,"",IF(SUM(--ISNUMBER(SEARCH({"Parte E","Apoquindo N"},H31)))>0,"",IF(OR(RIGHT(H31,3)=" NE",RIGHT(H31,3)=" NW",RIGHT(H31,3)=" SW",RIGHT(H31,3)=" SE",RIGHT(H31,2)=" N",RIGHT(H31,2)=" E",RIGHT(H31,2)=" W",RIGHT(H31,2)=" S",LEFT(H31,3)="NE ",LEFT(H31,3)="NW ",LEFT(H31,3)="SW ",LEFT(H31,3)="SE ",LEFT(H31,2)="N ",LEFT(H31,2)="E ",LEFT(H31,2)="W ",LEFT(H31,2)="S "),"Directional Check",IF(SUM(--ISNUMBER(SEARCH({" N "," E "," W "," S "," NE "," NW "," SW "," SE ","N.E","N.W","S.W","S.E","E.","N.","S.","W."},H31)))>0,"Directional Check",IF(SUM(--ISNUMBER(SEARCH({1,2,3,4,5,6,7,8,9,0},MID(H31,(SEARCH("nd ",H31)-1),1))))+SUM(--ISNUMBER(SEARCH({1,2,3,4,5,6,7,8,9,0},MID(H31,(SEARCH("rd ",H31)-1),1)))+SUM(--ISNUMBER(SEARCH({1,2,3,4,5,6,7,8,9,0},MID(H31,(SEARCH("st ",H31)-1),1))))+SUM(--ISNUMBER(SEARCH({1,2,3,4,5,6,7,8,9,0},MID(H31,(SEARCH("th ",H31)-1),1)))))>0,"","")))))} | AA31: =IF(IF(L31="US",IFERROR(VLOOKUP(J31,Country_Codes!$B:$B,1,0)=J31,"US State Code Error"),IF(L31="CA",IFERROR(VLOOKUP(J31,Country_Codes!$E:$E,1,0)=J31,"Canada State Code Error"),IF(L31="BR",IFERROR(VLOOKUP(J31,Country_Codes!$H:$H,1,0)=J31,"Brazil State Code Error"),IF(L31="AU",IFERROR(VLOOKUP(J31,Country_Codes!$K:$K,1,0)=J31,"Australia State Code Error"),""))))=TRUE,"",IF(L31="US",IFERROR(VLOOKUP(J31,Country_Codes!$B:$B,1,0)=J31,"US State Code Error"),IF(L31="CA",IFERROR(VLOOKUP(J31,Country_Codes!$E:$E,1,0)=J31,"Canada State Code Error"),IF(L31="BR",IFERROR(VLOOKUP(J31,Country_Codes!$H:$H,1,0)=J31,"Brazil State Code Error"),IF(L31="AU",IFERROR(VLOOKUP(J31,Country_Codes!$K:$K,1,0)=J31,"Australia State Code Error"),""))))) | AB31: =IF(OR(L31="US",L31="CA",L31="BR",L31="AU"),IF((EXACT(UPPER(J31),J31)),"","Country Code Casing"),IF(EXACT(J31,PROPER(J31)),"","Billing State casing")) | AC31: {=IFERROR(_xlfn.IFS(IF(AND(LEN(I31)=0,ISBLANK(I31)=FALSE),"",ISNUMBER(SEARCH(I31,H31))),"City/Postal Code/Country Found in Address",IF(AND(LEN(K31)=0,ISBLANK(K31)=FALSE),"",ISNUMBER(SEARCH(K31,H31))),"City/Postal Code/Country Found in Address",IF(AND(LEN(L31)=0,ISBLANK(L31)=FALSE),"",ISNUMBER(SEARCH(", "&L31,H31))),"City/Postal Code/Country Found in Address",IF(AND(LEN(J31)=0,ISBLANK(J31)=FALSE),"",ISNUMBER(SEARCH(", "&J31,H31))),"City/Postal Code/Country Found in Address",IF(AND(LEN(L31)=0,ISBLANK(L31)=FALSE),"",ISNUMBER(SEARCH(","&L31,H31))),"City/Postal Code/Country Found in Address",IF(AND(LEN(J31)=0,ISBLANK(J31)=FALSE),"",ISNUMBER(SEARCH(","&J31,H31))),"City/Postal Code/Country Found in Address"),"")} | AD31: =IF(ISNUMBER(SEARCH("PO",N31)),"PO# Entered in Tax ID Field","") | AE31: {=IFERROR(IF(VLOOKUP(LEFT(M31,MIN(SEARCH({1,2,3,4,5,6,7,8,9,0},M31&{1,2,3,4,5,6,7,8,9,0}))-1),Country_Codes!$N:$N,1,0)>0,"PO Number may be incorrect",""),"")} | AF31: =IF(N31="","",IF(EXACT(L31,LEFT(N31,2)),IF(EXACT(MID(N31,3,1)," "),"Check the Space inbetween County code & VAT",""),"Check the VAT Country Code Format")) | AG31: =IF((ISNUMBER(SEARCH("@",P31)))>0,"",IF(IF(--(ISNUMBER(SEARCH("'",P31)))>0,OR(EXACT(PROPER(P31),P31),EXACT((PROPER(LEFT(P31,FIND("'",P31)-2))&LOWER(MID(P31,FIND("'",P31)-1,1))&PROPER(MID(P31,FIND("'",P31)+0,LEN(P31)-FIND("'",P31)+1))),P31)),"Please check Billing Contact Casing")=TRUE,"","Please check Billing Contact casing")) | AH31: =IF(OR(L31="AS",L31="FM",L31="GU",L31="MH",L31="MP",L31="PW",L31="PR",L31="VI",L31="UM"),"US Territories Check","") | AI31: {=IF(G31="","",_xlfn.IFNA(_xlfn.IFS(L31=VLOOKUP(L31,Country_Codes!$M:$M,1,0)=TRUE,""),"Please check the country code"))} | AJ31: =IF(S31="","",S31&"; ")&IF(T31="","",T31&"; ")&IF(U31="","",U31&"; ")&IF(V31="","",V31&"; ")&IF(AF31="","",AF31&"; ")&IF(AG31="","",AG31&"; ")&IF(AH31="","",AH31&"; ")&IF(Z31="","",Z31&"; ")&IF(AA31="","",AA31&"; ")&IF(AB31="","",AB31&"; ")&IF(AC31="","",AC31&"; ")&IF(AD31="","",AD31&"; ")&IF(AE31="","",AE31&"; ")&IF(AI31="","",AI31&"; ")&IF(W31="","",W31&"; ")&IF(X31="","",X31&"; ")&IF(Y31="","",Y31&"; ") | AM31: =(COUNTA(S31:V31)-COUNTIFS((S31:V31),""))+(COUNTA(AB31)-COUNTIFS((AB31),""))+(COUNTA(AG31)-COUNTIFS((AG31),"")) -> 0 | AN31: =(COUNTA(W31)-COUNTIFS((W31),""))+(COUNTA(Z31)-COUNTIFS((Z31),"")) -> 0 | AO31: =(COUNTA(AA31)-COUNTIFS((AA31),""))+(COUNTA(AC31:AE31)-COUNTIFS((AC31:AE31),""))+(COUNTA(AH31:AI31)-COUNTIFS((AH31:AI31),"")) -> 0 | AP31: =(COUNTA(X31:Y31)-COUNTIFS((X31:Y31),""))+(COUNTA(AF31)-COUNTIFS((AF31),"")) -> 0 | AQ31: =SUM(AM31:AP31) -> 0 | AV31: 45456
A32: 45622 | B32: User 1 | C32: Billing Contact Name | E32: Smith Francis | F32: Sample Ltd | G32: ID_Num_5 | H32: Main Street | I32: London | K32: EC2V 7EE | L32: GB | M32: PO 030 | P32: Smith Frank | R32: =IF(G32=G31,"","Unique Record") | S32: =IF(F32="","",IF(EXACT(F32,(UPPER(F32))),"Account Upper Case","")) | T32: =IF(F32="","",IF(EXACT(F32,(LOWER(F32))),"Account Lower Case","")) | U32: =IF(EXACT(H32,PROPER(H32)),"","Billing Street - casing") | V32: =IF(EXACT(I32,PROPER(I32)),"","City - casing") | W32: =IF(OR(ISNUMBER(SEARCH("East",I32)),ISNUMBER(SEARCH("West",I32)),ISNUMBER(SEARCH("North",I32)),ISNUMBER(SEARCH("South",I32))),"",IF(OR(ISNUMBER(SEARCH("St.",I32)),ISNUMBER(SEARCH("St ",I32))),"Check St in city field",IF(RIGHT(I32,1)=".","Dot found in city field",""))) | X32: {=IF((SUMPRODUCT(--ISNUMBER(SEARCH({"!","@","#","$","%","^","&","~*","(",")","_","+","=","{","}","[","]","|","\",":",";","'","""","<",">",",",".","~?","/","~~","`"}, I32)))>0)=TRUE,"Special Characters Found in City","")} | Y32: {=IF((SUMPRODUCT(--ISNUMBER(SEARCH({"!","@","#","$","%","^","~*","(",")","_","+","=","{","}","[","]","|","\",":",";","'","""","<",">","~?","/","~~","`"},F32)))>0)=TRUE,"Special Characters Found in Account field","")} | Z32: {=IF(SUM(--ISNUMBER(SEARCH({1,2,3,4,5,6,7,8,9,0},MID(H32,(SEARCH(" E ",H32)-1),1))))+SUM(--ISNUMBER(SEARCH({1,2,3,4,5,6,7,8,9,0},MID(H32,(SEARCH(" E ",H32)+3),1))))=2,"",IF(SUM(--ISNUMBER(SEARCH({"Parte E","Apoquindo N"},H32)))>0,"",IF(OR(RIGHT(H32,3)=" NE",RIGHT(H32,3)=" NW",RIGHT(H32,3)=" SW",RIGHT(H32,3)=" SE",RIGHT(H32,2)=" N",RIGHT(H32,2)=" E",RIGHT(H32,2)=" W",RIGHT(H32,2)=" S",LEFT(H32,3)="NE ",LEFT(H32,3)="NW ",LEFT(H32,3)="SW ",LEFT(H32,3)="SE ",LEFT(H32,2)="N ",LEFT(H32,2)="E ",LEFT(H32,2)="W ",LEFT(H32,2)="S "),"Directional Check",IF(SUM(--ISNUMBER(SEARCH({" N "," E "," W "," S "," NE "," NW "," SW "," SE ","N.E","N.W","S.W","S.E","E.","N.","S.","W."},H32)))>0,"Directional Check",IF(SUM(--ISNUMBER(SEARCH({1,2,3,4,5,6,7,8,9,0},MID(H32,(SEARCH("nd ",H32)-1),1))))+SUM(--ISNUMBER(SEARCH({1,2,3,4,5,6,7,8,9,0},MID(H32,(SEARCH("rd ",H32)-1),1)))+SUM(--ISNUMBER(SEARCH({1,2,3,4,5,6,7,8,9,0},MID(H32,(SEARCH("st ",H32)-1),1))))+SUM(--ISNUMBER(SEARCH({1,2,3,4,5,6,7,8,9,0},MID(H32,(SEARCH("th ",H32)-1),1)))))>0,"","")))))} | AA32: =IF(IF(L32="US",IFERROR(VLOOKUP(J32,Country_Codes!$B:$B,1,0)=J32,"US State Code Error"),IF(L32="CA",IFERROR(VLOOKUP(J32,Country_Codes!$E:$E,1,0)=J32,"Canada State Code Error"),IF(L32="BR",IFERROR(VLOOKUP(J32,Country_Codes!$H:$H,1,0)=J32,"Brazil State Code Error"),IF(L32="AU",IFERROR(VLOOKUP(J32,Country_Codes!$K:$K,1,0)=J32,"Australia State Code Error"),""))))=TRUE,"",IF(L32="US",IFERROR(VLOOKUP(J32,Country_Codes!$B:$B,1,0)=J32,"US State Code Error"),IF(L32="CA",IFERROR(VLOOKUP(J32,Country_Codes!$E:$E,1,0)=J32,"Canada State Code Error"),IF(L32="BR",IFERROR(VLOOKUP(J32,Country_Codes!$H:$H,1,0)=J32,"Brazil State Code Error"),IF(L32="AU",IFERROR(VLOOKUP(J32,Country_Codes!$K:$K,1,0)=J32,"Australia State Code Error"),""))))) | AB32: =IF(OR(L32="US",L32="CA",L32="BR",L32="AU"),IF((EXACT(UPPER(J32),J32)),"","Country Code Casing"),IF(EXACT(J32,PROPER(J32)),"","Billing State casing")) | AC32: {=IFERROR(_xlfn.IFS(IF(AND(LEN(I32)=0,ISBLANK(I32)=FALSE),"",ISNUMBER(SEARCH(I32,H32))),"City/Postal Code/Country Found in Address",IF(AND(LEN(K32)=0,ISBLANK(K32)=FALSE),"",ISNUMBER(SEARCH(K32,H32))),"City/Postal Code/Country Found in Address",IF(AND(LEN(L32)=0,ISBLANK(L32)=FALSE),"",ISNUMBER(SEARCH(", "&L32,H32))),"City/Postal Code/Country Found in Address",IF(AND(LEN(J32)=0,ISBLANK(J32)=FALSE),"",ISNUMBER(SEARCH(", "&J32,H32))),"City/Postal Code/Country Found in Address",IF(AND(LEN(L32)=0,ISBLANK(L32)=FALSE),"",ISNUMBER(SEARCH(","&L32,H32))),"City/Postal Code/Country Found in Address",IF(AND(LEN(J32)=0,ISBLANK(J32)=FALSE),"",ISNUMBER(SEARCH(","&J32,H32))),"City/Postal Code/Country Found in Address"),"")} | AD32: =IF(ISNUMBER(SEARCH("PO",N32)),"PO# Entered in Tax ID Field","") | AE32: {=IFERROR(IF(VLOOKUP(LEFT(M32,MIN(SEARCH({1,2,3,4,5,6,7,8,9,0},M32&{1,2,3,4,5,6,7,8,9,0}))-1),Country_Codes!$N:$N,1,0)>0,"PO Number may be incorrect",""),"")} | AF32: =IF(N32="","",IF(EXACT(L32,LEFT(N32,2)),IF(EXACT(MID(N32,3,1)," "),"Check the Space inbetween County code & VAT",""),"Check the VAT Country Code Format")) | AG32: =IF((ISNUMBER(SEARCH("@",P32)))>0,"",IF(IF(--(ISNUMBER(SEARCH("'",P32)))>0,OR(EXACT(PROPER(P32),P32),EXACT((PROPER(LEFT(P32,FIND("'",P32)-2))&LOWER(MID(P32,FIND("'",P32)-1,1))&PROPER(MID(P32,FIND("'",P32)+0,LEN(P32)-FIND("'",P32)+1))),P32)),"Please check Billing Contact Casing")=TRUE,"","Please check Billing Contact casing")) | AH32: =IF(OR(L32="AS",L32="FM",L32="GU",L32="MH",L32="MP",L32="PW",L32="PR",L32="VI",L32="UM"),"US Territories Check","") | AI32: {=IF(G32="","",_xlfn.IFNA(_xlfn.IFS(L32=VLOOKUP(L32,Country_Codes!$M:$M,1,0)=TRUE,""),"Please check the country code"))} | AJ32: =IF(S32="","",S32&"; ")&IF(T32="","",T32&"; ")&IF(U32="","",U32&"; ")&IF(V32="","",V32&"; ")&IF(AF32="","",AF32&"; ")&IF(AG32="","",AG32&"; ")&IF(AH32="","",AH32&"; ")&IF(Z32="","",Z32&"; ")&IF(AA32="","",AA32&"; ")&IF(AB32="","",AB32&"; ")&IF(AC32="","",AC32&"; ")&IF(AD32="","",AD32&"; ")&IF(AE32="","",AE32&"; ")&IF(AI32="","",AI32&"; ")&IF(W32="","",W32&"; ")&IF(X32="","",X32&"; ")&IF(Y32="","",Y32&"; ") | AM32: =(COUNTA(S32:V32)-COUNTIFS((S32:V32),""))+(COUNTA(AB32)-COUNTIFS((AB32),""))+(COUNTA(AG32)-COUNTIFS((AG32),"")) -> 0 | AN32: =(COUNTA(W32)-COUNTIFS((W32),""))+(COUNTA(Z32)-COUNTIFS((Z32),"")) -> 0 | AO32: =(COUNTA(AA32)-COUNTIFS((AA32),""))+(COUNTA(AC32:AE32)-COUNTIFS((AC32:AE32),""))+(COUNTA(AH32:AI32)-COUNTIFS((AH32:AI32),"")) -> 0 | AP32: =(COUNTA(X32:Y32)-COUNTIFS((X32:Y32),""))+(COUNTA(AF32)-COUNTIFS((AF32),"")) -> 0 | AQ32: =SUM(AM32:AP32) -> 0 | AV32: 45457
A33: 45546 | B33: User 2 | C33: Bill To Contact | D33: ID-0006a000 | F33: Sample Technologies, Inc. | G33: ID_Num_6 | H33: 10000 Sample Way | I33: Redwood City | J33: CA | K33: 94063 | L33: US | P33: Accounts Payable | R33: =IF(G33=G32,"","Unique Record") -> Unique Record | S33: =IF(F33="","",IF(EXACT(F33,(UPPER(F33))),"Account Upper Case","")) | T33: =IF(F33="","",IF(EXACT(F33,(LOWER(F33))),"Account Lower Case","")) | U33: =IF(EXACT(H33,PROPER(H33)),"","Billing Street - casing") | V33: =IF(EXACT(I33,PROPER(I33)),"","City - casing") | W33: =IF(OR(ISNUMBER(SEARCH("East",I33)),ISNUMBER(SEARCH("West",I33)),ISNUMBER(SEARCH("North",I33)),ISNUMBER(SEARCH("South",I33))),"",IF(OR(ISNUMBER(SEARCH("St.",I33)),ISNUMBER(SEARCH("St ",I33))),"Check St in city field",IF(RIGHT(I33,1)=".","Dot found in city field",""))) | X33: {=IF((SUMPRODUCT(--ISNUMBER(SEARCH({"!","@","#","$","%","^","&","~*","(",")","_","+","=","{","}","[","]","|","\",":",";","'","""","<",">",",",".","~?","/","~~","`"}, I33)))>0)=TRUE,"Special Characters Found in City","")} | Y33: {=IF((SUMPRODUCT(--ISNUMBER(SEARCH({"!","@","#","$","%","^","~*","(",")","_","+","=","{","}","[","]","|","\",":",";","'","""","<",">","~?","/","~~","`"},F33)))>0)=TRUE,"Special Characters Found in Account field","")} | Z33: {=IF(SUM(--ISNUMBER(SEARCH({1,2,3,4,5,6,7,8,9,0},MID(H33,(SEARCH(" E ",H33)-1),1))))+SUM(--ISNUMBER(SEARCH({1,2,3,4,5,6,7,8,9,0},MID(H33,(SEARCH(" E ",H33)+3),1))))=2,"",IF(SUM(--ISNUMBER(SEARCH({"Parte E","Apoquindo N"},H33)))>0,"",IF(OR(RIGHT(H33,3)=" NE",RIGHT(H33,3)=" NW",RIGHT(H33,3)=" SW",RIGHT(H33,3)=" SE",RIGHT(H33,2)=" N",RIGHT(H33,2)=" E",RIGHT(H33,2)=" W",RIGHT(H33,2)=" S",LEFT(H33,3)="NE ",LEFT(H33,3)="NW ",LEFT(H33,3)="SW ",LEFT(H33,3)="SE ",LEFT(H33,2)="N ",LEFT(H33,2)="E ",LEFT(H33,2)="W ",LEFT(H33,2)="S "),"Directional Check",IF(SUM(--ISNUMBER(SEARCH({" N "," E "," W "," S "," NE "," NW "," SW "," SE ","N.E","N.W","S.W","S.E","E.","N.","S.","W."},H33)))>0,"Directional Check",IF(SUM(--ISNUMBER(SEARCH({1,2,3,4,5,6,7,8,9,0},MID(H33,(SEARCH("nd ",H33)-1),1))))+SUM(--ISNUMBER(SEARCH({1,2,3,4,5,6,7,8,9,0},MID(H33,(SEARCH("rd ",H33)-1),1)))+SUM(--ISNUMBER(SEARCH({1,2,3,4,5,6,7,8,9,0},MID(H33,(SEARCH("st ",H33)-1),1))))+SUM(--ISNUMBER(SEARCH({1,2,3,4,5,6,7,8,9,0},MID(H33,(SEARCH("th ",H33)-1),1)))))>0,"","")))))} | AA33: =IF(IF(L33="US",IFERROR(VLOOKUP(J33,Country_Codes!$B:$B,1,0)=J33,"US State Code Error"),IF(L33="CA",IFERROR(VLOOKUP(J33,Country_Codes!$E:$E,1,0)=J33,"Canada State Code Error"),IF(L33="BR",IFERROR(VLOOKUP(J33,Country_Codes!$H:$H,1,0)=J33,"Brazil State Code Error"),IF(L33="AU",IFERROR(VLOOKUP(J33,Country_Codes!$K:$K,1,0)=J33,"Australia State Code Error"),""))))=TRUE,"",IF(L33="US",IFERROR(VLOOKUP(J33,Country_Codes!$B:$B,1,0)=J33,"US State Code Error"),IF(L33="CA",IFERROR(VLOOKUP(J33,Country_Codes!$E:$E,1,0)=J33,"Canada State Code Error"),IF(L33="BR",IFERROR(VLOOKUP(J33,Country_Codes!$H:$H,1,0)=J33,"Brazil State Code Error"),IF(L33="AU",IFERROR(VLOOKUP(J33,Country_Codes!$K:$K,1,0)=J33,"Australia State Code Error"),""))))) | AB33: =IF(OR(L33="US",L33="CA",L33="BR",L33="AU"),IF((EXACT(UPPER(J33),J33)),"","Country Code Casing"),IF(EXACT(J33,PROPER(J33)),"","Billing State casing")) | AC33: {=IFERROR(_xlfn.IFS(IF(AND(LEN(I33)=0,ISBLANK(I33)=FALSE),"",ISNUMBER(SEARCH(I33,H33))),"City/Postal Code/Country Found in Address",IF(AND(LEN(K33)=0,ISBLANK(K33)=FALSE),"",ISNUMBER(SEARCH(K33,H33))),"City/Postal Code/Country Found in Address",IF(AND(LEN(L33)=0,ISBLANK(L33)=FALSE),"",ISNUMBER(SEARCH(", "&L33,H33))),"City/Postal Code/Country Found in Address",IF(AND(LEN(J33)=0,ISBLANK(J33)=FALSE),"",ISNUMBER(SEARCH(", "&J33,H33))),"City/Postal Code/Country Found in Address",IF(AND(LEN(L33)=0,ISBLANK(L33)=FALSE),"",ISNUMBER(SEARCH(","&L33,H33))),"City/Postal Code/Country Found in Address",IF(AND(LEN(J33)=0,ISBLANK(J33)=FALSE),"",ISNUMBER(SEARCH(","&J33,H33))),"City/Postal Code/Country Found in Address"),"")} | AD33: =IF(ISNUMBER(SEARCH("PO",N33)),"PO# Entered in Tax ID Field","") | AE33: {=IFERROR(IF(VLOOKUP(LEFT(M33,MIN(SEARCH({1,2,3,4,5,6,7,8,9,0},M33&{1,2,3,4,5,6,7,8,9,0}))-1),Country_Codes!$N:$N,1,0)>0,"PO Number may be incorrect",""),"")} | AF33: =IF(N33="","",IF(EXACT(L33,LEFT(N33,2)),IF(EXACT(MID(N33,3,1)," "),"Check the Space inbetween County code & VAT",""),"Check the VAT Country Code Format")) | AG33: =IF((ISNUMBER(SEARCH("@",P33)))>0,"",IF(IF(--(ISNUMBER(SEARCH("'",P33)))>0,OR(EXACT(PROPER(P33),P33),EXACT((PROPER(LEFT(P33,FIND("'",P33)-2))&LOWER(MID(P33,FIND("'",P33)-1,1))&PROPER(MID(P33,FIND("'",P33)+0,LEN(P33)-FIND("'",P33)+1))),P33)),"Please check Billing Contact Casing")=TRUE,"","Please check Billing Contact casing")) | AH33: =IF(OR(L33="AS",L33="FM",L33="GU",L33="MH",L33="MP",L33="PW",L33="PR",L33="VI",L33="UM"),"US Territories Check","") | AI33: {=IF(G33="","",_xlfn.IFNA(_xlfn.IFS(L33=VLOOKUP(L33,Country_Codes!$M:$M,1,0)=TRUE,""),"Please check the country code"))} | AJ33: =IF(S33="","",S33&"; ")&IF(T33="","",T33&"; ")&IF(U33="","",U33&"; ")&IF(V33="","",V33&"; ")&IF(AF33="","",AF33&"; ")&IF(AG33="","",AG33&"; ")&IF(AH33="","",AH33&"; ")&IF(Z33="","",Z33&"; ")&IF(AA33="","",AA33&"; ")&IF(AB33="","",AB33&"; ")&IF(AC33="","",AC33&"; ")&IF(AD33="","",AD33&"; ")&IF(AE33="","",AE33&"; ")&IF(AI33="","",AI33&"; ")&IF(W33="","",W33&"; ")&IF(X33="","",X33&"; ")&IF(Y33="","",Y33&"; ") | AM33: =(COUNTA(S33:V33)-COUNTIFS((S33:V33),""))+(COUNTA(AB33)-COUNTIFS((AB33),""))+(COUNTA(AG33)-COUNTIFS((AG33),"")) -> 0 | AN33: =(COUNTA(W33)-COUNTIFS((W33),""))+(COUNTA(Z33)-COUNTIFS((Z33),"")) -> 0 | AO33: =(COUNTA(AA33)-COUNTIFS((AA33),""))+(COUNTA(AC33:AE33)-COUNTIFS((AC33:AE33),""))+(COUNTA(AH33:AI33)-COUNTIFS((AH33:AI33),"")) -> 0 | AP33: =(COUNTA(X33:Y33)-COUNTIFS((X33:Y33),""))+(COUNTA(AF33)-COUNTIFS((AF33),"")) -> 0 | AQ33: =SUM(AM33:AP33) -> 0 | AV33: 45460
A34: 45546 | B34: User 2 | C34: Billing Contact Name | E34: Accounts Payable | F34: Sample Technologies, Inc. | G34: ID_Num_6 | H34: 10000 Sample Way | I34: Redwood City | J34: CA | K34: 94063 | L34: US | P34: Accounts Payable | R34: =IF(G34=G33,"","Unique Record") | S34: =IF(F34="","",IF(EXACT(F34,(UPPER(F34))),"Account Upper Case","")) | T34: =IF(F34="","",IF(EXACT(F34,(LOWER(F34))),"Account Lower Case","")) | U34: =IF(EXACT(H34,PROPER(H34)),"","Billing Street - casing") | V34: =IF(EXACT(I34,PROPER(I34)),"","City - casing") | W34: =IF(OR(ISNUMBER(SEARCH("East",I34)),ISNUMBER(SEARCH("West",I34)),ISNUMBER(SEARCH("North",I34)),ISNUMBER(SEARCH("South",I34))),"",IF(OR(ISNUMBER(SEARCH("St.",I34)),ISNUMBER(SEARCH("St ",I34))),"Check St in city field",IF(RIGHT(I34,1)=".","Dot found in city field",""))) | X34: {=IF((SUMPRODUCT(--ISNUMBER(SEARCH({"!","@","#","$","%","^","&","~*","(",")","_","+","=","{","}","[","]","|","\",":",";","'","""","<",">",",",".","~?","/","~~","`"}, I34)))>0)=TRUE,"Special Characters Found in City","")} | Y34: {=IF((SUMPRODUCT(--ISNUMBER(SEARCH({"!","@","#","$","%","^","~*","(",")","_","+","=","{","}","[","]","|","\",":",";","'","""","<",">","~?","/","~~","`"},F34)))>0)=TRUE,"Special Characters Found in Account field","")} | Z34: {=IF(SUM(--ISNUMBER(SEARCH({1,2,3,4,5,6,7,8,9,0},MID(H34,(SEARCH(" E ",H34)-1),1))))+SUM(--ISNUMBER(SEARCH({1,2,3,4,5,6,7,8,9,0},MID(H34,(SEARCH(" E ",H34)+3),1))))=2,"",IF(SUM(--ISNUMBER(SEARCH({"Parte E","Apoquindo N"},H34)))>0,"",IF(OR(RIGHT(H34,3)=" NE",RIGHT(H34,3)=" NW",RIGHT(H34,3)=" SW",RIGHT(H34,3)=" SE",RIGHT(H34,2)=" N",RIGHT(H34,2)=" E",RIGHT(H34,2)=" W",RIGHT(H34,2)=" S",LEFT(H34,3)="NE ",LEFT(H34,3)="NW ",LEFT(H34,3)="SW ",LEFT(H34,3)="SE ",LEFT(H34,2)="N ",LEFT(H34,2)="E ",LEFT(H34,2)="W ",LEFT(H34,2)="S "),"Directional Check",IF(SUM(--ISNUMBER(SEARCH({" N "," E "," W "," S "," NE "," NW "," SW "," SE ","N.E","N.W","S.W","S.E","E.","N.","S.","W."},H34)))>0,"Directional Check",IF(SUM(--ISNUMBER(SEARCH({1,2,3,4,5,6,7,8,9,0},MID(H34,(SEARCH("nd ",H34)-1),1))))+SUM(--ISNUMBER(SEARCH({1,2,3,4,5,6,7,8,9,0},MID(H34,(SEARCH("rd ",H34)-1),1)))+SUM(--ISNUMBER(SEARCH({1,2,3,4,5,6,7,8,9,0},MID(H34,(SEARCH("st ",H34)-1),1))))+SUM(--ISNUMBER(SEARCH({1,2,3,4,5,6,7,8,9,0},MID(H34,(SEARCH("th ",H34)-1),1)))))>0,"","")))))} | AA34: =IF(IF(L34="US",IFERROR(VLOOKUP(J34,Country_Codes!$B:$B,1,0)=J34,"US State Code Error"),IF(L34="CA",IFERROR(VLOOKUP(J34,Country_Codes!$E:$E,1,0)=J34,"Canada State Code Error"),IF(L34="BR",IFERROR(VLOOKUP(J34,Country_Codes!$H:$H,1,0)=J34,"Brazil State Code Error"),IF(L34="AU",IFERROR(VLOOKUP(J34,Country_Codes!$K:$K,1,0)=J34,"Australia State Code Error"),""))))=TRUE,"",IF(L34="US",IFERROR(VLOOKUP(J34,Country_Codes!$B:$B,1,0)=J34,"US State Code Error"),IF(L34="CA",IFERROR(VLOOKUP(J34,Country_Codes!$E:$E,1,0)=J34,"Canada State Code Error"),IF(L34="BR",IFERROR(VLOOKUP(J34,Country_Codes!$H:$H,1,0)=J34,"Brazil State Code Error"),IF(L34="AU",IFERROR(VLOOKUP(J34,Country_Codes!$K:$K,1,0)=J34,"Australia State Code Error"),""))))) | AB34: =IF(OR(L34="US",L34="CA",L34="BR",L34="AU"),IF((EXACT(UPPER(J34),J34)),"","Country Code Casing"),IF(EXACT(J34,PROPER(J34)),"","Billing State casing")) | AC34: {=IFERROR(_xlfn.IFS(IF(AND(LEN(I34)=0,ISBLANK(I34)=FALSE),"",ISNUMBER(SEARCH(I34,H34))),"City/Postal Code/Country Found in Address",IF(AND(LEN(K34)=0,ISBLANK(K34)=FALSE),"",ISNUMBER(SEARCH(K34,H34))),"City/Postal Code/Country Found in Address",IF(AND(LEN(L34)=0,ISBLANK(L34)=FALSE),"",ISNUMBER(SEARCH(", "&L34,H34))),"City/Postal Code/Country Found in Address",IF(AND(LEN(J34)=0,ISBLANK(J34)=FALSE),"",ISNUMBER(SEARCH(", "&J34,H34))),"City/Postal Code/Country Found in Address",IF(AND(LEN(L34)=0,ISBLANK(L34)=FALSE),"",ISNUMBER(SEARCH(","&L34,H34))),"City/Postal Code/Country Found in Address",IF(AND(LEN(J34)=0,ISBLANK(J34)=FALSE),"",ISNUMBER(SEARCH(","&J34,H34))),"City/Postal Code/Country Found in Address"),"")} | AD34: =IF(ISNUMBER(SEARCH("PO",N34)),"PO# Entered in Tax ID Field","") | AE34: {=IFERROR(IF(VLOOKUP(LEFT(M34,MIN(SEARCH({1,2,3,4,5,6,7,8,9,0},M34&{1,2,3,4,5,6,7,8,9,0}))-1),Country_Codes!$N:$N,1,0)>0,"PO Number may be incorrect",""),"")} | AF34: =IF(N34="","",IF(EXACT(L34,LEFT(N34,2)),IF(EXACT(MID(N34,3,1)," "),"Check the Space inbetween County code & VAT",""),"Check the VAT Country Code Format")) | AG34: =IF((ISNUMBER(SEARCH("@",P34)))>0,"",IF(IF(--(ISNUMBER(SEARCH("'",P34)))>0,OR(EXACT(PROPER(P34),P34),EXACT((PROPER(LEFT(P34,FIND("'",P34)-2))&LOWER(MID(P34,FIND("'",P34)-1,1))&PROPER(MID(P34,FIND("'",P34)+0,LEN(P34)-FIND("'",P34)+1))),P34)),"Please check Billing Contact Casing")=TRUE,"","Please check Billing Contact casing")) | AH34: =IF(OR(L34="AS",L34="FM",L34="GU",L34="MH",L34="MP",L34="PW",L34="PR",L34="VI",L34="UM"),"US Territories Check","") | AI34: {=IF(G34="","",_xlfn.IFNA(_xlfn.IFS(L34=VLOOKUP(L34,Country_Codes!$M:$M,1,0)=TRUE,""),"Please check the country code"))} | AJ34: =IF(S34="","",S34&"; ")&IF(T34="","",T34&"; ")&IF(U34="","",U34&"; ")&IF(V34="","",V34&"; ")&IF(AF34="","",AF34&"; ")&IF(AG34="","",AG34&"; ")&IF(AH34="","",AH34&"; ")&IF(Z34="","",Z34&"; ")&IF(AA34="","",AA34&"; ")&IF(AB34="","",AB34&"; ")&IF(AC34="","",AC34&"; ")&IF(AD34="","",AD34&"; ")&IF(AE34="","",AE34&"; ")&IF(AI34="","",AI34&"; ")&IF(W34="","",W34&"; ")&IF(X34="","",X34&"; ")&IF(Y34="","",Y34&"; ") | AM34: =(COUNTA(S34:V34)-COUNTIFS((S34:V34),""))+(COUNTA(AB34)-COUNTIFS((AB34),""))+(COUNTA(AG34)-COUNTIFS((AG34),"")) -> 0 | AN34: =(COUNTA(W34)-COUNTIFS((W34),""))+(COUNTA(Z34)-COUNTIFS((Z34),"")) -> 0 | AO34: =(COUNTA(AA34)-COUNTIFS((AA34),""))+(COUNTA(AC34:AE34)-COUNTIFS((AC34:AE34),""))+(COUNTA(AH34:AI34)-COUNTIFS((AH34:AI34),"")) -> 0 | AP34: =(COUNTA(X34:Y34)-COUNTIFS((X34:Y34),""))+(COUNTA(AF34)-COUNTIFS((AF34),"")) -> 0 | AQ34: =SUM(AM34:AP34) -> 0 | AV34: 45461
